{"newsArray":[{"article_id":"574d0c91d21d933b5ba91a758fc035dd","title":"WATCH: Aussie star hits winning runs in the most alpha way possible","link":"https://www.theroar.com.au/cricket/video/watch-aussie-star-hits-winning-runs-in-the-most-alpha-way-possible-1382512/","keywords":["cricket"],"creator":["The Roar"],"video_url":null,"description":"HowтАЩs the tuck of the bat under the arm from Phoebe Litchfield too!","content":"ONLY AVAILABLE IN PAID PLANS","pubDate":"2024-09-19 16:03:58","pubDateTZ":"UTC","image_url":"https://cdn4.theroar.com.au/wp-content/uploads/2024/09/image-6362163489112-755x432.jpg","source_id":"theroar_au","source_priority":163462,"source_name":"The Roar","source_url":"https://www.theroar.com.au","source_icon":"https://i.bytvi.com/domain_icons/theroar_au.jpg","language":"english","country":["australia"],"category":["sports"],"ai_tag":"ONLY AVAILABLE IN PROFESSIONAL AND CORPORATE PLANS","sentiment":"ONLY AVAILABLE IN PROFESSIONAL AND CORPORATE PLANS","sentiment_stats":"ONLY AVAILABLE IN PROFESSIONAL AND CORPORATE PLANS","ai_region":"ONLY AVAILABLE IN CORPORATE PLANS","ai_org":"ONLY AVAILABLE IN CORPORATE PLANS","duplicate":false},{"article_id":"bb11755cc34281c39eb9de35e7dab4e9","title":"Yashasvi Jaiswal: ржнрж╛рж░ржд ржнрж╛рж▓ ржЬрж╛ржпрж╝ржЧрж╛ржпрж╝ рж░ржпрж╝рзЗржЫрзЗ, ржмрж╛ржВрж▓рж╛ржжрзЗрж╢ржХрзЗ рж╣рзБржБрж╢рж┐ржпрж╝рж╛рж░рж┐ ржжрж┐ржпрж╝рзЗ рж░рж╛ржЦрж▓рзЗржи ржпрж╢рж╕рзНржмрзА","link":"https://bengali.abplive.com/sports/cricket/ind-vs-ban-chennai-test-yashasvi-jaiswal-has-no-complaints-about-pace-friendly-chepauk-conditions-1096274","keywords":["ржХрзНрж░рж┐ржХрзЗржЯ"],"creator":["ABP Ananda"],"video_url":null,"description":"ржЪрзЗржирзНржирж╛ржЗ: ржмрж╛ржВрж▓рж╛ржжрзЗрж╢рзЗрж░ ржкрзЗрж╕рж╛рж░ рж╣рж╛рж╕рж╛ржи ржорж╛рж╣ржорзБржжрзЗрж░ рж╕рзНржпрзБржЗржВржпрж╝рзЗрж░ ржмрж┐рж╖рзЗ рждржЦржи ржнрж╛рж░рждрзАржпрж╝ ржмрзНржпрж╛ржЯрж┐ржВржпрж╝рзЗрж░ ржкрзНрж░рж╛ржг ржУрж╖рзНржарж╛ржЧрждред рж░рзЗрж╛рж╣рж┐ржд рж╢рж░рзНржорж╛ ржерзЗржХрзЗ рж╢рзБрж░рзБ ржХрж░рзЗ ржмрж┐рж░рж╛ржЯ ржХрзЗрж╛рж╣рж▓рж┐, ржПржХрзЗрж░ ржкрж░ ржПржХ рж░ржерзА ржорж╣рж╛рж░ржерзАрж░рж╛ ржкрзНржпрж╛ржнрж┐рж▓рж┐ржпрж╝ржирзЗред ржЪрзЗржирзНржирж╛ржЗржпрж╝рзЗ ржЪрж╛ржкрзЗрж░ ржорзБржЦрзЗ рждрж┐ржирж┐ ржХрж╛рж░рзНржпржд ржПржХрж╛ржЗ ржмрзБржХ ржЪрж┐рждрж┐ржпрж╝рзЗ рж▓ржбрж╝рж╛ржЗ ржХрж░рж▓рзЗржи ржкрзНрж░ржержо рж╕рзЗрж╢ржирзЗред рждрж┐ржирж┐, ржпрж╢рж╕рзНржмрзА ржЬржпрж╝рж╕ржУржпрж╝рж╛рж▓ (Yashasvi Jaiswal)ред рж░рзЗрж╛рж╣рж┐ржд рж╢рж░рзНржорж╛рж░ рж╕ржЩрзНржЧрзЗ ржЗржирж┐ржВрж╕ ржУржкрзЗржи ржХрж░рждрзЗ ржирзЗржорзЗ ржмрзГрж╣рж╕рзНржкрждрж┐ржмрж╛рж░ ржпрж┐ржирж┐ рззрззрзо ржмрж▓рзЗ рзлрзм рж░рж╛ржирзЗрж░ ржЗржирж┐ржВрж╕ ржЦрзЗрж▓рж▓рзЗржиредржкрзНрж░ржержо ржжрж┐ржирзЗрж░ рж╢рзЗрж╖рзЗ ржЖрж░ ржЕрж╢рзНржмрж┐ржи, рж░ржмрзАржирзНржжрзНрж░ ржЬрж╛ржбрзЗржЬрж╛рж░ ржкрж╛рж░рзНржЯржирж╛рж░рж╢рж┐ржкрзЗ ржнрж╛рж▓ ржЬрж╛ржпрж╝ржЧрж╛ржпрж╝ ржкрзЗрзЧржБржЫрзЗ ржЧрж┐ржпрж╝рзЗржЫрзЗ ржнрж╛рж░рждред ржЕржмрж┐ржЪрзНржЫрзЗржжрзНржп рж╕ржкрзНрждржо ржЙржЗржХрзЗржЯрзЗ рззрзпрзл рж░рж╛ржи ржпрзЗрж╛ржЧ ржХрж░рзЗржЫрзЗржи ржжрзБржЬржирзЗ (India vs Bangladesh)ред ржпржжрж┐ржУ ржкрж╛рж▓рзНржЯрж╛ рж▓ржбрж╝рж╛ржЗржпрж╝рзЗрж░ рж╢рзБрж░рзБржЯрж╛ рж╣ржпрж╝рзЗржЫрж┐рж▓ ржпрж╢рж╕рзНржмрзАрж░ ржмрзНржпрж╛ржЯрзЗржЗред ржШрж░рзЗрж░ ржорж╛ржарзЗ ржмржЫрж░рзЗрж░ ржЧрзЗрж╛ржбрж╝рж╛ржпрж╝ ржЗржВрж▓рзНржпрж╛ржирзНржбрзЗрж░ ржмрж┐рж░рзБржжрзНржзрзЗ ржЯрзЗрж╕рзНржЯ рж╕рж┐рж░рж┐ржЬрзЗ рж╕рж╛рждрж╢рзЗрж╛рж░ ржУржкрж░ рж░рж╛ржи ржХрж░рзЗ рж╕рзБржирзАрж▓ ржЧрж╛ржУрж╕рзНржХрж░рзЗрж░ рж░рзЗржХрж░рзНржб рж╕рзНржкрж░рзНрж╢ ржХрж░рзЗржЫрж┐рж▓рзЗржиред ржмрж╛ржВрж▓рж╛ржжрзЗрж╢рзЗрж░ ржмрж┐рж░рзБржжрзНржзрзЗржУ ржмрзНржпрж╛ржЯ рж╣рж╛рждрзЗ рж╕ржкрзНрж░рждрж┐ржн ржпрж╢рж╕рзНржмрзАредржХрзАржнрж╛ржмрзЗ ржмрж╛ржВрж▓рж╛ржжрзЗрж╢рзЗрж░ ржкрзЗрж╕ ржмрзЗрж╛рж▓рж┐ржВржпрж╝рзЗрж░ ржЭрж╛ржБржЭ рж╕рж╛ржорж▓рж╛рж▓рзЗржи? ржпрзЗржЦрж╛ржирзЗ ржмрж┐рж░рж╛ржЯ ржХрзЗрж╛рж╣рж▓рж┐ ржкрж░рзНржпржирзНржд ржЕржлрж╕рзНржЯрж╛ржорзНржкрзЗрж░ ржмрж╛ржЗрж░рзЗрж░ ржмрж▓рзЗ ржкрж╛рждрж╛ ржлрж╛ржБржжрзЗ ржкрж╛ ржжрж┐ржпрж╝рзЗ ржбрзНрж░рзЗрж╕рж┐ржВрж░рзБржорзЗ ржлрж┐рж░рзЗ ржЧрзЗрж▓рзЗржи? ржкрзНрж░ржержо ржжрж┐ржирзЗрж░ ржЦрзЗрж▓рж╛рж░ рж╢рзЗрж╖рзЗ рж╕рж╛ржВржмрж╛ржжрж┐ржХ ржмрзИржаржХрзЗ ржпрж╢рж╕рзНржмрзА ржмрж▓рзЗржи, 'ржПржЗ ржкрж░рж┐ржмрзЗрж╢, ржкрж░рж┐рж╕рзНржерж┐рждрж┐рждрзЗ ржмрзНржпрж╛ржЯ ржХрж░рждрзЗ ржирзЗржорзЗ ржжрж╛рж░рзБржг ржЕржнрж┐ржЬрзНржЮрждрж╛ рж╣рж▓ред ржПржЗ ржкрж░рж┐рж╕рзНржерж┐рждрж┐ ржЖржорж╛ржХрзЗ ржЖрж░ржУ рж╢ржХрзНрждрж┐рж╢рж╛рж▓рзА ржХрж░рзЗржЫрзЗред ржПржЗ ржзрж░ржирзЗрж░ ржкрж░рж┐рж╕рзНржерж┐рждрж┐рждрзЗ ржХрзАржнрж╛ржмрзЗ ржЦрзЗрж▓рж╛ ржжрж░ржХрж╛рж░, рждрж╛ ржирж┐ржпрж╝рзЗ ржЕржирзЗржХ ржХрж┐ржЫрзБ рж╢рж┐ржЦрж▓рж╛ржоред ржХрзАржнрж╛ржмрзЗ ржкрж░рж┐ржХрж▓рзНржкржирж╛ ржХрж░рзЗ ржЗржирж┐ржВрж╕ ржПржЧрж┐ржпрж╝рзЗ ржирж┐ржпрж╝рзЗ ржпрж╛ржУржпрж╝рж╛ ржпрж╛ржпрж╝, рж╕рзЗржЯрж╛ржУ рж╢рж┐ржЦрж▓рж╛ржоред'ржЖрж░ржУ ржкржбрж╝рзБржи: рж╕ржорж╛ржЬрзЗрж░ ржорж╣рж┐рж╖рж╛рж╕рзБрж░рзЗрж░рж╛ ржирж┐ржкрж╛ржд ржпрж╛ржХ, ржкрзНрж░рж╛рж░рзНржержирж╛ржпрж╝ ржмрж┐рж╢рзЗрж╖ ржЕржирзБрж╖рзНржарж╛ржи ржХрж░ржЫрзЗржи ржбрзЗрж╛ржирж╛ржпрж╢рж╕рзНржмрзА ржЖрж░ржУ ржмрж▓рзЗржи, 'ржЖржорж┐ ржжрж▓рзЗрж░ ржкрзНрж░ржпрж╝рзЗрж╛ржЬржи ржЕржирзБржпрж╛ржпрж╝рзА ржЦрзЗрж▓рж╛рж░ ржЪрзЗрж╖рзНржЯрж╛ ржХрж░рзЗржЫрж┐ред рж╕рзЗржЗ ржорждрзЗрж╛ ржирж┐ржЬрзЗрж░ ржЦрзЗрж▓рж╛ ржкрж╛рж▓рзНржЯрзЗржЫрж┐ред рж╢рзБрж░рзБрждрзЗ ржЙржЗржХрзЗржЯ ржкржбрж╝рж▓рзЗ ржЖржорж┐ ржХрзАржнрж╛ржмрзЗ ржмрзНржпрж╛ржЯрж┐ржВ ржХрж░ржм? ржпржЦржи рж░рж╛ржи ржЖрж╕ржЫрзЗ, ржХрзАржнрж╛ржмрзЗ ржмрзНржпрж╛ржЯрж┐ржВ ржХрж░ржм?'ржЯрзЗрж╕рзНржЯрзЗ ржкржЮрзНржЪржо рж╣рж╛ржлрж╕рзЗржЮрзНржЪрзБрж░рж┐ ржХрж░рзЗржЫрзЗржи ржпрж╢рж╕рзНржмрзАред рждржмрзЗ ржЗржВрж▓рзНржпрж╛ржирзНржбрзЗрж░ ржмрж┐рж░рзБржжрзНржзрзЗ ржпрзЗржнрж╛ржмрзЗ ржЖржЧрзНрж░рж╛рж╕рзА ржмрзНржпрж╛ржЯрж┐ржВ ржХрж░рзЗржЫрж┐рж▓рзЗржи, ржмрж╛ржВрж▓рж╛ржжрзЗрж╢рзЗрж░ ржмрж┐рж░рзБржжрзНржзрзЗ ржЪрзЗржирзНржирж╛ржЗржпрж╝рзЗ рж╕рзЗржнрж╛ржмрзЗ ржмрзНржпрж╛ржЯрж┐ржВ ржХрж░рзЗржиржирж┐ред ржмрж░ржВ ржЕржирзЗржХ рж╕рждрж░рзНржХ ржжрзЗржЦрж┐ржпрж╝рзЗржЫрзЗ ржорзБржорзНржмржЗржпрж╝рзЗрж░ ржмрзНржпрж╛ржЯрж╛рж░ржХрзЗред ржкржЮрзНржЪрж╛рж╢рзЗрж░ ржХржо рж╕рзНржЯрзНрж░ржЗржХ рж░рзЗржЯ рж░рзЗржЦрзЗ рж░рж╛ржи ржХрж░рзЗржЫрзЗржиредржжрзНржмрж┐рждрзАржпрж╝ рж╕рзЗрж╢ржирзЗ ржирж╛рж╣рж┐ржж рж░рж╛ржирж╛рж░ ржЪржХрж┐ржд ржмрж╛ржЙржирзНрж╕рж╛рж░рзЗ рждрж┐ржирж┐ ржЖржЙржЯ рж╣ржиред ржпржжрж┐ржУ ржнрж╛рж░ржд ржнрж╛рж▓ ржЬрж╛ржпрж╝ржЧрж╛ржпрж╝ ржЖржЫрзЗ ржмрж▓рзЗржЗ ржоржирзЗ ржХрж░рзЗржи ржпрж╢рж╕рзНржмрзАред ржмрж▓рзЗржЫрзЗржи, 'рж╢рзБрж░рзБрж░ ржжрж┐ржХрзЗ ржкрж┐ржЪрзЗ ржкржбрж╝рзЗ ржмрж▓ ржирзАржЪрзБ рж╣ржЪрзНржЫрж┐рж▓, ржиржбрж╝рж╛ржЪржбрж╝рж╛ ржХрж░ржЫрж┐рж▓ред рждрж╛ржЗ ржЖржорж░рж╛ рж╕ржоржпрж╝ ржирж┐ржпрж╝рзЗ ржЦрзЗрж▓ржЫрж┐рж▓рж╛ржоред рждржмрзЗ рж╢рзЗрж╖ рж╕рзЗрж╢ржирзЗ ржнрж╛рж▓ ржЧрждрж┐рждрзЗ рж░рж╛ржи ржЙржарзЗржЫрзЗред ржПржЗ ржорзБрж╣рзВрж░рзНрждрзЗ ржЖржорж░рж╛ ржнрж╛рж▓ ржЬрж╛ржпрж╝ржЧрж╛ржпрж╝ рж░ржпрж╝рзЗржЫрж┐ред'ржЖрж░ржУ ржкржбрж╝рзБржи: ржЖрж░ ржЬрж┐ ржХрж░ ржХрж╛ржгрзНржбрзЗ ржХрзБрж░рзБржЪрж┐ржХрж░ ржнрж╛рж╖рж╛ржпрж╝ ржЖржХрзНрж░ржоржг, рж╕рж╛ржЗржмрж╛рж░ ржХрзНрж░рж╛ржЗржо рж╢рж╛ржЦрж╛ржпрж╝ ржЕржнрж┐ржпрзЗрж╛ржЧ рж╕рзЗрзЧрж░ржнрзЗрж░ржЖржкржирж╛рж░ ржкржЫржирзНржжрзЗрж░ ржЦржмрж░ ржЖрж░ ржЖржкржбрзЗржЯ ржкрж╛ржмрзЗржи ржЖржкржирж╛рж░ ржкржЫржирзНржжрзЗрж░ ржЪрзНржпрж╛ржЯрж┐ржВ ржкрзНрж▓рзНржпрж╛ржЯржлрж░рзНржо рж╣рзЗрж╛ржпрж╝рж╛ржЯрж╕ ржЕрзНржпрж╛ржкрзЗржУред ржпрзБржХрзНржд рж╣рзЗрж╛ржи ABP Ananda рж╣рзЗрж╛ржпрж╝рж╛ржЯрж╕ ржЕрзНржпрж╛ржк ржЪрзНржпрж╛ржирзЗрж▓рзЗред","content":"ONLY AVAILABLE IN PAID PLANS","pubDate":"2024-09-19 16:03:31","pubDateTZ":"UTC","image_url":"https://feeds.abplive.com/onecms/images/uploaded-images/2024/09/19/bc22ea7663385fad4cf3ac88d4567bbb172676008002450_original.jpg","source_id":"abplive","source_priority":7754,"source_name":"Abp News","source_url":"http://abplive.com","source_icon":"https://i.bytvi.com/domain_icons/abplive.jpg","language":"bengali","country":["india"],"category":["sports"],"ai_tag":"ONLY AVAILABLE IN PROFESSIONAL AND CORPORATE PLANS","sentiment":"ONLY AVAILABLE IN PROFESSIONAL AND CORPORATE PLANS","sentiment_stats":"ONLY AVAILABLE IN PROFESSIONAL AND CORPORATE PLANS","ai_region":"ONLY AVAILABLE IN CORPORATE PLANS","ai_org":"ONLY AVAILABLE IN CORPORATE PLANS","duplicate":false},{"article_id":"039a585fe6e294a7ee804eaa8cbe0bcd","title":"WATCH: Sarfaraz Ahmed Sledges Babar Azam, Pakistan Captain Scores Century In Reply During Champions Cup","link":"https://zeenews.india.com/cricket/watch-sarfaraz-ahmed-sledges-babar-azam-pakistan-captain-scores-century-in-reply-during-champions-cup-2795727.html","keywords":null,"creator":["Zee News"],"video_url":null,"description":"Babar Azam scored a century in the Champions Cup after Sarfaraz Ahmed sledged him during the game.","content":"ONLY AVAILABLE IN PAID PLANS","pubDate":"2024-09-19 16:03:00","pubDateTZ":"UTC","image_url":"https://english.cdn.zeenews.com/sites/default/files/styles/zm_700x400/public/2024/09/19/1516746-ind-8.png?im=Resize%3D%28400%29","source_id":"zeenews","source_priority":5319,"source_name":"Zee News","source_url":"http://zeenews.india.com","source_icon":"https://i.bytvi.com/domain_icons/zeenews.png","language":"english","country":["india"],"category":["sports"],"ai_tag":"ONLY AVAILABLE IN PROFESSIONAL AND CORPORATE PLANS","sentiment":"ONLY AVAILABLE IN PROFESSIONAL AND CORPORATE PLANS","sentiment_stats":"ONLY AVAILABLE IN PROFESSIONAL AND CORPORATE PLANS","ai_region":"ONLY AVAILABLE IN CORPORATE PLANS","ai_org":"ONLY AVAILABLE IN CORPORATE PLANS","duplicate":false},{"article_id":"ecc0bc8e7a1bd92f220daa521e76ed98","title":"IND vs BAN: 'рдЪреАрддреЗ рдХреА рдЪрд╛рд▓, рдмрд╛рдЬ рдХреА рдирдЬрд░ рдФрд░ рдЬрдбреНрдбреВ рдХреА..' рдЬрдбреЗрдЬрд╛ рдХреА рддрд╛рд░реАрдл рдореЗрдВ рд╢рд╛рдпрд░ рдмрдиреЗ рд╕реВрд░реНрдпрд╛, рдлреИрдВрд╕ рдХрд░ рд░рд╣реЗ рд╡рд╛рд╣-рд╡рд╛рд╣","link":"https://zeenews.india.com/hindi/sports/cricket/suryakumar-yadav-unique-way-to-praised-r-ashwin-century-ravindra-jadeja-ind-vs-ban-1st-test/2437929","keywords":null,"creator":["Zee News рд╣рд┐рдиреНрджреА","Zee News Hindi"],"video_url":null,"description":"India vs Bangladesh: рдЬрдбреЗрдЬрд╛-рдЕрд╢реНрд╡рд┐рди рдХреА рдЬреЛрдбрд╝реА рдХреА рджрд╣рд╢рдд рджреБрдирд┐рдпрд╛рднрд░ рдХреА рдЯреАрдореЛрдВ рдореЗрдВ рд╣реИ. рджреЛрдиреЛрдВ рджрд┐рдЧреНрдЧрдЬреЛрдВ рдиреЗ рдЕрдкрдиреА рдлрд┐рд░рдХреА рд╕реЗ рдХрдИ рдмрдбрд╝реЗ рдзреБрд░рдВрдзрд░реЛрдВ рдХреЛ рдЪрд╛рд░реЛ рдЦрд╛рдиреЗ рдЪрд┐рдд рдХрд░ рджрд┐рдпрд╛. рд▓реЗрдХрд┐рди 19 рд╕рд┐рддрдВрдмрд░ рдХреЛ рдпреЗ рдЬреЛрдбрд╝реА рдмрд▓реНрд▓реЗ рд╕реЗ рд░рдВрдЧ рдЬрдорд╛рддреА рдирдЬрд░ рдЖрдИ. рд╡рд┐рд░рд╛рдЯ-рд░реЛрд╣рд┐рдд рдХреЗ рд╡рд┐рдХреЗрдЯ рдХреЗ рдмрд╛рдж рдЬреАрдд рдХреЗ рд╕рдкрдиреЗ рджреЗрдЦрдиреЗ рд▓рдЧреА рдмрд╛рдВрдЧреНрд▓рд╛рджреЗрд╢ рдХреЛ рдЕрд╢реНрд╡рд┐рди-рдЬрдбреЗрдЬрд╛ рдиреЗ рдирд╛рдХреЛ рдЪрдиреЗ рдЪрдмрд╡рд╛ рджрд┐рдП. рдЬрд┐рд╕рдХреЗ рдмрд╛рдж рд╕реВрд░реНрдпрд╛ рдХреА рдЬреБрдмрд╛рдВ рд╕реЗ рднреА рд╢рд╛рдпрд░реА рдирд┐рдХрд▓рдиреЗ рд▓рдЧреА.","content":"ONLY AVAILABLE IN PAID PLANS","pubDate":"2024-09-19 16:00:12","pubDateTZ":"UTC","image_url":"https://hindi.cdn.zeenews.com/hindi/sites/default/files/2024/09/19/3246715-ashwin-and-jadeja.png?im=FitAndFill%3D%281200%2C900%29","source_id":"zeenews","source_priority":5319,"source_name":"Zee News","source_url":"http://zeenews.india.com","source_icon":"https://i.bytvi.com/domain_icons/zeenews.png","language":"hindi","country":["india"],"category":["sports"],"ai_tag":"ONLY AVAILABLE IN PROFESSIONAL AND CORPORATE PLANS","sentiment":"ONLY AVAILABLE IN PROFESSIONAL AND CORPORATE PLANS","sentiment_stats":"ONLY AVAILABLE IN PROFESSIONAL AND CORPORATE PLANS","ai_region":"ONLY AVAILABLE IN CORPORATE PLANS","ai_org":"ONLY AVAILABLE IN CORPORATE PLANS","duplicate":false},{"article_id":"03c43ad6ab1b6f73df5795430c67387f","title":"Shreyas Iyer goes for duck again, Sanju Samson quick fires with 89 against India B in Duleep Trophy 2024","link":"https://www.india.com/sports/shreyas-iyer-goes-for-duck-again-sanju-samson-quick-fires-with-89-against-india-b-in-duleep-trophy-2024-7259900/","keywords":["ks bharat","mukesh kumar","sanju samson","duleep trophy 2024","rahul chahar","shreyas iyer","sports","cricket","ricky bhui","devdutt padikkal","navdeep saini"],"creator":null,"video_url":null,"description":"Indian wicketkeeper-batter Sanju Samson rescued India D with a brilliant unbeaten fifty against India B in the Duleep Trophy 2024 final-round fixtures on Thursday.","content":"ONLY AVAILABLE IN PAID PLANS","pubDate":"2024-09-19 15:59:59","pubDateTZ":"UTC","image_url":"https://static.india.com/wp-content/themes/icom/images/default-big.svg","source_id":"india","source_priority":8067,"source_name":"India","source_url":"https://www.india.com","source_icon":"https://i.bytvi.com/domain_icons/india.png","language":"english","country":["india"],"category":["sports"],"ai_tag":"ONLY AVAILABLE IN PROFESSIONAL AND CORPORATE PLANS","sentiment":"ONLY AVAILABLE IN PROFESSIONAL AND CORPORATE PLANS","sentiment_stats":"ONLY AVAILABLE IN PROFESSIONAL AND CORPORATE PLANS","ai_region":"ONLY AVAILABLE IN CORPORATE PLANS","ai_org":"ONLY AVAILABLE IN CORPORATE PLANS","duplicate":false},{"article_id":"af0b6e1ff6e4a3df5e3e24c09c42467e","title":"тАШркдрлЗркирлЗ 40 ркУрк╡рк░ рк░ркорк╡рк╛ ркжрлЛтАЩ ... рк╕рк░рклрк░рк╛ркЭ ркЕрк╣рлЗркоркжрлЗ ркХрк░рлНркпрлЛ ркЯрлНрк░рлЛрк▓ ркЕркирлЗ ркмрк╛ркмрк░ ркЖркЭркорлЗ рклркЯркХрк╛рк░рлА 30ркорлА рк╕ркжрлА","link":"https://tv9gujarati.com/sports/cricket-news/sarfaraz-ahmed-troll-babar-azam-hit-list-a-century-in-champions-odi-cup-pakistan-1094074.html","keywords":["рк╕рлНрккрлЛрк░рлНркЯрк╕ ркирлНркпрлВркЭ","ркХрлНрк░рк┐ркХрлЗркЯ ркирлНркпрлВркЭ"],"creator":["Smit Chauhan"],"video_url":null,"description":"ркмрк╛ркмрк░ ркЖркЭрко ркЪрлЗркорлНрккрк┐ркпркирлНрк╕ ркХрккркорк╛ркВ рк╕рк╛рк░рлА ркИркирк┐ркВркЧ рк░ркорлА рк░рк╣рлНркпрлЛ ркЫрлЗ ркЕркирлЗ рк╣рк╡рлЗ ркдрлЗркгрлЗ рк╕ркжрлА рккркг рклркЯркХрк╛рк░рлА ркЫрлЗ. ркмрк╛ркмрк░ ркЖркЭркорлЗ ркдрлЗркирлА 30ркорлА рк▓рк┐рк╕рлНркЯ A рк╕ркжрлА рклркЯркХрк╛рк░рлА рк╣ркдрлА. ркЬрлЛ ркХрлЗ ркдрлЗркирлА рк╕ркжрлА ркжрк░ркорк┐ркпрк╛рки рккрк╛ркХрк┐рк╕рлНркдрк╛ркиркирк╛ рккрлВрк░рлНрк╡ ркХрлЗрккрлНркЯрки рк╕рк░рклрк░рк╛ркЭ ркЕрк╣рлЗркоркжрлЗ ркдрлЗркирлЗ ркЯрлНрк░рлЛрк▓ ркХрк░рк╡рк╛ркирлЛ рккрлНрк░ркпрк╛рк╕ ркХрк░рлНркпрлЛ рк╣ркдрлЛ.","content":"ONLY AVAILABLE IN PAID PLANS","pubDate":"2024-09-19 15:58:40","pubDateTZ":"UTC","image_url":"https://images.tv9gujarati.com/wp-content/uploads/2024/09/Babar-Azam-2.jpg?w=1280","source_id":"tv9gujarati","source_priority":75214,"source_name":"Tv9 Gujarati","source_url":"https://tv9gujarati.com","source_icon":"https://i.bytvi.com/domain_icons/tv9gujarati.jpg","language":"gujarati","country":["india"],"category":["sports"],"ai_tag":"ONLY AVAILABLE IN PROFESSIONAL AND CORPORATE PLANS","sentiment":"ONLY AVAILABLE IN PROFESSIONAL AND CORPORATE PLANS","sentiment_stats":"ONLY AVAILABLE IN PROFESSIONAL AND CORPORATE PLANS","ai_region":"ONLY AVAILABLE IN CORPORATE PLANS","ai_org":"ONLY AVAILABLE IN CORPORATE PLANS","duplicate":false},{"article_id":"b3c4604cbc6f7ee9f4346eccf4c4ff36","title":"IND vs BAN 1st Test: ржЕрж╢рзНржмрж┐ржи-ржЬрж╛ржбрзЗржЬрж╛ржпрж╝ ржорзБржЧрзНржз рж╕ржЪрж┐ржи, рждрж╛рж░ржХрж╛ ржЕрж▓рж░рж╛ржЙржирзНржбрж╛рж░ржжрзЗрж░ ржнрзВржпрж╝рж╕рзА ржкрзНрж░рж╢ржВрж╕рж╛ржпрж╝ ржнрж░рж╛рж▓рзЗржи 'ржорж╛рж╕рзНржЯрж╛рж░ ржмрзНрж▓рж╛рж╕рзНржЯрж╛рж░'","link":"https://bengali.abplive.com/sports/cricket/r-ashwin-ravindra-jadeja-brillant-partnership-rescues-ind-vs-ban-1st-test-sachin-tendulkar-lauds-1096273","keywords":["ржХрзНрж░рж┐ржХрзЗржЯ"],"creator":["ABP Ananda"],"video_url":null,"description":"ржЪрзЗржирзНржирж╛ржЗ: ржмрж╛ржВрж▓рж╛ржжрзЗрж╢рзЗрж░ ржЪрзЗржирзНржирж╛ржЗржпрж╝рзЗ ржкрзНрж░ржержо ржЯрзЗрж╕рзНржЯрзЗ (IND vs BAN 1st Test) рждрж░рзБржг ржлрж╛рж╕рзНржЯ ржмрзЗрж╛рж▓рж╛рж░ржжрзЗрж░ ржмрж┐рж░рзБржжрзНржзрзЗ ржПржХрзЗ ржПржХрзЗ ржпржЦржи ржЯрж┐ржо ржЗржирзНржбрж┐ржпрж╝рж╛рж░ ржорж╣рж╛рждрж╛рж░ржХрж╛рж░рж╛ рж╕рж╛ржЬржШрж░рзЗ ржлрж┐рж░рзЗ ржЧрж┐ржпрж╝рзЗржЫрзЗржи, ржпржЦржи ржЯрж┐ржо ржЗржирзНржбрж┐ржпрж╝рж╛ ржжрзБ'рж╢рзЗрж╛ рж░рж╛ржирзЗрж░ ржЧржгрзНржбрж┐ржУ ржкрж╛рж░ ржХрж░рждрзЗ ржкрж╛рж░ржмрзЗ ржХрж┐ ржирж╛, рж╕рзЗржЗ ржирж┐ржпрж╝рзЗ рж╕ржВрж╢ржпрж╝ рждрзИрж░рж┐ рж╣ржпрж╝рзЗржЫрж┐рж▓, рждржЦржиржЗ ржмрзНржпрж╛ржЯ рж╣рж╛рждрзЗ рж░рзБржЦрзЗ ржжрж╛ржБржбрж╝рж╛ржи ржжрзБржЗ ржЕрж▓рж░рж╛ржЙржирзНржбрж╛рж░ред рж░ржмрзАржирзНржжрзНрж░ ржЬрж╛ржбрзЗржЬрж╛ (Ravindra Jadeja) ржУ ржЖрж░ ржЕрж╢рзНржмрж┐ржи (R Ashwin) ржнрж╛рж░рждржХрзЗ ржжрзБ'рж╢рзЗрж╛ ржкрж╛рж░ ржХрж░рж╛ржирзЗрж╛ ржиржпрж╝, ржкрзНрж░ржержо ржжрж┐ржирзЗрж░ ржЦрзЗрж▓рж╛рж╢рзЗрж╖рзЗ рзйрзлрзж рж░рж╛ржирзЗрж░ ржжрзЗрж╛рж░ржЧрзЗрж╛ржбрж╝рж╛ржпрж╝ ржкрзЗрзЧржБржЫрзЗ ржжрж┐рж▓рзЗржиред ржЬрзБржбрж╝рж▓рзЗржи рззрзпрзл рж░рж╛ржиредржжрж┐ржирж╢рзЗрж╖рзЗ ржжрзБржЗ рждрж╛рж░ржХрж╛ржЗ ржХрж┐ржирзНрждрзБ ржЕржкрж░рж╛ржЬрж┐ржд рж░ржпрж╝рзЗржЫрзЗржиред ржЕрж╢рзНржмрж┐ржирзЗрж░ рж╕ржВржЧрзНрж░рж╣ рззрзжрзи, ржЬрж╛ржбрзЗржЬрж╛рж░ ржЭрзБрж▓рж┐рждрзЗ рзорзм рж░рж╛ржиред ржжрзБржЗ рждрж╛рж░ржХрж╛рж░ рззрзпрзл рж░рж╛ржи рж╕ржкрзНрждржо ржЙржЗржХрзЗржЯрзЗ ржЪрж┐ржкржХрзЗ рж╕рж░рзНржмржХрж╛рж▓рзАржи рж░рзЗржХрж░рзНржбред рждрж╛ржБрж░рж╛ ржХрж╛рж▓ ржХрж┐ржирзНрждрзБ ржирж┐ржЬрзЗржжрзЗрж░ ржПржЗ рж╕рзНржорж░ржгрзАржпрж╝ ржкрж╛рж░рзНржЯржирж╛рж░рж╢рж┐ржкржХрзЗ ржЖрж░ржУ ржмрж╛ржбрж╝рж╛рждрзЗ ржкрж╛рж░рзЗржиред ржЕрж╢рзНржмрж┐ржи ржУ ржЬрж╛ржбрзЗржЬрж╛рж░ ржПржЗ ржкрж╛рж░рзНржЯржирж╛рж░рж╢рж┐ржк ржЫрж╛ржбрж╝рж╛ ржнрж╛рж░рждрзАржпрж╝ ржжрж▓ ржпрзЗ ржмрж┐рж░рж╛ржЯ ржмрж┐ржкрж╛ржХрзЗ ржкржбрж╝ржд, рждрж╛ ржмрж▓рж╛рж░ ржЕржмржХрж╛рж╢ рж░рж╛ржЦрзЗ ржирж╛редржжрзБржЗ ржЕржнрж┐ржЬрзНржЮ рждрж╛рж░ржХрж╛рж░ ржмрзНржпрж╛ржЯрж┐ржВржпрж╝рзЗ ржорзБржЧрзНржз рж╕рзНржмржпрж╝ржВ 'ржХрзНрж░рж┐ржХрзЗржЯ ржИрж╢рзНржмрж░'ржУред ржкрзНрж░ржержо ржжрж┐ржирзЗрж░ ржЦрзЗрж▓рж╛рж╢рзЗрж╖рзЗ рж╕ржЪрж┐ржи рждрзЗржирзНржбрзБрж▓ржХрж░ (Sachin Tendulkar) ржирж┐ржЬрзЗрж░ рж╕рзЗрж╛рж╢рзНржпрж╛рж▓ ржорж┐ржбрж┐ржпрж╝рж╛ржпрж╝ ржЬрж╛ржбрзЗржЬрж╛ ржУ ржЕрж╢рзНржмрж┐ржирзЗрж░ ржкрзНрж░рж╢ржВрж╕рж╛ ржХрж░рзЗржиред 'ржорж╛рж╕рзНржЯрж╛рж░ ржмрзНрж▓рж╛рж╕рзНржЯрж╛рж░'-рж░ ржорждрзЗ ржжрзБржЗ рждрж╛рж░ржХрж╛ ржорзНржпрж╛ржЪрзЗ ржнрж╛рж░рждржХрзЗ ржПржЧрж┐ржпрж╝рзЗ ржжрж┐ржпрж╝рзЗржЫрзЗржиред рждрж┐ржирж┐ рж▓рзЗржЦрзЗржи, 'рж╣рждрж╛рж╢рж╛ ржерзЗржХрзЗ ржжрж╛ржкржЯред ржЕрж╢рзНржмрж┐ржи ржУ ржЬрж╛ржбрзЗржЬрж╛ ржжрзБрж░ржирзНржд ржЗржирж┐ржВрж╕ ржЖржмрж╛рж░ ржорзНржпрж╛ржЪрзЗрж░ ржорзЗрж╛ржбрж╝ ржнрж╛рж░рждрзЗрж░ ржжрж┐ржХрзЗ ржШрзБрж░рж┐ржпрж╝рзЗ ржжрж┐ржпрж╝рзЗржЫрзЗред ржПржЗ ржЕрж▓рж░рж╛ржЙржирзНржб ржжржХрзНрж╖рждрж╛ржЯрж╛ ржЕржкрж░рж┐рж╣рж╛рж░рзНржпред ржжрзБрж░ржирзНржд ржкрж╛рж░рзНржЯржирж╛рж░рж╢рж┐ржк ржЧржбрж╝рзЗржЫред' From despair to domination! @ashwinravi99 and @imjadeja's knocks have turned the tide for India once again. This all-round brilliance is invaluable. Super partnership boys. ЁЯСПЁЯП╝#INDvBAN pic.twitter.com/eZNW6yOr8VтАФ Sachin Tendulkar (@sachin_rt) September 19, 2024ржнрж╛рж░рждрзАржпрж╝ ржЯржк ржЕрж░рзНржбрж╛рж░рзЗ ржпрж╢рж╕рзНржмрзА ржЬржпрж╝рж╕ржУржпрж╝рж╛рж▓ рж╣рж╛ржлрж╕рзЗржЮрзНржЪрзБрж░рж┐ ржХрж░рж▓рзЗржУ, рж░рзЗрж╛рж╣рж┐рждрж░рж╛ рж╕ржорзНржкрзВрж░рзНржг ржмрзНржпрж░рзНржеред ржЬржпрж╝рж╕ржУржпрж╝рж╛рж▓ ржПржмржВ ржЛрж╖ржн ржкржирзНрже рж╣рж╛ржлрж╕рзЗржЮрзНржЪрзБрж░рж┐рж░ ржкрж╛рж░рзНржЯржирж╛рж░рж╢рж┐ржк ржЧржбрж╝рж▓рзЗржУ, ржкрж░ржкрж░ ржЙржЗржХрзЗржЯ рж╣рж╛рж░рж╛ржпрж╝ ржнрж╛рж░рждред ржХрзЗржПрж▓ рж░рж╛рж╣рзБрж▓ ржпржЦржи рззрзм рж░рж╛ржирзЗ рж╕рж╛ржЬржШрж░рзЗ ржлрзЗрж░рзЗржи рждржЦржи ржнрж╛рж░рждрзЗрж░ рж╕рзНржХрзЗрж╛рж░ ржЫржпрж╝ ржЙржЗржХрзЗржЯрзЗ рззрзкрзк рж░рж╛ржиред ржжрж┐ржирж╢рзЗрж╖рзЗ ржнрж╛рж░рждрзЗрж░ рж╕рзНржХрзЗрж╛рж░ ржЫржпрж╝ ржЙржЗржХрзЗржЯрзЗрж░ ржмрж┐ржирж┐ржоржпрж╝рзЗ рзйрзйрзп рж░рж╛ржиред ржЕрж╢рзНржмрж┐ржи ржПржХрзЗржмрж╛рж░рзЗржЗ рж╢рзБрж░рзБ ржерзЗржХрзЗ ржирзЗржорзЗ ржжрзБрж░ржирзНржд ржЖржЧрзНрж░рж╛рж╕рзА ржмрзНржпрж╛ржЯрж┐ржВ ржХрж░рзЗржиред ржирж┐ржЬрзЗрж░ рж╖рж╖рзНржа рж╢рждрж░рж╛ржи ржкрзВрж░ржг ржХрж░рзЗржи рждрж┐ржирж┐ред ржЬрж╛ржбрзЗржЬрж╛ржУ рж╕рзЗржЮрзНржЪрзБрж░рж┐ рж╣рж╛ржБржХрж╛рждрзЗ ржкрж╛рж░рзЗржи ржХрж┐ ржирж╛, рж╕рзЗржЯрж╛ржЗ ржжрзЗржЦрж╛рж░ ржмрж┐рж╖ржпрж╝ред ржЖржкржирж╛рж░ ржкржЫржирзНржжрзЗрж░ ржЦржмрж░ ржЖрж░ ржЖржкржбрзЗржЯ ржкрж╛ржмрзЗржи ржЖржкржирж╛рж░ ржкржЫржирзНржжрзЗрж░ ржЪрзНржпрж╛ржЯрж┐ржВ ржкрзНрж▓рзНржпрж╛ржЯржлрж░рзНржо рж╣рзЗрж╛ржпрж╝рж╛ржЯрж╕ ржЕрзНржпрж╛ржкрзЗржУред ржпрзБржХрзНржд рж╣рзЗрж╛ржи ABP Ananda рж╣рзЗрж╛ржпрж╝рж╛ржЯрж╕ ржЕрзНржпрж╛ржк ржЪрзНржпрж╛ржирзЗрж▓рзЗредржЖрж░ржУ ржкржбрж╝рзБржи: ржЯрзЗрж╕рзНржЯ ржЗрждрж┐рж╣рж╛рж╕рзЗ ржПрж░ ржЖржЧрзЗ ржХржЦржиржУ рж╣ржпрж╝ржирж┐, ржЪрзЗржирзНржирж╛ржЗржпрж╝рзЗ рж╣рж╛ржлрж╕рзЗржЮрзНржЪрзБрж░рж┐ рж╣рж╛ржБржХрж┐ржпрж╝рзЗ ржПржоржиржЗ ржХрзГрждрж┐рждрзНржм ржЧржбрж╝рж▓рзЗржи ржпрж╢рж╕рзНржмрзА","content":"ONLY AVAILABLE IN PAID PLANS","pubDate":"2024-09-19 15:58:08","pubDateTZ":"UTC","image_url":"https://feeds.abplive.com/onecms/images/uploaded-images/2024/09/19/471cd0b36a7eddb07d70faf378b059c91726761215705507_original.jpg","source_id":"abplive","source_priority":7754,"source_name":"Abp News","source_url":"http://abplive.com","source_icon":"https://i.bytvi.com/domain_icons/abplive.jpg","language":"bengali","country":["india"],"category":["sports"],"ai_tag":"ONLY AVAILABLE IN PROFESSIONAL AND CORPORATE PLANS","sentiment":"ONLY AVAILABLE IN PROFESSIONAL AND CORPORATE PLANS","sentiment_stats":"ONLY AVAILABLE IN PROFESSIONAL AND CORPORATE PLANS","ai_region":"ONLY AVAILABLE IN CORPORATE PLANS","ai_org":"ONLY AVAILABLE IN CORPORATE PLANS","duplicate":false},{"article_id":"79b613a0a4bf939547875a8ee86dbf40","title":"рдЪреЗрдиреНрдирдИ рдЯреЗрд╕реНрдЯ рдореЗрдВ рдЯреАрдо рдЗрдВрдбрд┐рдпрд╛ рдХреА рдЬреАрдд рдкрд╣рд▓реЗ рд╣реА рджрд┐рди рд╣реБрдИ рддрдп! рдорд┐рд▓ рдЧрдИ рдореБрдХрд╛рдмрд▓рд╛ рдирд╛ рд╣рд╛рд░рдиреЗ рдХреА рдЧрд╛рд░рдВрдЯреА","link":"https://www.tv9hindi.com/sports/cricket-news/team-india-never-lost-any-match-whenever-r-ashwin-has-scored-century-2839516.html","keywords":null,"creator":["TV9 Bharatvarsh"],"video_url":null,"description":"рдЪреЗрдиреНрдирдИ рдЯреЗрд╕реНрдЯ рдХреЗ рдкрд╣рд▓реЗ рджрд┐рди рдЯреАрдо рдЗрдВрдбрд┐рдпрд╛ рдиреЗ 6 рд╡рд┐рдХреЗрдЯ рдХреЗ рдиреБрдХрд╕рд╛рди рдкрд░ 339 рд░рди рдмрдирд╛рдП. рд░рд╡реАрдВрджреНрд░ рдЬрдбреЗрдЬрд╛ рдФрд░ рдЖрд░ рдЕрд╢реНрд╡рд┐рди рдХреА рдУрд░ рд╕реЗ рдХрдорд╛рд▓ рдХреА рдкрд╛рд░рд┐рдпрд╛рдВ рджреЗрдЦрдиреЗ рдХреЛ рдорд┐рд▓реА. рдпреЗ рджреЛрдиреЛрдВ рдмрд▓реНрд▓реЗрдмрд╛рдЬ рдЕрднреА рднреА рдирд╛рдмрд╛рдж рд╣реИрдВ рдФрд░ рдЦреЗрд▓ рдХреЗ рджреВрд╕рд░реЗ рджрд┐рди рдЯреАрдо рдХреЛ рдмрдбрд╝реЗ рд╕реНрдХреЛрд░ рддрдХ рдкрд╣реБрдВрдЪрд╛рдиреЗ рдХреЗ рд▓рд┐рдП рдореИрджрд╛рди рдкрд░ рдЙрддрд░реЗрдВрдЧреЗ.","content":"ONLY AVAILABLE IN PAID PLANS","pubDate":"2024-09-19 15:57:29","pubDateTZ":"UTC","image_url":"https://images.tv9hindi.com/wp-content/uploads/2024/09/r-ashwin-1.jpg","source_id":"tv9bharatvarsh","source_priority":40538658,"source_name":"Tv9 Bharatvarsh","source_url":"https://www.tv9hindi.com","source_icon":null,"language":"hindi","country":["india"],"category":["sports"],"ai_tag":"ONLY AVAILABLE IN PROFESSIONAL AND CORPORATE PLANS","sentiment":"ONLY AVAILABLE IN PROFESSIONAL AND CORPORATE PLANS","sentiment_stats":"ONLY AVAILABLE IN PROFESSIONAL AND CORPORATE PLANS","ai_region":"ONLY AVAILABLE IN CORPORATE PLANS","ai_org":"ONLY AVAILABLE IN CORPORATE PLANS","duplicate":false},{"article_id":"4e14361ad73be6754a94a6f1ea345ad2","title":"Bangladesh A complete T20 WC tune-up with series win in Sri Lanka","link":"https://www.thedailystar.net/sports/cricket/news/bangladesh-complete-t20-wc-tune-series-win-sri-lanka-3707241","keywords":null,"creator":null,"video_url":null,"description":"Bangladesh WomenтАЩs A team bowlers stood out in the final T20 of the five-match series against Sri Lankan A to help their side register an eight-wicket win and clinch a 4-1 series win at the Colts in Colombo today.","content":"ONLY AVAILABLE IN PAID PLANS","pubDate":"2024-09-19 15:55:06","pubDateTZ":"UTC","image_url":"https://www.thedailystar.net/sites/default/files/styles/big_202/public/images/2024/09/19/jdgklfk.jpg","source_id":"thedailystar","source_priority":32093,"source_name":"The Daily Star","source_url":"https://www.thedailystar.com","source_icon":"https://i.bytvi.com/domain_icons/thedailystar.png","language":"english","country":["bangladesh"],"category":["sports"],"ai_tag":"ONLY AVAILABLE IN PROFESSIONAL AND CORPORATE PLANS","sentiment":"ONLY AVAILABLE IN PROFESSIONAL AND CORPORATE PLANS","sentiment_stats":"ONLY AVAILABLE IN PROFESSIONAL AND CORPORATE PLANS","ai_region":"ONLY AVAILABLE IN CORPORATE PLANS","ai_org":"ONLY AVAILABLE IN CORPORATE PLANS","duplicate":false},{"article_id":"c1907499e505bfaa41dfe0f375440c9e","title":"IND vs BAN: ржмрж╛ржШ ржжрзЗржЦрж▓рзЗржЗ рж╢рж┐ржХрж╛рж░рзЗ ржмрзЗрж░рзЗрж╛ржи! ржЖржмрж╛рж░ржУ тАШрждрж▓рзЗрж╛ржпрж╝рж╛рж░-ржмрж╛ржЬрж┐тАЩ ржЬрж╛ржбрзЗржЬрж╛рж░","link":"https://tv9bangla.com/sports/cricket-news/ind-vs-ban-ravindra-jadejas-consistent-performance-against-bangladesh-in-test-1120894.html","keywords":["ржХрзНрж░рж┐ржХрзЗржЯ","ржЦрзЗрж▓рж╛-sports news"],"creator":["TV9 Bangla"],"video_url":null,"description":"India vs Bangladesh 1st Test: рж░рзЗрж╛рж╣рж┐ржд рж╢рж░рзНржорж╛, ржмрж┐рж░рж╛ржЯ ржХрзЗрж╛рж╣рж▓рж┐, рж╢рзБржнржоржи ржЧрж┐рж▓рж░рж╛ ржнрж░рж╕рж╛ ржжрж┐рждрзЗ ржкрж╛рж░рзЗржиржирж┐ред ржпрж╢рж╕рзНржмрзА рж╣рж╛ржлрж╕рзЗржЮрзНржЪрзБрж░рж┐ ржХрж░рж▓рзЗржУ ржпржерзЗрж╖рзНржЯ ржЫрж┐рж▓ ржирж╛ред ржорзНржпрж╛ржЪрзЗ ржкрж╛рж░рзНржержХрзНржп ржЧржбрж╝рзЗ ржжрж┐рж▓ ржЕрж╢рзНржмрж┐ржи-ржЬрж╛ржбрзЗржЬрж╛ ржЬрзБржЯрж┐ржЗред ржЕрждрж┐рж░рж┐ржХрзНржд ржбрж┐ржлрзЗржирзНрж╕ ржиржпрж╝, ржмрж░ржВ ржкрж╛рж▓рзНржЯрж╛ ржЖржХрзНрж░ржоржгрзЗ ржмрж╛ржВрж▓рж╛ржжрзЗрж╢ржХрзЗ ржЪрж╛ржкрзЗ ржлрзЗрж▓рзЗржи ржЕрж╢рзНржмрж┐ржи ржУ ржЬрж╛ржбрзЗржЬрж╛ред","content":"ONLY AVAILABLE IN PAID PLANS","pubDate":"2024-09-19 15:55:05","pubDateTZ":"UTC","image_url":"https://images.tv9bangla.com/wp-content/uploads/2024/09/IND-vs-BAN-Ravindra-Jadejas-consistent-Performance-against-Bangladesh-in-Test.jpg?w=1280","source_id":"tv9bangla","source_priority":32033,"source_name":"Tv9 Bangla News","source_url":"https://tv9bangla.com","source_icon":"https://i.bytvi.com/domain_icons/tv9bangla.png","language":"bengali","country":["india"],"category":["sports"],"ai_tag":"ONLY AVAILABLE IN PROFESSIONAL AND CORPORATE PLANS","sentiment":"ONLY AVAILABLE IN PROFESSIONAL AND CORPORATE PLANS","sentiment_stats":"ONLY AVAILABLE IN PROFESSIONAL AND CORPORATE PLANS","ai_region":"ONLY AVAILABLE IN CORPORATE PLANS","ai_org":"ONLY AVAILABLE IN CORPORATE PLANS","duplicate":false},{"article_id":"574d0c91d21d933b5ba91a758fc035dd","title":"WATCH: Aussie star hits winning runs in the most alpha way possible","link":"https://www.theroar.com.au/cricket/video/watch-aussie-star-hits-winning-runs-in-the-most-alpha-way-possible-1382512/","keywords":["cricket"],"creator":["The Roar"],"video_url":null,"description":"HowтАЩs the tuck of the bat under the arm from Phoebe Litchfield too!","content":"ONLY AVAILABLE IN PAID PLANS","pubDate":"2024-09-19 16:03:58","pubDateTZ":"UTC","image_url":"https://cdn4.theroar.com.au/wp-content/uploads/2024/09/image-6362163489112-755x432.jpg","source_id":"theroar_au","source_priority":163462,"source_name":"The Roar","source_url":"https://www.theroar.com.au","source_icon":"https://i.bytvi.com/domain_icons/theroar_au.jpg","language":"english","country":["australia"],"category":["sports"],"ai_tag":"ONLY AVAILABLE IN PROFESSIONAL AND CORPORATE PLANS","sentiment":"ONLY AVAILABLE IN PROFESSIONAL AND CORPORATE PLANS","sentiment_stats":"ONLY AVAILABLE IN PROFESSIONAL AND CORPORATE PLANS","ai_region":"ONLY AVAILABLE IN CORPORATE PLANS","ai_org":"ONLY AVAILABLE IN CORPORATE PLANS","duplicate":false},{"article_id":"bb11755cc34281c39eb9de35e7dab4e9","title":"Yashasvi Jaiswal: ржнрж╛рж░ржд ржнрж╛рж▓ ржЬрж╛ржпрж╝ржЧрж╛ржпрж╝ рж░ржпрж╝рзЗржЫрзЗ, ржмрж╛ржВрж▓рж╛ржжрзЗрж╢ржХрзЗ рж╣рзБржБрж╢рж┐ржпрж╝рж╛рж░рж┐ ржжрж┐ржпрж╝рзЗ рж░рж╛ржЦрж▓рзЗржи ржпрж╢рж╕рзНржмрзА","link":"https://bengali.abplive.com/sports/cricket/ind-vs-ban-chennai-test-yashasvi-jaiswal-has-no-complaints-about-pace-friendly-chepauk-conditions-1096274","keywords":["ржХрзНрж░рж┐ржХрзЗржЯ"],"creator":["ABP Ananda"],"video_url":null,"description":"ржЪрзЗржирзНржирж╛ржЗ: ржмрж╛ржВрж▓рж╛ржжрзЗрж╢рзЗрж░ ржкрзЗрж╕рж╛рж░ рж╣рж╛рж╕рж╛ржи ржорж╛рж╣ржорзБржжрзЗрж░ рж╕рзНржпрзБржЗржВржпрж╝рзЗрж░ ржмрж┐рж╖рзЗ рждржЦржи ржнрж╛рж░рждрзАржпрж╝ ржмрзНржпрж╛ржЯрж┐ржВржпрж╝рзЗрж░ ржкрзНрж░рж╛ржг ржУрж╖рзНржарж╛ржЧрждред рж░рзЗрж╛рж╣рж┐ржд рж╢рж░рзНржорж╛ ржерзЗржХрзЗ рж╢рзБрж░рзБ ржХрж░рзЗ ржмрж┐рж░рж╛ржЯ ржХрзЗрж╛рж╣рж▓рж┐, ржПржХрзЗрж░ ржкрж░ ржПржХ рж░ржерзА ржорж╣рж╛рж░ржерзАрж░рж╛ ржкрзНржпрж╛ржнрж┐рж▓рж┐ржпрж╝ржирзЗред ржЪрзЗржирзНржирж╛ржЗржпрж╝рзЗ ржЪрж╛ржкрзЗрж░ ржорзБржЦрзЗ рждрж┐ржирж┐ ржХрж╛рж░рзНржпржд ржПржХрж╛ржЗ ржмрзБржХ ржЪрж┐рждрж┐ржпрж╝рзЗ рж▓ржбрж╝рж╛ржЗ ржХрж░рж▓рзЗржи ржкрзНрж░ржержо рж╕рзЗрж╢ржирзЗред рждрж┐ржирж┐, ржпрж╢рж╕рзНржмрзА ржЬржпрж╝рж╕ржУржпрж╝рж╛рж▓ (Yashasvi Jaiswal)ред рж░рзЗрж╛рж╣рж┐ржд рж╢рж░рзНржорж╛рж░ рж╕ржЩрзНржЧрзЗ ржЗржирж┐ржВрж╕ ржУржкрзЗржи ржХрж░рждрзЗ ржирзЗржорзЗ ржмрзГрж╣рж╕рзНржкрждрж┐ржмрж╛рж░ ржпрж┐ржирж┐ рззрззрзо ржмрж▓рзЗ рзлрзм рж░рж╛ржирзЗрж░ ржЗржирж┐ржВрж╕ ржЦрзЗрж▓рж▓рзЗржиредржкрзНрж░ржержо ржжрж┐ржирзЗрж░ рж╢рзЗрж╖рзЗ ржЖрж░ ржЕрж╢рзНржмрж┐ржи, рж░ржмрзАржирзНржжрзНрж░ ржЬрж╛ржбрзЗржЬрж╛рж░ ржкрж╛рж░рзНржЯржирж╛рж░рж╢рж┐ржкрзЗ ржнрж╛рж▓ ржЬрж╛ржпрж╝ржЧрж╛ржпрж╝ ржкрзЗрзЧржБржЫрзЗ ржЧрж┐ржпрж╝рзЗржЫрзЗ ржнрж╛рж░рждред ржЕржмрж┐ржЪрзНржЫрзЗржжрзНржп рж╕ржкрзНрждржо ржЙржЗржХрзЗржЯрзЗ рззрзпрзл рж░рж╛ржи ржпрзЗрж╛ржЧ ржХрж░рзЗржЫрзЗржи ржжрзБржЬржирзЗ (India vs Bangladesh)ред ржпржжрж┐ржУ ржкрж╛рж▓рзНржЯрж╛ рж▓ржбрж╝рж╛ржЗржпрж╝рзЗрж░ рж╢рзБрж░рзБржЯрж╛ рж╣ржпрж╝рзЗржЫрж┐рж▓ ржпрж╢рж╕рзНржмрзАрж░ ржмрзНржпрж╛ржЯрзЗржЗред ржШрж░рзЗрж░ ржорж╛ржарзЗ ржмржЫрж░рзЗрж░ ржЧрзЗрж╛ржбрж╝рж╛ржпрж╝ ржЗржВрж▓рзНржпрж╛ржирзНржбрзЗрж░ ржмрж┐рж░рзБржжрзНржзрзЗ ржЯрзЗрж╕рзНржЯ рж╕рж┐рж░рж┐ржЬрзЗ рж╕рж╛рждрж╢рзЗрж╛рж░ ржУржкрж░ рж░рж╛ржи ржХрж░рзЗ рж╕рзБржирзАрж▓ ржЧрж╛ржУрж╕рзНржХрж░рзЗрж░ рж░рзЗржХрж░рзНржб рж╕рзНржкрж░рзНрж╢ ржХрж░рзЗржЫрж┐рж▓рзЗржиред ржмрж╛ржВрж▓рж╛ржжрзЗрж╢рзЗрж░ ржмрж┐рж░рзБржжрзНржзрзЗржУ ржмрзНржпрж╛ржЯ рж╣рж╛рждрзЗ рж╕ржкрзНрж░рждрж┐ржн ржпрж╢рж╕рзНржмрзАредржХрзАржнрж╛ржмрзЗ ржмрж╛ржВрж▓рж╛ржжрзЗрж╢рзЗрж░ ржкрзЗрж╕ ржмрзЗрж╛рж▓рж┐ржВржпрж╝рзЗрж░ ржЭрж╛ржБржЭ рж╕рж╛ржорж▓рж╛рж▓рзЗржи? ржпрзЗржЦрж╛ржирзЗ ржмрж┐рж░рж╛ржЯ ржХрзЗрж╛рж╣рж▓рж┐ ржкрж░рзНржпржирзНржд ржЕржлрж╕рзНржЯрж╛ржорзНржкрзЗрж░ ржмрж╛ржЗрж░рзЗрж░ ржмрж▓рзЗ ржкрж╛рждрж╛ ржлрж╛ржБржжрзЗ ржкрж╛ ржжрж┐ржпрж╝рзЗ ржбрзНрж░рзЗрж╕рж┐ржВрж░рзБржорзЗ ржлрж┐рж░рзЗ ржЧрзЗрж▓рзЗржи? ржкрзНрж░ржержо ржжрж┐ржирзЗрж░ ржЦрзЗрж▓рж╛рж░ рж╢рзЗрж╖рзЗ рж╕рж╛ржВржмрж╛ржжрж┐ржХ ржмрзИржаржХрзЗ ржпрж╢рж╕рзНржмрзА ржмрж▓рзЗржи, 'ржПржЗ ржкрж░рж┐ржмрзЗрж╢, ржкрж░рж┐рж╕рзНржерж┐рждрж┐рждрзЗ ржмрзНржпрж╛ржЯ ржХрж░рждрзЗ ржирзЗржорзЗ ржжрж╛рж░рзБржг ржЕржнрж┐ржЬрзНржЮрждрж╛ рж╣рж▓ред ржПржЗ ржкрж░рж┐рж╕рзНржерж┐рждрж┐ ржЖржорж╛ржХрзЗ ржЖрж░ржУ рж╢ржХрзНрждрж┐рж╢рж╛рж▓рзА ржХрж░рзЗржЫрзЗред ржПржЗ ржзрж░ржирзЗрж░ ржкрж░рж┐рж╕рзНржерж┐рждрж┐рждрзЗ ржХрзАржнрж╛ржмрзЗ ржЦрзЗрж▓рж╛ ржжрж░ржХрж╛рж░, рждрж╛ ржирж┐ржпрж╝рзЗ ржЕржирзЗржХ ржХрж┐ржЫрзБ рж╢рж┐ржЦрж▓рж╛ржоред ржХрзАржнрж╛ржмрзЗ ржкрж░рж┐ржХрж▓рзНржкржирж╛ ржХрж░рзЗ ржЗржирж┐ржВрж╕ ржПржЧрж┐ржпрж╝рзЗ ржирж┐ржпрж╝рзЗ ржпрж╛ржУржпрж╝рж╛ ржпрж╛ржпрж╝, рж╕рзЗржЯрж╛ржУ рж╢рж┐ржЦрж▓рж╛ржоред'ржЖрж░ржУ ржкржбрж╝рзБржи: рж╕ржорж╛ржЬрзЗрж░ ржорж╣рж┐рж╖рж╛рж╕рзБрж░рзЗрж░рж╛ ржирж┐ржкрж╛ржд ржпрж╛ржХ, ржкрзНрж░рж╛рж░рзНржержирж╛ржпрж╝ ржмрж┐рж╢рзЗрж╖ ржЕржирзБрж╖рзНржарж╛ржи ржХрж░ржЫрзЗржи ржбрзЗрж╛ржирж╛ржпрж╢рж╕рзНржмрзА ржЖрж░ржУ ржмрж▓рзЗржи, 'ржЖржорж┐ ржжрж▓рзЗрж░ ржкрзНрж░ржпрж╝рзЗрж╛ржЬржи ржЕржирзБржпрж╛ржпрж╝рзА ржЦрзЗрж▓рж╛рж░ ржЪрзЗрж╖рзНржЯрж╛ ржХрж░рзЗржЫрж┐ред рж╕рзЗржЗ ржорждрзЗрж╛ ржирж┐ржЬрзЗрж░ ржЦрзЗрж▓рж╛ ржкрж╛рж▓рзНржЯрзЗржЫрж┐ред рж╢рзБрж░рзБрждрзЗ ржЙржЗржХрзЗржЯ ржкржбрж╝рж▓рзЗ ржЖржорж┐ ржХрзАржнрж╛ржмрзЗ ржмрзНржпрж╛ржЯрж┐ржВ ржХрж░ржм? ржпржЦржи рж░рж╛ржи ржЖрж╕ржЫрзЗ, ржХрзАржнрж╛ржмрзЗ ржмрзНржпрж╛ржЯрж┐ржВ ржХрж░ржм?'ржЯрзЗрж╕рзНржЯрзЗ ржкржЮрзНржЪржо рж╣рж╛ржлрж╕рзЗржЮрзНржЪрзБрж░рж┐ ржХрж░рзЗржЫрзЗржи ржпрж╢рж╕рзНржмрзАред рждржмрзЗ ржЗржВрж▓рзНржпрж╛ржирзНржбрзЗрж░ ржмрж┐рж░рзБржжрзНржзрзЗ ржпрзЗржнрж╛ржмрзЗ ржЖржЧрзНрж░рж╛рж╕рзА ржмрзНржпрж╛ржЯрж┐ржВ ржХрж░рзЗржЫрж┐рж▓рзЗржи, ржмрж╛ржВрж▓рж╛ржжрзЗрж╢рзЗрж░ ржмрж┐рж░рзБржжрзНржзрзЗ ржЪрзЗржирзНржирж╛ржЗржпрж╝рзЗ рж╕рзЗржнрж╛ржмрзЗ ржмрзНржпрж╛ржЯрж┐ржВ ржХрж░рзЗржиржирж┐ред ржмрж░ржВ ржЕржирзЗржХ рж╕рждрж░рзНржХ ржжрзЗржЦрж┐ржпрж╝рзЗржЫрзЗ ржорзБржорзНржмржЗржпрж╝рзЗрж░ ржмрзНржпрж╛ржЯрж╛рж░ржХрзЗред ржкржЮрзНржЪрж╛рж╢рзЗрж░ ржХржо рж╕рзНржЯрзНрж░ржЗржХ рж░рзЗржЯ рж░рзЗржЦрзЗ рж░рж╛ржи ржХрж░рзЗржЫрзЗржиредржжрзНржмрж┐рждрзАржпрж╝ рж╕рзЗрж╢ржирзЗ ржирж╛рж╣рж┐ржж рж░рж╛ржирж╛рж░ ржЪржХрж┐ржд ржмрж╛ржЙржирзНрж╕рж╛рж░рзЗ рждрж┐ржирж┐ ржЖржЙржЯ рж╣ржиред ржпржжрж┐ржУ ржнрж╛рж░ржд ржнрж╛рж▓ ржЬрж╛ржпрж╝ржЧрж╛ржпрж╝ ржЖржЫрзЗ ржмрж▓рзЗржЗ ржоржирзЗ ржХрж░рзЗржи ржпрж╢рж╕рзНржмрзАред ржмрж▓рзЗржЫрзЗржи, 'рж╢рзБрж░рзБрж░ ржжрж┐ржХрзЗ ржкрж┐ржЪрзЗ ржкржбрж╝рзЗ ржмрж▓ ржирзАржЪрзБ рж╣ржЪрзНржЫрж┐рж▓, ржиржбрж╝рж╛ржЪржбрж╝рж╛ ржХрж░ржЫрж┐рж▓ред рждрж╛ржЗ ржЖржорж░рж╛ рж╕ржоржпрж╝ ржирж┐ржпрж╝рзЗ ржЦрзЗрж▓ржЫрж┐рж▓рж╛ржоред рждржмрзЗ рж╢рзЗрж╖ рж╕рзЗрж╢ржирзЗ ржнрж╛рж▓ ржЧрждрж┐рждрзЗ рж░рж╛ржи ржЙржарзЗржЫрзЗред ржПржЗ ржорзБрж╣рзВрж░рзНрждрзЗ ржЖржорж░рж╛ ржнрж╛рж▓ ржЬрж╛ржпрж╝ржЧрж╛ржпрж╝ рж░ржпрж╝рзЗржЫрж┐ред'ржЖрж░ржУ ржкржбрж╝рзБржи: ржЖрж░ ржЬрж┐ ржХрж░ ржХрж╛ржгрзНржбрзЗ ржХрзБрж░рзБржЪрж┐ржХрж░ ржнрж╛рж╖рж╛ржпрж╝ ржЖржХрзНрж░ржоржг, рж╕рж╛ржЗржмрж╛рж░ ржХрзНрж░рж╛ржЗржо рж╢рж╛ржЦрж╛ржпрж╝ ржЕржнрж┐ржпрзЗрж╛ржЧ рж╕рзЗрзЧрж░ржнрзЗрж░ржЖржкржирж╛рж░ ржкржЫржирзНржжрзЗрж░ ржЦржмрж░ ржЖрж░ ржЖржкржбрзЗржЯ ржкрж╛ржмрзЗржи ржЖржкржирж╛рж░ ржкржЫржирзНржжрзЗрж░ ржЪрзНржпрж╛ржЯрж┐ржВ ржкрзНрж▓рзНржпрж╛ржЯржлрж░рзНржо рж╣рзЗрж╛ржпрж╝рж╛ржЯрж╕ ржЕрзНржпрж╛ржкрзЗржУред ржпрзБржХрзНржд рж╣рзЗрж╛ржи ABP Ananda рж╣рзЗрж╛ржпрж╝рж╛ржЯрж╕ ржЕрзНржпрж╛ржк ржЪрзНржпрж╛ржирзЗрж▓рзЗред","content":"ONLY AVAILABLE IN PAID PLANS","pubDate":"2024-09-19 16:03:31","pubDateTZ":"UTC","image_url":"https://feeds.abplive.com/onecms/images/uploaded-images/2024/09/19/bc22ea7663385fad4cf3ac88d4567bbb172676008002450_original.jpg","source_id":"abplive","source_priority":7754,"source_name":"Abp News","source_url":"http://abplive.com","source_icon":"https://i.bytvi.com/domain_icons/abplive.jpg","language":"bengali","country":["india"],"category":["sports"],"ai_tag":"ONLY AVAILABLE IN PROFESSIONAL AND CORPORATE PLANS","sentiment":"ONLY AVAILABLE IN PROFESSIONAL AND CORPORATE PLANS","sentiment_stats":"ONLY AVAILABLE IN PROFESSIONAL AND CORPORATE PLANS","ai_region":"ONLY AVAILABLE IN CORPORATE PLANS","ai_org":"ONLY AVAILABLE IN CORPORATE PLANS","duplicate":false},{"article_id":"039a585fe6e294a7ee804eaa8cbe0bcd","title":"WATCH: Sarfaraz Ahmed Sledges Babar Azam, Pakistan Captain Scores Century In Reply During Champions Cup","link":"https://zeenews.india.com/cricket/watch-sarfaraz-ahmed-sledges-babar-azam-pakistan-captain-scores-century-in-reply-during-champions-cup-2795727.html","keywords":null,"creator":["Zee News"],"video_url":null,"description":"Babar Azam scored a century in the Champions Cup after Sarfaraz Ahmed sledged him during the game.","content":"ONLY AVAILABLE IN PAID PLANS","pubDate":"2024-09-19 16:03:00","pubDateTZ":"UTC","image_url":"https://english.cdn.zeenews.com/sites/default/files/styles/zm_700x400/public/2024/09/19/1516746-ind-8.png?im=Resize%3D%28400%29","source_id":"zeenews","source_priority":5319,"source_name":"Zee News","source_url":"http://zeenews.india.com","source_icon":"https://i.bytvi.com/domain_icons/zeenews.png","language":"english","country":["india"],"category":["sports"],"ai_tag":"ONLY AVAILABLE IN PROFESSIONAL AND CORPORATE PLANS","sentiment":"ONLY AVAILABLE IN PROFESSIONAL AND CORPORATE PLANS","sentiment_stats":"ONLY AVAILABLE IN PROFESSIONAL AND CORPORATE PLANS","ai_region":"ONLY AVAILABLE IN CORPORATE PLANS","ai_org":"ONLY AVAILABLE IN CORPORATE PLANS","duplicate":false},{"article_id":"ecc0bc8e7a1bd92f220daa521e76ed98","title":"IND vs BAN: 'рдЪреАрддреЗ рдХреА рдЪрд╛рд▓, рдмрд╛рдЬ рдХреА рдирдЬрд░ рдФрд░ рдЬрдбреНрдбреВ рдХреА..' рдЬрдбреЗрдЬрд╛ рдХреА рддрд╛рд░реАрдл рдореЗрдВ рд╢рд╛рдпрд░ рдмрдиреЗ рд╕реВрд░реНрдпрд╛, рдлреИрдВрд╕ рдХрд░ рд░рд╣реЗ рд╡рд╛рд╣-рд╡рд╛рд╣","link":"https://zeenews.india.com/hindi/sports/cricket/suryakumar-yadav-unique-way-to-praised-r-ashwin-century-ravindra-jadeja-ind-vs-ban-1st-test/2437929","keywords":null,"creator":["Zee News рд╣рд┐рдиреНрджреА","Zee News Hindi"],"video_url":null,"description":"India vs Bangladesh: рдЬрдбреЗрдЬрд╛-рдЕрд╢реНрд╡рд┐рди рдХреА рдЬреЛрдбрд╝реА рдХреА рджрд╣рд╢рдд рджреБрдирд┐рдпрд╛рднрд░ рдХреА рдЯреАрдореЛрдВ рдореЗрдВ рд╣реИ. рджреЛрдиреЛрдВ рджрд┐рдЧреНрдЧрдЬреЛрдВ рдиреЗ рдЕрдкрдиреА рдлрд┐рд░рдХреА рд╕реЗ рдХрдИ рдмрдбрд╝реЗ рдзреБрд░рдВрдзрд░реЛрдВ рдХреЛ рдЪрд╛рд░реЛ рдЦрд╛рдиреЗ рдЪрд┐рдд рдХрд░ рджрд┐рдпрд╛. рд▓реЗрдХрд┐рди 19 рд╕рд┐рддрдВрдмрд░ рдХреЛ рдпреЗ рдЬреЛрдбрд╝реА рдмрд▓реНрд▓реЗ рд╕реЗ рд░рдВрдЧ рдЬрдорд╛рддреА рдирдЬрд░ рдЖрдИ. рд╡рд┐рд░рд╛рдЯ-рд░реЛрд╣рд┐рдд рдХреЗ рд╡рд┐рдХреЗрдЯ рдХреЗ рдмрд╛рдж рдЬреАрдд рдХреЗ рд╕рдкрдиреЗ рджреЗрдЦрдиреЗ рд▓рдЧреА рдмрд╛рдВрдЧреНрд▓рд╛рджреЗрд╢ рдХреЛ рдЕрд╢реНрд╡рд┐рди-рдЬрдбреЗрдЬрд╛ рдиреЗ рдирд╛рдХреЛ рдЪрдиреЗ рдЪрдмрд╡рд╛ рджрд┐рдП. рдЬрд┐рд╕рдХреЗ рдмрд╛рдж рд╕реВрд░реНрдпрд╛ рдХреА рдЬреБрдмрд╛рдВ рд╕реЗ рднреА рд╢рд╛рдпрд░реА рдирд┐рдХрд▓рдиреЗ рд▓рдЧреА.","content":"ONLY AVAILABLE IN PAID PLANS","pubDate":"2024-09-19 16:00:12","pubDateTZ":"UTC","image_url":"https://hindi.cdn.zeenews.com/hindi/sites/default/files/2024/09/19/3246715-ashwin-and-jadeja.png?im=FitAndFill%3D%281200%2C900%29","source_id":"zeenews","source_priority":5319,"source_name":"Zee News","source_url":"http://zeenews.india.com","source_icon":"https://i.bytvi.com/domain_icons/zeenews.png","language":"hindi","country":["india"],"category":["sports"],"ai_tag":"ONLY AVAILABLE IN PROFESSIONAL AND CORPORATE PLANS","sentiment":"ONLY AVAILABLE IN PROFESSIONAL AND CORPORATE PLANS","sentiment_stats":"ONLY AVAILABLE IN PROFESSIONAL AND CORPORATE PLANS","ai_region":"ONLY AVAILABLE IN CORPORATE PLANS","ai_org":"ONLY AVAILABLE IN CORPORATE PLANS","duplicate":false},{"article_id":"03c43ad6ab1b6f73df5795430c67387f","title":"Shreyas Iyer goes for duck again, Sanju Samson quick fires with 89 against India B in Duleep Trophy 2024","link":"https://www.india.com/sports/shreyas-iyer-goes-for-duck-again-sanju-samson-quick-fires-with-89-against-india-b-in-duleep-trophy-2024-7259900/","keywords":["ks bharat","mukesh kumar","sanju samson","duleep trophy 2024","rahul chahar","shreyas iyer","sports","cricket","ricky bhui","devdutt padikkal","navdeep saini"],"creator":null,"video_url":null,"description":"Indian wicketkeeper-batter Sanju Samson rescued India D with a brilliant unbeaten fifty against India B in the Duleep Trophy 2024 final-round fixtures on Thursday.","content":"ONLY AVAILABLE IN PAID PLANS","pubDate":"2024-09-19 15:59:59","pubDateTZ":"UTC","image_url":"https://static.india.com/wp-content/themes/icom/images/default-big.svg","source_id":"india","source_priority":8067,"source_name":"India","source_url":"https://www.india.com","source_icon":"https://i.bytvi.com/domain_icons/india.png","language":"english","country":["india"],"category":["sports"],"ai_tag":"ONLY AVAILABLE IN PROFESSIONAL AND CORPORATE PLANS","sentiment":"ONLY AVAILABLE IN PROFESSIONAL AND CORPORATE PLANS","sentiment_stats":"ONLY AVAILABLE IN PROFESSIONAL AND CORPORATE PLANS","ai_region":"ONLY AVAILABLE IN CORPORATE PLANS","ai_org":"ONLY AVAILABLE IN CORPORATE PLANS","duplicate":false},{"article_id":"af0b6e1ff6e4a3df5e3e24c09c42467e","title":"тАШркдрлЗркирлЗ 40 ркУрк╡рк░ рк░ркорк╡рк╛ ркжрлЛтАЩ ... рк╕рк░рклрк░рк╛ркЭ ркЕрк╣рлЗркоркжрлЗ ркХрк░рлНркпрлЛ ркЯрлНрк░рлЛрк▓ ркЕркирлЗ ркмрк╛ркмрк░ ркЖркЭркорлЗ рклркЯркХрк╛рк░рлА 30ркорлА рк╕ркжрлА","link":"https://tv9gujarati.com/sports/cricket-news/sarfaraz-ahmed-troll-babar-azam-hit-list-a-century-in-champions-odi-cup-pakistan-1094074.html","keywords":["рк╕рлНрккрлЛрк░рлНркЯрк╕ ркирлНркпрлВркЭ","ркХрлНрк░рк┐ркХрлЗркЯ ркирлНркпрлВркЭ"],"creator":["Smit Chauhan"],"video_url":null,"description":"ркмрк╛ркмрк░ ркЖркЭрко ркЪрлЗркорлНрккрк┐ркпркирлНрк╕ ркХрккркорк╛ркВ рк╕рк╛рк░рлА ркИркирк┐ркВркЧ рк░ркорлА рк░рк╣рлНркпрлЛ ркЫрлЗ ркЕркирлЗ рк╣рк╡рлЗ ркдрлЗркгрлЗ рк╕ркжрлА рккркг рклркЯркХрк╛рк░рлА ркЫрлЗ. ркмрк╛ркмрк░ ркЖркЭркорлЗ ркдрлЗркирлА 30ркорлА рк▓рк┐рк╕рлНркЯ A рк╕ркжрлА рклркЯркХрк╛рк░рлА рк╣ркдрлА. ркЬрлЛ ркХрлЗ ркдрлЗркирлА рк╕ркжрлА ркжрк░ркорк┐ркпрк╛рки рккрк╛ркХрк┐рк╕рлНркдрк╛ркиркирк╛ рккрлВрк░рлНрк╡ ркХрлЗрккрлНркЯрки рк╕рк░рклрк░рк╛ркЭ ркЕрк╣рлЗркоркжрлЗ ркдрлЗркирлЗ ркЯрлНрк░рлЛрк▓ ркХрк░рк╡рк╛ркирлЛ рккрлНрк░ркпрк╛рк╕ ркХрк░рлНркпрлЛ рк╣ркдрлЛ.","content":"ONLY AVAILABLE IN PAID PLANS","pubDate":"2024-09-19 15:58:40","pubDateTZ":"UTC","image_url":"https://images.tv9gujarati.com/wp-content/uploads/2024/09/Babar-Azam-2.jpg?w=1280","source_id":"tv9gujarati","source_priority":75214,"source_name":"Tv9 Gujarati","source_url":"https://tv9gujarati.com","source_icon":"https://i.bytvi.com/domain_icons/tv9gujarati.jpg","language":"gujarati","country":["india"],"category":["sports"],"ai_tag":"ONLY AVAILABLE IN PROFESSIONAL AND CORPORATE PLANS","sentiment":"ONLY AVAILABLE IN PROFESSIONAL AND CORPORATE PLANS","sentiment_stats":"ONLY AVAILABLE IN PROFESSIONAL AND CORPORATE PLANS","ai_region":"ONLY AVAILABLE IN CORPORATE PLANS","ai_org":"ONLY AVAILABLE IN CORPORATE PLANS","duplicate":false},{"article_id":"b3c4604cbc6f7ee9f4346eccf4c4ff36","title":"IND vs BAN 1st Test: ржЕрж╢рзНржмрж┐ржи-ржЬрж╛ржбрзЗржЬрж╛ржпрж╝ ржорзБржЧрзНржз рж╕ржЪрж┐ржи, рждрж╛рж░ржХрж╛ ржЕрж▓рж░рж╛ржЙржирзНржбрж╛рж░ржжрзЗрж░ ржнрзВржпрж╝рж╕рзА ржкрзНрж░рж╢ржВрж╕рж╛ржпрж╝ ржнрж░рж╛рж▓рзЗржи 'ржорж╛рж╕рзНржЯрж╛рж░ ржмрзНрж▓рж╛рж╕рзНржЯрж╛рж░'","link":"https://bengali.abplive.com/sports/cricket/r-ashwin-ravindra-jadeja-brillant-partnership-rescues-ind-vs-ban-1st-test-sachin-tendulkar-lauds-1096273","keywords":["ржХрзНрж░рж┐ржХрзЗржЯ"],"creator":["ABP Ananda"],"video_url":null,"description":"ржЪрзЗржирзНржирж╛ржЗ: ржмрж╛ржВрж▓рж╛ржжрзЗрж╢рзЗрж░ ржЪрзЗржирзНржирж╛ржЗржпрж╝рзЗ ржкрзНрж░ржержо ржЯрзЗрж╕рзНржЯрзЗ (IND vs BAN 1st Test) рждрж░рзБржг ржлрж╛рж╕рзНржЯ ржмрзЗрж╛рж▓рж╛рж░ржжрзЗрж░ ржмрж┐рж░рзБржжрзНржзрзЗ ржПржХрзЗ ржПржХрзЗ ржпржЦржи ржЯрж┐ржо ржЗржирзНржбрж┐ржпрж╝рж╛рж░ ржорж╣рж╛рждрж╛рж░ржХрж╛рж░рж╛ рж╕рж╛ржЬржШрж░рзЗ ржлрж┐рж░рзЗ ржЧрж┐ржпрж╝рзЗржЫрзЗржи, ржпржЦржи ржЯрж┐ржо ржЗржирзНржбрж┐ржпрж╝рж╛ ржжрзБ'рж╢рзЗрж╛ рж░рж╛ржирзЗрж░ ржЧржгрзНржбрж┐ржУ ржкрж╛рж░ ржХрж░рждрзЗ ржкрж╛рж░ржмрзЗ ржХрж┐ ржирж╛, рж╕рзЗржЗ ржирж┐ржпрж╝рзЗ рж╕ржВрж╢ржпрж╝ рждрзИрж░рж┐ рж╣ржпрж╝рзЗржЫрж┐рж▓, рждржЦржиржЗ ржмрзНржпрж╛ржЯ рж╣рж╛рждрзЗ рж░рзБржЦрзЗ ржжрж╛ржБржбрж╝рж╛ржи ржжрзБржЗ ржЕрж▓рж░рж╛ржЙржирзНржбрж╛рж░ред рж░ржмрзАржирзНржжрзНрж░ ржЬрж╛ржбрзЗржЬрж╛ (Ravindra Jadeja) ржУ ржЖрж░ ржЕрж╢рзНржмрж┐ржи (R Ashwin) ржнрж╛рж░рждржХрзЗ ржжрзБ'рж╢рзЗрж╛ ржкрж╛рж░ ржХрж░рж╛ржирзЗрж╛ ржиржпрж╝, ржкрзНрж░ржержо ржжрж┐ржирзЗрж░ ржЦрзЗрж▓рж╛рж╢рзЗрж╖рзЗ рзйрзлрзж рж░рж╛ржирзЗрж░ ржжрзЗрж╛рж░ржЧрзЗрж╛ржбрж╝рж╛ржпрж╝ ржкрзЗрзЧржБржЫрзЗ ржжрж┐рж▓рзЗржиред ржЬрзБржбрж╝рж▓рзЗржи рззрзпрзл рж░рж╛ржиредржжрж┐ржирж╢рзЗрж╖рзЗ ржжрзБржЗ рждрж╛рж░ржХрж╛ржЗ ржХрж┐ржирзНрждрзБ ржЕржкрж░рж╛ржЬрж┐ржд рж░ржпрж╝рзЗржЫрзЗржиред ржЕрж╢рзНржмрж┐ржирзЗрж░ рж╕ржВржЧрзНрж░рж╣ рззрзжрзи, ржЬрж╛ржбрзЗржЬрж╛рж░ ржЭрзБрж▓рж┐рждрзЗ рзорзм рж░рж╛ржиред ржжрзБржЗ рждрж╛рж░ржХрж╛рж░ рззрзпрзл рж░рж╛ржи рж╕ржкрзНрждржо ржЙржЗржХрзЗржЯрзЗ ржЪрж┐ржкржХрзЗ рж╕рж░рзНржмржХрж╛рж▓рзАржи рж░рзЗржХрж░рзНржбред рждрж╛ржБрж░рж╛ ржХрж╛рж▓ ржХрж┐ржирзНрждрзБ ржирж┐ржЬрзЗржжрзЗрж░ ржПржЗ рж╕рзНржорж░ржгрзАржпрж╝ ржкрж╛рж░рзНржЯржирж╛рж░рж╢рж┐ржкржХрзЗ ржЖрж░ржУ ржмрж╛ржбрж╝рж╛рждрзЗ ржкрж╛рж░рзЗржиред ржЕрж╢рзНржмрж┐ржи ржУ ржЬрж╛ржбрзЗржЬрж╛рж░ ржПржЗ ржкрж╛рж░рзНржЯржирж╛рж░рж╢рж┐ржк ржЫрж╛ржбрж╝рж╛ ржнрж╛рж░рждрзАржпрж╝ ржжрж▓ ржпрзЗ ржмрж┐рж░рж╛ржЯ ржмрж┐ржкрж╛ржХрзЗ ржкржбрж╝ржд, рждрж╛ ржмрж▓рж╛рж░ ржЕржмржХрж╛рж╢ рж░рж╛ржЦрзЗ ржирж╛редржжрзБржЗ ржЕржнрж┐ржЬрзНржЮ рждрж╛рж░ржХрж╛рж░ ржмрзНржпрж╛ржЯрж┐ржВржпрж╝рзЗ ржорзБржЧрзНржз рж╕рзНржмржпрж╝ржВ 'ржХрзНрж░рж┐ржХрзЗржЯ ржИрж╢рзНржмрж░'ржУред ржкрзНрж░ржержо ржжрж┐ржирзЗрж░ ржЦрзЗрж▓рж╛рж╢рзЗрж╖рзЗ рж╕ржЪрж┐ржи рждрзЗржирзНржбрзБрж▓ржХрж░ (Sachin Tendulkar) ржирж┐ржЬрзЗрж░ рж╕рзЗрж╛рж╢рзНржпрж╛рж▓ ржорж┐ржбрж┐ржпрж╝рж╛ржпрж╝ ржЬрж╛ржбрзЗржЬрж╛ ржУ ржЕрж╢рзНржмрж┐ржирзЗрж░ ржкрзНрж░рж╢ржВрж╕рж╛ ржХрж░рзЗржиред 'ржорж╛рж╕рзНржЯрж╛рж░ ржмрзНрж▓рж╛рж╕рзНржЯрж╛рж░'-рж░ ржорждрзЗ ржжрзБржЗ рждрж╛рж░ржХрж╛ ржорзНржпрж╛ржЪрзЗ ржнрж╛рж░рждржХрзЗ ржПржЧрж┐ржпрж╝рзЗ ржжрж┐ржпрж╝рзЗржЫрзЗржиред рждрж┐ржирж┐ рж▓рзЗржЦрзЗржи, 'рж╣рждрж╛рж╢рж╛ ржерзЗржХрзЗ ржжрж╛ржкржЯред ржЕрж╢рзНржмрж┐ржи ржУ ржЬрж╛ржбрзЗржЬрж╛ ржжрзБрж░ржирзНржд ржЗржирж┐ржВрж╕ ржЖржмрж╛рж░ ржорзНржпрж╛ржЪрзЗрж░ ржорзЗрж╛ржбрж╝ ржнрж╛рж░рждрзЗрж░ ржжрж┐ржХрзЗ ржШрзБрж░рж┐ржпрж╝рзЗ ржжрж┐ржпрж╝рзЗржЫрзЗред ржПржЗ ржЕрж▓рж░рж╛ржЙржирзНржб ржжржХрзНрж╖рждрж╛ржЯрж╛ ржЕржкрж░рж┐рж╣рж╛рж░рзНржпред ржжрзБрж░ржирзНржд ржкрж╛рж░рзНржЯржирж╛рж░рж╢рж┐ржк ржЧржбрж╝рзЗржЫред' From despair to domination! @ashwinravi99 and @imjadeja's knocks have turned the tide for India once again. This all-round brilliance is invaluable. Super partnership boys. ЁЯСПЁЯП╝#INDvBAN pic.twitter.com/eZNW6yOr8VтАФ Sachin Tendulkar (@sachin_rt) September 19, 2024ржнрж╛рж░рждрзАржпрж╝ ржЯржк ржЕрж░рзНржбрж╛рж░рзЗ ржпрж╢рж╕рзНржмрзА ржЬржпрж╝рж╕ржУржпрж╝рж╛рж▓ рж╣рж╛ржлрж╕рзЗржЮрзНржЪрзБрж░рж┐ ржХрж░рж▓рзЗржУ, рж░рзЗрж╛рж╣рж┐рждрж░рж╛ рж╕ржорзНржкрзВрж░рзНржг ржмрзНржпрж░рзНржеред ржЬржпрж╝рж╕ржУржпрж╝рж╛рж▓ ржПржмржВ ржЛрж╖ржн ржкржирзНрже рж╣рж╛ржлрж╕рзЗржЮрзНржЪрзБрж░рж┐рж░ ржкрж╛рж░рзНржЯржирж╛рж░рж╢рж┐ржк ржЧржбрж╝рж▓рзЗржУ, ржкрж░ржкрж░ ржЙржЗржХрзЗржЯ рж╣рж╛рж░рж╛ржпрж╝ ржнрж╛рж░рждред ржХрзЗржПрж▓ рж░рж╛рж╣рзБрж▓ ржпржЦржи рззрзм рж░рж╛ржирзЗ рж╕рж╛ржЬржШрж░рзЗ ржлрзЗрж░рзЗржи рждржЦржи ржнрж╛рж░рждрзЗрж░ рж╕рзНржХрзЗрж╛рж░ ржЫржпрж╝ ржЙржЗржХрзЗржЯрзЗ рззрзкрзк рж░рж╛ржиред ржжрж┐ржирж╢рзЗрж╖рзЗ ржнрж╛рж░рждрзЗрж░ рж╕рзНржХрзЗрж╛рж░ ржЫржпрж╝ ржЙржЗржХрзЗржЯрзЗрж░ ржмрж┐ржирж┐ржоржпрж╝рзЗ рзйрзйрзп рж░рж╛ржиред ржЕрж╢рзНржмрж┐ржи ржПржХрзЗржмрж╛рж░рзЗржЗ рж╢рзБрж░рзБ ржерзЗржХрзЗ ржирзЗржорзЗ ржжрзБрж░ржирзНржд ржЖржЧрзНрж░рж╛рж╕рзА ржмрзНржпрж╛ржЯрж┐ржВ ржХрж░рзЗржиред ржирж┐ржЬрзЗрж░ рж╖рж╖рзНржа рж╢рждрж░рж╛ржи ржкрзВрж░ржг ржХрж░рзЗржи рждрж┐ржирж┐ред ржЬрж╛ржбрзЗржЬрж╛ржУ рж╕рзЗржЮрзНржЪрзБрж░рж┐ рж╣рж╛ржБржХрж╛рждрзЗ ржкрж╛рж░рзЗржи ржХрж┐ ржирж╛, рж╕рзЗржЯрж╛ржЗ ржжрзЗржЦрж╛рж░ ржмрж┐рж╖ржпрж╝ред ржЖржкржирж╛рж░ ржкржЫржирзНржжрзЗрж░ ржЦржмрж░ ржЖрж░ ржЖржкржбрзЗржЯ ржкрж╛ржмрзЗржи ржЖржкржирж╛рж░ ржкржЫржирзНржжрзЗрж░ ржЪрзНржпрж╛ржЯрж┐ржВ ржкрзНрж▓рзНржпрж╛ржЯржлрж░рзНржо рж╣рзЗрж╛ржпрж╝рж╛ржЯрж╕ ржЕрзНржпрж╛ржкрзЗржУред ржпрзБржХрзНржд рж╣рзЗрж╛ржи ABP Ananda рж╣рзЗрж╛ржпрж╝рж╛ржЯрж╕ ржЕрзНржпрж╛ржк ржЪрзНржпрж╛ржирзЗрж▓рзЗредржЖрж░ржУ ржкржбрж╝рзБржи: ржЯрзЗрж╕рзНржЯ ржЗрждрж┐рж╣рж╛рж╕рзЗ ржПрж░ ржЖржЧрзЗ ржХржЦржиржУ рж╣ржпрж╝ржирж┐, ржЪрзЗржирзНржирж╛ржЗржпрж╝рзЗ рж╣рж╛ржлрж╕рзЗржЮрзНржЪрзБрж░рж┐ рж╣рж╛ржБржХрж┐ржпрж╝рзЗ ржПржоржиржЗ ржХрзГрждрж┐рждрзНржм ржЧржбрж╝рж▓рзЗржи ржпрж╢рж╕рзНржмрзА","content":"ONLY AVAILABLE IN PAID PLANS","pubDate":"2024-09-19 15:58:08","pubDateTZ":"UTC","image_url":"https://feeds.abplive.com/onecms/images/uploaded-images/2024/09/19/471cd0b36a7eddb07d70faf378b059c91726761215705507_original.jpg","source_id":"abplive","source_priority":7754,"source_name":"Abp News","source_url":"http://abplive.com","source_icon":"https://i.bytvi.com/domain_icons/abplive.jpg","language":"bengali","country":["india"],"category":["sports"],"ai_tag":"ONLY AVAILABLE IN PROFESSIONAL AND CORPORATE PLANS","sentiment":"ONLY AVAILABLE IN PROFESSIONAL AND CORPORATE PLANS","sentiment_stats":"ONLY AVAILABLE IN PROFESSIONAL AND CORPORATE PLANS","ai_region":"ONLY AVAILABLE IN CORPORATE PLANS","ai_org":"ONLY AVAILABLE IN CORPORATE PLANS","duplicate":false},{"article_id":"79b613a0a4bf939547875a8ee86dbf40","title":"рдЪреЗрдиреНрдирдИ рдЯреЗрд╕реНрдЯ рдореЗрдВ рдЯреАрдо рдЗрдВрдбрд┐рдпрд╛ рдХреА рдЬреАрдд рдкрд╣рд▓реЗ рд╣реА рджрд┐рди рд╣реБрдИ рддрдп! рдорд┐рд▓ рдЧрдИ рдореБрдХрд╛рдмрд▓рд╛ рдирд╛ рд╣рд╛рд░рдиреЗ рдХреА рдЧрд╛рд░рдВрдЯреА","link":"https://www.tv9hindi.com/sports/cricket-news/team-india-never-lost-any-match-whenever-r-ashwin-has-scored-century-2839516.html","keywords":null,"creator":["TV9 Bharatvarsh"],"video_url":null,"description":"рдЪреЗрдиреНрдирдИ рдЯреЗрд╕реНрдЯ рдХреЗ рдкрд╣рд▓реЗ рджрд┐рди рдЯреАрдо рдЗрдВрдбрд┐рдпрд╛ рдиреЗ 6 рд╡рд┐рдХреЗрдЯ рдХреЗ рдиреБрдХрд╕рд╛рди рдкрд░ 339 рд░рди рдмрдирд╛рдП. рд░рд╡реАрдВрджреНрд░ рдЬрдбреЗрдЬрд╛ рдФрд░ рдЖрд░ рдЕрд╢реНрд╡рд┐рди рдХреА рдУрд░ рд╕реЗ рдХрдорд╛рд▓ рдХреА рдкрд╛рд░рд┐рдпрд╛рдВ рджреЗрдЦрдиреЗ рдХреЛ рдорд┐рд▓реА. рдпреЗ рджреЛрдиреЛрдВ рдмрд▓реНрд▓реЗрдмрд╛рдЬ рдЕрднреА рднреА рдирд╛рдмрд╛рдж рд╣реИрдВ рдФрд░ рдЦреЗрд▓ рдХреЗ рджреВрд╕рд░реЗ рджрд┐рди рдЯреАрдо рдХреЛ рдмрдбрд╝реЗ рд╕реНрдХреЛрд░ рддрдХ рдкрд╣реБрдВрдЪрд╛рдиреЗ рдХреЗ рд▓рд┐рдП рдореИрджрд╛рди рдкрд░ рдЙрддрд░реЗрдВрдЧреЗ.","content":"ONLY AVAILABLE IN PAID PLANS","pubDate":"2024-09-19 15:57:29","pubDateTZ":"UTC","image_url":"https://images.tv9hindi.com/wp-content/uploads/2024/09/r-ashwin-1.jpg","source_id":"tv9bharatvarsh","source_priority":40538658,"source_name":"Tv9 Bharatvarsh","source_url":"https://www.tv9hindi.com","source_icon":null,"language":"hindi","country":["india"],"category":["sports"],"ai_tag":"ONLY AVAILABLE IN PROFESSIONAL AND CORPORATE PLANS","sentiment":"ONLY AVAILABLE IN PROFESSIONAL AND CORPORATE PLANS","sentiment_stats":"ONLY AVAILABLE IN PROFESSIONAL AND CORPORATE PLANS","ai_region":"ONLY AVAILABLE IN CORPORATE PLANS","ai_org":"ONLY AVAILABLE IN CORPORATE PLANS","duplicate":false},{"article_id":"4e14361ad73be6754a94a6f1ea345ad2","title":"Bangladesh A complete T20 WC tune-up with series win in Sri Lanka","link":"https://www.thedailystar.net/sports/cricket/news/bangladesh-complete-t20-wc-tune-series-win-sri-lanka-3707241","keywords":null,"creator":null,"video_url":null,"description":"Bangladesh WomenтАЩs A team bowlers stood out in the final T20 of the five-match series against Sri Lankan A to help their side register an eight-wicket win and clinch a 4-1 series win at the Colts in Colombo today.","content":"ONLY AVAILABLE IN PAID PLANS","pubDate":"2024-09-19 15:55:06","pubDateTZ":"UTC","image_url":"https://www.thedailystar.net/sites/default/files/styles/big_202/public/images/2024/09/19/jdgklfk.jpg","source_id":"thedailystar","source_priority":32093,"source_name":"The Daily Star","source_url":"https://www.thedailystar.com","source_icon":"https://i.bytvi.com/domain_icons/thedailystar.png","language":"english","country":["bangladesh"],"category":["sports"],"ai_tag":"ONLY AVAILABLE IN PROFESSIONAL AND CORPORATE PLANS","sentiment":"ONLY AVAILABLE IN PROFESSIONAL AND CORPORATE PLANS","sentiment_stats":"ONLY AVAILABLE IN PROFESSIONAL AND CORPORATE PLANS","ai_region":"ONLY AVAILABLE IN CORPORATE PLANS","ai_org":"ONLY AVAILABLE IN CORPORATE PLANS","duplicate":false},{"article_id":"c1907499e505bfaa41dfe0f375440c9e","title":"IND vs BAN: ржмрж╛ржШ ржжрзЗржЦрж▓рзЗржЗ рж╢рж┐ржХрж╛рж░рзЗ ржмрзЗрж░рзЗрж╛ржи! ржЖржмрж╛рж░ржУ тАШрждрж▓рзЗрж╛ржпрж╝рж╛рж░-ржмрж╛ржЬрж┐тАЩ ржЬрж╛ржбрзЗржЬрж╛рж░","link":"https://tv9bangla.com/sports/cricket-news/ind-vs-ban-ravindra-jadejas-consistent-performance-against-bangladesh-in-test-1120894.html","keywords":["ржХрзНрж░рж┐ржХрзЗржЯ","ржЦрзЗрж▓рж╛-sports news"],"creator":["TV9 Bangla"],"video_url":null,"description":"India vs Bangladesh 1st Test: рж░рзЗрж╛рж╣рж┐ржд рж╢рж░рзНржорж╛, ржмрж┐рж░рж╛ржЯ ржХрзЗрж╛рж╣рж▓рж┐, рж╢рзБржнржоржи ржЧрж┐рж▓рж░рж╛ ржнрж░рж╕рж╛ ржжрж┐рждрзЗ ржкрж╛рж░рзЗржиржирж┐ред ржпрж╢рж╕рзНржмрзА рж╣рж╛ржлрж╕рзЗржЮрзНржЪрзБрж░рж┐ ржХрж░рж▓рзЗржУ ржпржерзЗрж╖рзНржЯ ржЫрж┐рж▓ ржирж╛ред ржорзНржпрж╛ржЪрзЗ ржкрж╛рж░рзНржержХрзНржп ржЧржбрж╝рзЗ ржжрж┐рж▓ ржЕрж╢рзНржмрж┐ржи-ржЬрж╛ржбрзЗржЬрж╛ ржЬрзБржЯрж┐ржЗред ржЕрждрж┐рж░рж┐ржХрзНржд ржбрж┐ржлрзЗржирзНрж╕ ржиржпрж╝, ржмрж░ржВ ржкрж╛рж▓рзНржЯрж╛ ржЖржХрзНрж░ржоржгрзЗ ржмрж╛ржВрж▓рж╛ржжрзЗрж╢ржХрзЗ ржЪрж╛ржкрзЗ ржлрзЗрж▓рзЗржи ржЕрж╢рзНржмрж┐ржи ржУ ржЬрж╛ржбрзЗржЬрж╛ред","content":"ONLY AVAILABLE IN PAID PLANS","pubDate":"2024-09-19 15:55:05","pubDateTZ":"UTC","image_url":"https://images.tv9bangla.com/wp-content/uploads/2024/09/IND-vs-BAN-Ravindra-Jadejas-consistent-Performance-against-Bangladesh-in-Test.jpg?w=1280","source_id":"tv9bangla","source_priority":32033,"source_name":"Tv9 Bangla News","source_url":"https://tv9bangla.com","source_icon":"https://i.bytvi.com/domain_icons/tv9bangla.png","language":"bengali","country":["india"],"category":["sports"],"ai_tag":"ONLY AVAILABLE IN PROFESSIONAL AND CORPORATE PLANS","sentiment":"ONLY AVAILABLE IN PROFESSIONAL AND CORPORATE PLANS","sentiment_stats":"ONLY AVAILABLE IN PROFESSIONAL AND CORPORATE PLANS","ai_region":"ONLY AVAILABLE IN CORPORATE PLANS","ai_org":"ONLY AVAILABLE IN CORPORATE PLANS","duplicate":false},{"article_id":"574d0c91d21d933b5ba91a758fc035dd","title":"WATCH: Aussie star hits winning runs in the most alpha way possible","link":"https://www.theroar.com.au/cricket/video/watch-aussie-star-hits-winning-runs-in-the-most-alpha-way-possible-1382512/","keywords":["cricket"],"creator":["The Roar"],"video_url":null,"description":"HowтАЩs the tuck of the bat under the arm from Phoebe Litchfield too!","content":"ONLY AVAILABLE IN PAID PLANS","pubDate":"2024-09-19 16:03:58","pubDateTZ":"UTC","image_url":"https://cdn4.theroar.com.au/wp-content/uploads/2024/09/image-6362163489112-755x432.jpg","source_id":"theroar_au","source_priority":163462,"source_name":"The Roar","source_url":"https://www.theroar.com.au","source_icon":"https://i.bytvi.com/domain_icons/theroar_au.jpg","language":"english","country":["australia"],"category":["sports"],"ai_tag":"ONLY AVAILABLE IN PROFESSIONAL AND CORPORATE PLANS","sentiment":"ONLY AVAILABLE IN PROFESSIONAL AND CORPORATE PLANS","sentiment_stats":"ONLY AVAILABLE IN PROFESSIONAL AND CORPORATE PLANS","ai_region":"ONLY AVAILABLE IN CORPORATE PLANS","ai_org":"ONLY AVAILABLE IN CORPORATE PLANS","duplicate":false},{"article_id":"bb11755cc34281c39eb9de35e7dab4e9","title":"Yashasvi Jaiswal: ржнрж╛рж░ржд ржнрж╛рж▓ ржЬрж╛ржпрж╝ржЧрж╛ржпрж╝ рж░ржпрж╝рзЗржЫрзЗ, ржмрж╛ржВрж▓рж╛ржжрзЗрж╢ржХрзЗ рж╣рзБржБрж╢рж┐ржпрж╝рж╛рж░рж┐ ржжрж┐ржпрж╝рзЗ рж░рж╛ржЦрж▓рзЗржи ржпрж╢рж╕рзНржмрзА","link":"https://bengali.abplive.com/sports/cricket/ind-vs-ban-chennai-test-yashasvi-jaiswal-has-no-complaints-about-pace-friendly-chepauk-conditions-1096274","keywords":["ржХрзНрж░рж┐ржХрзЗржЯ"],"creator":["ABP Ananda"],"video_url":null,"description":"ржЪрзЗржирзНржирж╛ржЗ: ржмрж╛ржВрж▓рж╛ржжрзЗрж╢рзЗрж░ ржкрзЗрж╕рж╛рж░ рж╣рж╛рж╕рж╛ржи ржорж╛рж╣ржорзБржжрзЗрж░ рж╕рзНржпрзБржЗржВржпрж╝рзЗрж░ ржмрж┐рж╖рзЗ рждржЦржи ржнрж╛рж░рждрзАржпрж╝ ржмрзНржпрж╛ржЯрж┐ржВржпрж╝рзЗрж░ ржкрзНрж░рж╛ржг ржУрж╖рзНржарж╛ржЧрждред рж░рзЗрж╛рж╣рж┐ржд рж╢рж░рзНржорж╛ ржерзЗржХрзЗ рж╢рзБрж░рзБ ржХрж░рзЗ ржмрж┐рж░рж╛ржЯ ржХрзЗрж╛рж╣рж▓рж┐, ржПржХрзЗрж░ ржкрж░ ржПржХ рж░ржерзА ржорж╣рж╛рж░ржерзАрж░рж╛ ржкрзНржпрж╛ржнрж┐рж▓рж┐ржпрж╝ржирзЗред ржЪрзЗржирзНржирж╛ржЗржпрж╝рзЗ ржЪрж╛ржкрзЗрж░ ржорзБржЦрзЗ рждрж┐ржирж┐ ржХрж╛рж░рзНржпржд ржПржХрж╛ржЗ ржмрзБржХ ржЪрж┐рждрж┐ржпрж╝рзЗ рж▓ржбрж╝рж╛ржЗ ржХрж░рж▓рзЗржи ржкрзНрж░ржержо рж╕рзЗрж╢ржирзЗред рждрж┐ржирж┐, ржпрж╢рж╕рзНржмрзА ржЬржпрж╝рж╕ржУржпрж╝рж╛рж▓ (Yashasvi Jaiswal)ред рж░рзЗрж╛рж╣рж┐ржд рж╢рж░рзНржорж╛рж░ рж╕ржЩрзНржЧрзЗ ржЗржирж┐ржВрж╕ ржУржкрзЗржи ржХрж░рждрзЗ ржирзЗржорзЗ ржмрзГрж╣рж╕рзНржкрждрж┐ржмрж╛рж░ ржпрж┐ржирж┐ рззрззрзо ржмрж▓рзЗ рзлрзм рж░рж╛ржирзЗрж░ ржЗржирж┐ржВрж╕ ржЦрзЗрж▓рж▓рзЗржиредржкрзНрж░ржержо ржжрж┐ржирзЗрж░ рж╢рзЗрж╖рзЗ ржЖрж░ ржЕрж╢рзНржмрж┐ржи, рж░ржмрзАржирзНржжрзНрж░ ржЬрж╛ржбрзЗржЬрж╛рж░ ржкрж╛рж░рзНржЯржирж╛рж░рж╢рж┐ржкрзЗ ржнрж╛рж▓ ржЬрж╛ржпрж╝ржЧрж╛ржпрж╝ ржкрзЗрзЧржБржЫрзЗ ржЧрж┐ржпрж╝рзЗржЫрзЗ ржнрж╛рж░рждред ржЕржмрж┐ржЪрзНржЫрзЗржжрзНржп рж╕ржкрзНрждржо ржЙржЗржХрзЗржЯрзЗ рззрзпрзл рж░рж╛ржи ржпрзЗрж╛ржЧ ржХрж░рзЗржЫрзЗржи ржжрзБржЬржирзЗ (India vs Bangladesh)ред ржпржжрж┐ржУ ржкрж╛рж▓рзНржЯрж╛ рж▓ржбрж╝рж╛ржЗржпрж╝рзЗрж░ рж╢рзБрж░рзБржЯрж╛ рж╣ржпрж╝рзЗржЫрж┐рж▓ ржпрж╢рж╕рзНржмрзАрж░ ржмрзНржпрж╛ржЯрзЗржЗред ржШрж░рзЗрж░ ржорж╛ржарзЗ ржмржЫрж░рзЗрж░ ржЧрзЗрж╛ржбрж╝рж╛ржпрж╝ ржЗржВрж▓рзНржпрж╛ржирзНржбрзЗрж░ ржмрж┐рж░рзБржжрзНржзрзЗ ржЯрзЗрж╕рзНржЯ рж╕рж┐рж░рж┐ржЬрзЗ рж╕рж╛рждрж╢рзЗрж╛рж░ ржУржкрж░ рж░рж╛ржи ржХрж░рзЗ рж╕рзБржирзАрж▓ ржЧрж╛ржУрж╕рзНржХрж░рзЗрж░ рж░рзЗржХрж░рзНржб рж╕рзНржкрж░рзНрж╢ ржХрж░рзЗржЫрж┐рж▓рзЗржиред ржмрж╛ржВрж▓рж╛ржжрзЗрж╢рзЗрж░ ржмрж┐рж░рзБржжрзНржзрзЗржУ ржмрзНржпрж╛ржЯ рж╣рж╛рждрзЗ рж╕ржкрзНрж░рждрж┐ржн ржпрж╢рж╕рзНржмрзАредржХрзАржнрж╛ржмрзЗ ржмрж╛ржВрж▓рж╛ржжрзЗрж╢рзЗрж░ ржкрзЗрж╕ ржмрзЗрж╛рж▓рж┐ржВржпрж╝рзЗрж░ ржЭрж╛ржБржЭ рж╕рж╛ржорж▓рж╛рж▓рзЗржи? ржпрзЗржЦрж╛ржирзЗ ржмрж┐рж░рж╛ржЯ ржХрзЗрж╛рж╣рж▓рж┐ ржкрж░рзНржпржирзНржд ржЕржлрж╕рзНржЯрж╛ржорзНржкрзЗрж░ ржмрж╛ржЗрж░рзЗрж░ ржмрж▓рзЗ ржкрж╛рждрж╛ ржлрж╛ржБржжрзЗ ржкрж╛ ржжрж┐ржпрж╝рзЗ ржбрзНрж░рзЗрж╕рж┐ржВрж░рзБржорзЗ ржлрж┐рж░рзЗ ржЧрзЗрж▓рзЗржи? ржкрзНрж░ржержо ржжрж┐ржирзЗрж░ ржЦрзЗрж▓рж╛рж░ рж╢рзЗрж╖рзЗ рж╕рж╛ржВржмрж╛ржжрж┐ржХ ржмрзИржаржХрзЗ ржпрж╢рж╕рзНржмрзА ржмрж▓рзЗржи, 'ржПржЗ ржкрж░рж┐ржмрзЗрж╢, ржкрж░рж┐рж╕рзНржерж┐рждрж┐рждрзЗ ржмрзНржпрж╛ржЯ ржХрж░рждрзЗ ржирзЗржорзЗ ржжрж╛рж░рзБржг ржЕржнрж┐ржЬрзНржЮрждрж╛ рж╣рж▓ред ржПржЗ ржкрж░рж┐рж╕рзНржерж┐рждрж┐ ржЖржорж╛ржХрзЗ ржЖрж░ржУ рж╢ржХрзНрждрж┐рж╢рж╛рж▓рзА ржХрж░рзЗржЫрзЗред ржПржЗ ржзрж░ржирзЗрж░ ржкрж░рж┐рж╕рзНржерж┐рждрж┐рждрзЗ ржХрзАржнрж╛ржмрзЗ ржЦрзЗрж▓рж╛ ржжрж░ржХрж╛рж░, рждрж╛ ржирж┐ржпрж╝рзЗ ржЕржирзЗржХ ржХрж┐ржЫрзБ рж╢рж┐ржЦрж▓рж╛ржоред ржХрзАржнрж╛ржмрзЗ ржкрж░рж┐ржХрж▓рзНржкржирж╛ ржХрж░рзЗ ржЗржирж┐ржВрж╕ ржПржЧрж┐ржпрж╝рзЗ ржирж┐ржпрж╝рзЗ ржпрж╛ржУржпрж╝рж╛ ржпрж╛ржпрж╝, рж╕рзЗржЯрж╛ржУ рж╢рж┐ржЦрж▓рж╛ржоред'ржЖрж░ржУ ржкржбрж╝рзБржи: рж╕ржорж╛ржЬрзЗрж░ ржорж╣рж┐рж╖рж╛рж╕рзБрж░рзЗрж░рж╛ ржирж┐ржкрж╛ржд ржпрж╛ржХ, ржкрзНрж░рж╛рж░рзНржержирж╛ржпрж╝ ржмрж┐рж╢рзЗрж╖ ржЕржирзБрж╖рзНржарж╛ржи ржХрж░ржЫрзЗржи ржбрзЗрж╛ржирж╛ржпрж╢рж╕рзНржмрзА ржЖрж░ржУ ржмрж▓рзЗржи, 'ржЖржорж┐ ржжрж▓рзЗрж░ ржкрзНрж░ржпрж╝рзЗрж╛ржЬржи ржЕржирзБржпрж╛ржпрж╝рзА ржЦрзЗрж▓рж╛рж░ ржЪрзЗрж╖рзНржЯрж╛ ржХрж░рзЗржЫрж┐ред рж╕рзЗржЗ ржорждрзЗрж╛ ржирж┐ржЬрзЗрж░ ржЦрзЗрж▓рж╛ ржкрж╛рж▓рзНржЯрзЗржЫрж┐ред рж╢рзБрж░рзБрждрзЗ ржЙржЗржХрзЗржЯ ржкржбрж╝рж▓рзЗ ржЖржорж┐ ржХрзАржнрж╛ржмрзЗ ржмрзНржпрж╛ржЯрж┐ржВ ржХрж░ржм? ржпржЦржи рж░рж╛ржи ржЖрж╕ржЫрзЗ, ржХрзАржнрж╛ржмрзЗ ржмрзНржпрж╛ржЯрж┐ржВ ржХрж░ржм?'ржЯрзЗрж╕рзНржЯрзЗ ржкржЮрзНржЪржо рж╣рж╛ржлрж╕рзЗржЮрзНржЪрзБрж░рж┐ ржХрж░рзЗржЫрзЗржи ржпрж╢рж╕рзНржмрзАред рждржмрзЗ ржЗржВрж▓рзНржпрж╛ржирзНржбрзЗрж░ ржмрж┐рж░рзБржжрзНржзрзЗ ржпрзЗржнрж╛ржмрзЗ ржЖржЧрзНрж░рж╛рж╕рзА ржмрзНржпрж╛ржЯрж┐ржВ ржХрж░рзЗржЫрж┐рж▓рзЗржи, ржмрж╛ржВрж▓рж╛ржжрзЗрж╢рзЗрж░ ржмрж┐рж░рзБржжрзНржзрзЗ ржЪрзЗржирзНржирж╛ржЗржпрж╝рзЗ рж╕рзЗржнрж╛ржмрзЗ ржмрзНржпрж╛ржЯрж┐ржВ ржХрж░рзЗржиржирж┐ред ржмрж░ржВ ржЕржирзЗржХ рж╕рждрж░рзНржХ ржжрзЗржЦрж┐ржпрж╝рзЗржЫрзЗ ржорзБржорзНржмржЗржпрж╝рзЗрж░ ржмрзНржпрж╛ржЯрж╛рж░ржХрзЗред ржкржЮрзНржЪрж╛рж╢рзЗрж░ ржХржо рж╕рзНржЯрзНрж░ржЗржХ рж░рзЗржЯ рж░рзЗржЦрзЗ рж░рж╛ржи ржХрж░рзЗржЫрзЗржиредржжрзНржмрж┐рждрзАржпрж╝ рж╕рзЗрж╢ржирзЗ ржирж╛рж╣рж┐ржж рж░рж╛ржирж╛рж░ ржЪржХрж┐ржд ржмрж╛ржЙржирзНрж╕рж╛рж░рзЗ рждрж┐ржирж┐ ржЖржЙржЯ рж╣ржиред ржпржжрж┐ржУ ржнрж╛рж░ржд ржнрж╛рж▓ ржЬрж╛ржпрж╝ржЧрж╛ржпрж╝ ржЖржЫрзЗ ржмрж▓рзЗржЗ ржоржирзЗ ржХрж░рзЗржи ржпрж╢рж╕рзНржмрзАред ржмрж▓рзЗржЫрзЗржи, 'рж╢рзБрж░рзБрж░ ржжрж┐ржХрзЗ ржкрж┐ржЪрзЗ ржкржбрж╝рзЗ ржмрж▓ ржирзАржЪрзБ рж╣ржЪрзНржЫрж┐рж▓, ржиржбрж╝рж╛ржЪржбрж╝рж╛ ржХрж░ржЫрж┐рж▓ред рждрж╛ржЗ ржЖржорж░рж╛ рж╕ржоржпрж╝ ржирж┐ржпрж╝рзЗ ржЦрзЗрж▓ржЫрж┐рж▓рж╛ржоред рждржмрзЗ рж╢рзЗрж╖ рж╕рзЗрж╢ржирзЗ ржнрж╛рж▓ ржЧрждрж┐рждрзЗ рж░рж╛ржи ржЙржарзЗржЫрзЗред ржПржЗ ржорзБрж╣рзВрж░рзНрждрзЗ ржЖржорж░рж╛ ржнрж╛рж▓ ржЬрж╛ржпрж╝ржЧрж╛ржпрж╝ рж░ржпрж╝рзЗржЫрж┐ред'ржЖрж░ржУ ржкржбрж╝рзБржи: ржЖрж░ ржЬрж┐ ржХрж░ ржХрж╛ржгрзНржбрзЗ ржХрзБрж░рзБржЪрж┐ржХрж░ ржнрж╛рж╖рж╛ржпрж╝ ржЖржХрзНрж░ржоржг, рж╕рж╛ржЗржмрж╛рж░ ржХрзНрж░рж╛ржЗржо рж╢рж╛ржЦрж╛ржпрж╝ ржЕржнрж┐ржпрзЗрж╛ржЧ рж╕рзЗрзЧрж░ржнрзЗрж░ржЖржкржирж╛рж░ ржкржЫржирзНржжрзЗрж░ ржЦржмрж░ ржЖрж░ ржЖржкржбрзЗржЯ ржкрж╛ржмрзЗржи ржЖржкржирж╛рж░ ржкржЫржирзНржжрзЗрж░ ржЪрзНржпрж╛ржЯрж┐ржВ ржкрзНрж▓рзНржпрж╛ржЯржлрж░рзНржо рж╣рзЗрж╛ржпрж╝рж╛ржЯрж╕ ржЕрзНржпрж╛ржкрзЗржУред ржпрзБржХрзНржд рж╣рзЗрж╛ржи ABP Ananda рж╣рзЗрж╛ржпрж╝рж╛ржЯрж╕ ржЕрзНржпрж╛ржк ржЪрзНржпрж╛ржирзЗрж▓рзЗред","content":"ONLY AVAILABLE IN PAID PLANS","pubDate":"2024-09-19 16:03:31","pubDateTZ":"UTC","image_url":"https://feeds.abplive.com/onecms/images/uploaded-images/2024/09/19/bc22ea7663385fad4cf3ac88d4567bbb172676008002450_original.jpg","source_id":"abplive","source_priority":7754,"source_name":"Abp News","source_url":"http://abplive.com","source_icon":"https://i.bytvi.com/domain_icons/abplive.jpg","language":"bengali","country":["india"],"category":["sports"],"ai_tag":"ONLY AVAILABLE IN PROFESSIONAL AND CORPORATE PLANS","sentiment":"ONLY AVAILABLE IN PROFESSIONAL AND CORPORATE PLANS","sentiment_stats":"ONLY AVAILABLE IN PROFESSIONAL AND CORPORATE PLANS","ai_region":"ONLY AVAILABLE IN CORPORATE PLANS","ai_org":"ONLY AVAILABLE IN CORPORATE PLANS","duplicate":false},{"article_id":"039a585fe6e294a7ee804eaa8cbe0bcd","title":"WATCH: Sarfaraz Ahmed Sledges Babar Azam, Pakistan Captain Scores Century In Reply During Champions Cup","link":"https://zeenews.india.com/cricket/watch-sarfaraz-ahmed-sledges-babar-azam-pakistan-captain-scores-century-in-reply-during-champions-cup-2795727.html","keywords":null,"creator":["Zee News"],"video_url":null,"description":"Babar Azam scored a century in the Champions Cup after Sarfaraz Ahmed sledged him during the game.","content":"ONLY AVAILABLE IN PAID PLANS","pubDate":"2024-09-19 16:03:00","pubDateTZ":"UTC","image_url":"https://english.cdn.zeenews.com/sites/default/files/styles/zm_700x400/public/2024/09/19/1516746-ind-8.png?im=Resize%3D%28400%29","source_id":"zeenews","source_priority":5319,"source_name":"Zee News","source_url":"http://zeenews.india.com","source_icon":"https://i.bytvi.com/domain_icons/zeenews.png","language":"english","country":["india"],"category":["sports"],"ai_tag":"ONLY AVAILABLE IN PROFESSIONAL AND CORPORATE PLANS","sentiment":"ONLY AVAILABLE IN PROFESSIONAL AND CORPORATE PLANS","sentiment_stats":"ONLY AVAILABLE IN PROFESSIONAL AND CORPORATE PLANS","ai_region":"ONLY AVAILABLE IN CORPORATE PLANS","ai_org":"ONLY AVAILABLE IN CORPORATE PLANS","duplicate":false},{"article_id":"ecc0bc8e7a1bd92f220daa521e76ed98","title":"IND vs BAN: 'рдЪреАрддреЗ рдХреА рдЪрд╛рд▓, рдмрд╛рдЬ рдХреА рдирдЬрд░ рдФрд░ рдЬрдбреНрдбреВ рдХреА..' рдЬрдбреЗрдЬрд╛ рдХреА рддрд╛рд░реАрдл рдореЗрдВ рд╢рд╛рдпрд░ рдмрдиреЗ рд╕реВрд░реНрдпрд╛, рдлреИрдВрд╕ рдХрд░ рд░рд╣реЗ рд╡рд╛рд╣-рд╡рд╛рд╣","link":"https://zeenews.india.com/hindi/sports/cricket/suryakumar-yadav-unique-way-to-praised-r-ashwin-century-ravindra-jadeja-ind-vs-ban-1st-test/2437929","keywords":null,"creator":["Zee News рд╣рд┐рдиреНрджреА","Zee News Hindi"],"video_url":null,"description":"India vs Bangladesh: рдЬрдбреЗрдЬрд╛-рдЕрд╢реНрд╡рд┐рди рдХреА рдЬреЛрдбрд╝реА рдХреА рджрд╣рд╢рдд рджреБрдирд┐рдпрд╛рднрд░ рдХреА рдЯреАрдореЛрдВ рдореЗрдВ рд╣реИ. рджреЛрдиреЛрдВ рджрд┐рдЧреНрдЧрдЬреЛрдВ рдиреЗ рдЕрдкрдиреА рдлрд┐рд░рдХреА рд╕реЗ рдХрдИ рдмрдбрд╝реЗ рдзреБрд░рдВрдзрд░реЛрдВ рдХреЛ рдЪрд╛рд░реЛ рдЦрд╛рдиреЗ рдЪрд┐рдд рдХрд░ рджрд┐рдпрд╛. рд▓реЗрдХрд┐рди 19 рд╕рд┐рддрдВрдмрд░ рдХреЛ рдпреЗ рдЬреЛрдбрд╝реА рдмрд▓реНрд▓реЗ рд╕реЗ рд░рдВрдЧ рдЬрдорд╛рддреА рдирдЬрд░ рдЖрдИ. рд╡рд┐рд░рд╛рдЯ-рд░реЛрд╣рд┐рдд рдХреЗ рд╡рд┐рдХреЗрдЯ рдХреЗ рдмрд╛рдж рдЬреАрдд рдХреЗ рд╕рдкрдиреЗ рджреЗрдЦрдиреЗ рд▓рдЧреА рдмрд╛рдВрдЧреНрд▓рд╛рджреЗрд╢ рдХреЛ рдЕрд╢реНрд╡рд┐рди-рдЬрдбреЗрдЬрд╛ рдиреЗ рдирд╛рдХреЛ рдЪрдиреЗ рдЪрдмрд╡рд╛ рджрд┐рдП. рдЬрд┐рд╕рдХреЗ рдмрд╛рдж рд╕реВрд░реНрдпрд╛ рдХреА рдЬреБрдмрд╛рдВ рд╕реЗ рднреА рд╢рд╛рдпрд░реА рдирд┐рдХрд▓рдиреЗ рд▓рдЧреА.","content":"ONLY AVAILABLE IN PAID PLANS","pubDate":"2024-09-19 16:00:12","pubDateTZ":"UTC","image_url":"https://hindi.cdn.zeenews.com/hindi/sites/default/files/2024/09/19/3246715-ashwin-and-jadeja.png?im=FitAndFill%3D%281200%2C900%29","source_id":"zeenews","source_priority":5319,"source_name":"Zee News","source_url":"http://zeenews.india.com","source_icon":"https://i.bytvi.com/domain_icons/zeenews.png","language":"hindi","country":["india"],"category":["sports"],"ai_tag":"ONLY AVAILABLE IN PROFESSIONAL AND CORPORATE PLANS","sentiment":"ONLY AVAILABLE IN PROFESSIONAL AND CORPORATE PLANS","sentiment_stats":"ONLY AVAILABLE IN PROFESSIONAL AND CORPORATE PLANS","ai_region":"ONLY AVAILABLE IN CORPORATE PLANS","ai_org":"ONLY AVAILABLE IN CORPORATE PLANS","duplicate":false},{"article_id":"03c43ad6ab1b6f73df5795430c67387f","title":"Shreyas Iyer goes for duck again, Sanju Samson quick fires with 89 against India B in Duleep Trophy 2024","link":"https://www.india.com/sports/shreyas-iyer-goes-for-duck-again-sanju-samson-quick-fires-with-89-against-india-b-in-duleep-trophy-2024-7259900/","keywords":["ks bharat","mukesh kumar","sanju samson","duleep trophy 2024","rahul chahar","shreyas iyer","sports","cricket","ricky bhui","devdutt padikkal","navdeep saini"],"creator":null,"video_url":null,"description":"Indian wicketkeeper-batter Sanju Samson rescued India D with a brilliant unbeaten fifty against India B in the Duleep Trophy 2024 final-round fixtures on Thursday.","content":"ONLY AVAILABLE IN PAID PLANS","pubDate":"2024-09-19 15:59:59","pubDateTZ":"UTC","image_url":"https://static.india.com/wp-content/themes/icom/images/default-big.svg","source_id":"india","source_priority":8067,"source_name":"India","source_url":"https://www.india.com","source_icon":"https://i.bytvi.com/domain_icons/india.png","language":"english","country":["india"],"category":["sports"],"ai_tag":"ONLY AVAILABLE IN PROFESSIONAL AND CORPORATE PLANS","sentiment":"ONLY AVAILABLE IN PROFESSIONAL AND CORPORATE PLANS","sentiment_stats":"ONLY AVAILABLE IN PROFESSIONAL AND CORPORATE PLANS","ai_region":"ONLY AVAILABLE IN CORPORATE PLANS","ai_org":"ONLY AVAILABLE IN CORPORATE PLANS","duplicate":false},{"article_id":"af0b6e1ff6e4a3df5e3e24c09c42467e","title":"тАШркдрлЗркирлЗ 40 ркУрк╡рк░ рк░ркорк╡рк╛ ркжрлЛтАЩ ... рк╕рк░рклрк░рк╛ркЭ ркЕрк╣рлЗркоркжрлЗ ркХрк░рлНркпрлЛ ркЯрлНрк░рлЛрк▓ ркЕркирлЗ ркмрк╛ркмрк░ ркЖркЭркорлЗ рклркЯркХрк╛рк░рлА 30ркорлА рк╕ркжрлА","link":"https://tv9gujarati.com/sports/cricket-news/sarfaraz-ahmed-troll-babar-azam-hit-list-a-century-in-champions-odi-cup-pakistan-1094074.html","keywords":["рк╕рлНрккрлЛрк░рлНркЯрк╕ ркирлНркпрлВркЭ","ркХрлНрк░рк┐ркХрлЗркЯ ркирлНркпрлВркЭ"],"creator":["Smit Chauhan"],"video_url":null,"description":"ркмрк╛ркмрк░ ркЖркЭрко ркЪрлЗркорлНрккрк┐ркпркирлНрк╕ ркХрккркорк╛ркВ рк╕рк╛рк░рлА ркИркирк┐ркВркЧ рк░ркорлА рк░рк╣рлНркпрлЛ ркЫрлЗ ркЕркирлЗ рк╣рк╡рлЗ ркдрлЗркгрлЗ рк╕ркжрлА рккркг рклркЯркХрк╛рк░рлА ркЫрлЗ. ркмрк╛ркмрк░ ркЖркЭркорлЗ ркдрлЗркирлА 30ркорлА рк▓рк┐рк╕рлНркЯ A рк╕ркжрлА рклркЯркХрк╛рк░рлА рк╣ркдрлА. ркЬрлЛ ркХрлЗ ркдрлЗркирлА рк╕ркжрлА ркжрк░ркорк┐ркпрк╛рки рккрк╛ркХрк┐рк╕рлНркдрк╛ркиркирк╛ рккрлВрк░рлНрк╡ ркХрлЗрккрлНркЯрки рк╕рк░рклрк░рк╛ркЭ ркЕрк╣рлЗркоркжрлЗ ркдрлЗркирлЗ ркЯрлНрк░рлЛрк▓ ркХрк░рк╡рк╛ркирлЛ рккрлНрк░ркпрк╛рк╕ ркХрк░рлНркпрлЛ рк╣ркдрлЛ.","content":"ONLY AVAILABLE IN PAID PLANS","pubDate":"2024-09-19 15:58:40","pubDateTZ":"UTC","image_url":"https://images.tv9gujarati.com/wp-content/uploads/2024/09/Babar-Azam-2.jpg?w=1280","source_id":"tv9gujarati","source_priority":75214,"source_name":"Tv9 Gujarati","source_url":"https://tv9gujarati.com","source_icon":"https://i.bytvi.com/domain_icons/tv9gujarati.jpg","language":"gujarati","country":["india"],"category":["sports"],"ai_tag":"ONLY AVAILABLE IN PROFESSIONAL AND CORPORATE PLANS","sentiment":"ONLY AVAILABLE IN PROFESSIONAL AND CORPORATE PLANS","sentiment_stats":"ONLY AVAILABLE IN PROFESSIONAL AND CORPORATE PLANS","ai_region":"ONLY AVAILABLE IN CORPORATE PLANS","ai_org":"ONLY AVAILABLE IN CORPORATE PLANS","duplicate":false},{"article_id":"b3c4604cbc6f7ee9f4346eccf4c4ff36","title":"IND vs BAN 1st Test: ржЕрж╢рзНржмрж┐ржи-ржЬрж╛ржбрзЗржЬрж╛ржпрж╝ ржорзБржЧрзНржз рж╕ржЪрж┐ржи, рждрж╛рж░ржХрж╛ ржЕрж▓рж░рж╛ржЙржирзНржбрж╛рж░ржжрзЗрж░ ржнрзВржпрж╝рж╕рзА ржкрзНрж░рж╢ржВрж╕рж╛ржпрж╝ ржнрж░рж╛рж▓рзЗржи 'ржорж╛рж╕рзНржЯрж╛рж░ ржмрзНрж▓рж╛рж╕рзНржЯрж╛рж░'","link":"https://bengali.abplive.com/sports/cricket/r-ashwin-ravindra-jadeja-brillant-partnership-rescues-ind-vs-ban-1st-test-sachin-tendulkar-lauds-1096273","keywords":["ржХрзНрж░рж┐ржХрзЗржЯ"],"creator":["ABP Ananda"],"video_url":null,"description":"ржЪрзЗржирзНржирж╛ржЗ: ржмрж╛ржВрж▓рж╛ржжрзЗрж╢рзЗрж░ ржЪрзЗржирзНржирж╛ржЗржпрж╝рзЗ ржкрзНрж░ржержо ржЯрзЗрж╕рзНржЯрзЗ (IND vs BAN 1st Test) рждрж░рзБржг ржлрж╛рж╕рзНржЯ ржмрзЗрж╛рж▓рж╛рж░ржжрзЗрж░ ржмрж┐рж░рзБржжрзНржзрзЗ ржПржХрзЗ ржПржХрзЗ ржпржЦржи ржЯрж┐ржо ржЗржирзНржбрж┐ржпрж╝рж╛рж░ ржорж╣рж╛рждрж╛рж░ржХрж╛рж░рж╛ рж╕рж╛ржЬржШрж░рзЗ ржлрж┐рж░рзЗ ржЧрж┐ржпрж╝рзЗржЫрзЗржи, ржпржЦржи ржЯрж┐ржо ржЗржирзНржбрж┐ржпрж╝рж╛ ржжрзБ'рж╢рзЗрж╛ рж░рж╛ржирзЗрж░ ржЧржгрзНржбрж┐ржУ ржкрж╛рж░ ржХрж░рждрзЗ ржкрж╛рж░ржмрзЗ ржХрж┐ ржирж╛, рж╕рзЗржЗ ржирж┐ржпрж╝рзЗ рж╕ржВрж╢ржпрж╝ рждрзИрж░рж┐ рж╣ржпрж╝рзЗржЫрж┐рж▓, рждржЦржиржЗ ржмрзНржпрж╛ржЯ рж╣рж╛рждрзЗ рж░рзБржЦрзЗ ржжрж╛ржБржбрж╝рж╛ржи ржжрзБржЗ ржЕрж▓рж░рж╛ржЙржирзНржбрж╛рж░ред рж░ржмрзАржирзНржжрзНрж░ ржЬрж╛ржбрзЗржЬрж╛ (Ravindra Jadeja) ржУ ржЖрж░ ржЕрж╢рзНржмрж┐ржи (R Ashwin) ржнрж╛рж░рждржХрзЗ ржжрзБ'рж╢рзЗрж╛ ржкрж╛рж░ ржХрж░рж╛ржирзЗрж╛ ржиржпрж╝, ржкрзНрж░ржержо ржжрж┐ржирзЗрж░ ржЦрзЗрж▓рж╛рж╢рзЗрж╖рзЗ рзйрзлрзж рж░рж╛ржирзЗрж░ ржжрзЗрж╛рж░ржЧрзЗрж╛ржбрж╝рж╛ржпрж╝ ржкрзЗрзЧржБржЫрзЗ ржжрж┐рж▓рзЗржиред ржЬрзБржбрж╝рж▓рзЗржи рззрзпрзл рж░рж╛ржиредржжрж┐ржирж╢рзЗрж╖рзЗ ржжрзБржЗ рждрж╛рж░ржХрж╛ржЗ ржХрж┐ржирзНрждрзБ ржЕржкрж░рж╛ржЬрж┐ржд рж░ржпрж╝рзЗржЫрзЗржиред ржЕрж╢рзНржмрж┐ржирзЗрж░ рж╕ржВржЧрзНрж░рж╣ рззрзжрзи, ржЬрж╛ржбрзЗржЬрж╛рж░ ржЭрзБрж▓рж┐рждрзЗ рзорзм рж░рж╛ржиред ржжрзБржЗ рждрж╛рж░ржХрж╛рж░ рззрзпрзл рж░рж╛ржи рж╕ржкрзНрждржо ржЙржЗржХрзЗржЯрзЗ ржЪрж┐ржкржХрзЗ рж╕рж░рзНржмржХрж╛рж▓рзАржи рж░рзЗржХрж░рзНржбред рждрж╛ржБрж░рж╛ ржХрж╛рж▓ ржХрж┐ржирзНрждрзБ ржирж┐ржЬрзЗржжрзЗрж░ ржПржЗ рж╕рзНржорж░ржгрзАржпрж╝ ржкрж╛рж░рзНржЯржирж╛рж░рж╢рж┐ржкржХрзЗ ржЖрж░ржУ ржмрж╛ржбрж╝рж╛рждрзЗ ржкрж╛рж░рзЗржиред ржЕрж╢рзНржмрж┐ржи ржУ ржЬрж╛ржбрзЗржЬрж╛рж░ ржПржЗ ржкрж╛рж░рзНржЯржирж╛рж░рж╢рж┐ржк ржЫрж╛ржбрж╝рж╛ ржнрж╛рж░рждрзАржпрж╝ ржжрж▓ ржпрзЗ ржмрж┐рж░рж╛ржЯ ржмрж┐ржкрж╛ржХрзЗ ржкржбрж╝ржд, рждрж╛ ржмрж▓рж╛рж░ ржЕржмржХрж╛рж╢ рж░рж╛ржЦрзЗ ржирж╛редржжрзБржЗ ржЕржнрж┐ржЬрзНржЮ рждрж╛рж░ржХрж╛рж░ ржмрзНржпрж╛ржЯрж┐ржВржпрж╝рзЗ ржорзБржЧрзНржз рж╕рзНржмржпрж╝ржВ 'ржХрзНрж░рж┐ржХрзЗржЯ ржИрж╢рзНржмрж░'ржУред ржкрзНрж░ржержо ржжрж┐ржирзЗрж░ ржЦрзЗрж▓рж╛рж╢рзЗрж╖рзЗ рж╕ржЪрж┐ржи рждрзЗржирзНржбрзБрж▓ржХрж░ (Sachin Tendulkar) ржирж┐ржЬрзЗрж░ рж╕рзЗрж╛рж╢рзНржпрж╛рж▓ ржорж┐ржбрж┐ржпрж╝рж╛ржпрж╝ ржЬрж╛ржбрзЗржЬрж╛ ржУ ржЕрж╢рзНржмрж┐ржирзЗрж░ ржкрзНрж░рж╢ржВрж╕рж╛ ржХрж░рзЗржиред 'ржорж╛рж╕рзНржЯрж╛рж░ ржмрзНрж▓рж╛рж╕рзНржЯрж╛рж░'-рж░ ржорждрзЗ ржжрзБржЗ рждрж╛рж░ржХрж╛ ржорзНржпрж╛ржЪрзЗ ржнрж╛рж░рждржХрзЗ ржПржЧрж┐ржпрж╝рзЗ ржжрж┐ржпрж╝рзЗржЫрзЗржиред рждрж┐ржирж┐ рж▓рзЗржЦрзЗржи, 'рж╣рждрж╛рж╢рж╛ ржерзЗржХрзЗ ржжрж╛ржкржЯред ржЕрж╢рзНржмрж┐ржи ржУ ржЬрж╛ржбрзЗржЬрж╛ ржжрзБрж░ржирзНржд ржЗржирж┐ржВрж╕ ржЖржмрж╛рж░ ржорзНржпрж╛ржЪрзЗрж░ ржорзЗрж╛ржбрж╝ ржнрж╛рж░рждрзЗрж░ ржжрж┐ржХрзЗ ржШрзБрж░рж┐ржпрж╝рзЗ ржжрж┐ржпрж╝рзЗржЫрзЗред ржПржЗ ржЕрж▓рж░рж╛ржЙржирзНржб ржжржХрзНрж╖рждрж╛ржЯрж╛ ржЕржкрж░рж┐рж╣рж╛рж░рзНржпред ржжрзБрж░ржирзНржд ржкрж╛рж░рзНржЯржирж╛рж░рж╢рж┐ржк ржЧржбрж╝рзЗржЫред' From despair to domination! @ashwinravi99 and @imjadeja's knocks have turned the tide for India once again. This all-round brilliance is invaluable. Super partnership boys. ЁЯСПЁЯП╝#INDvBAN pic.twitter.com/eZNW6yOr8VтАФ Sachin Tendulkar (@sachin_rt) September 19, 2024ржнрж╛рж░рждрзАржпрж╝ ржЯржк ржЕрж░рзНржбрж╛рж░рзЗ ржпрж╢рж╕рзНржмрзА ржЬржпрж╝рж╕ржУржпрж╝рж╛рж▓ рж╣рж╛ржлрж╕рзЗржЮрзНржЪрзБрж░рж┐ ржХрж░рж▓рзЗржУ, рж░рзЗрж╛рж╣рж┐рждрж░рж╛ рж╕ржорзНржкрзВрж░рзНржг ржмрзНржпрж░рзНржеред ржЬржпрж╝рж╕ржУржпрж╝рж╛рж▓ ржПржмржВ ржЛрж╖ржн ржкржирзНрже рж╣рж╛ржлрж╕рзЗржЮрзНржЪрзБрж░рж┐рж░ ржкрж╛рж░рзНржЯржирж╛рж░рж╢рж┐ржк ржЧржбрж╝рж▓рзЗржУ, ржкрж░ржкрж░ ржЙржЗржХрзЗржЯ рж╣рж╛рж░рж╛ржпрж╝ ржнрж╛рж░рждред ржХрзЗржПрж▓ рж░рж╛рж╣рзБрж▓ ржпржЦржи рззрзм рж░рж╛ржирзЗ рж╕рж╛ржЬржШрж░рзЗ ржлрзЗрж░рзЗржи рждржЦржи ржнрж╛рж░рждрзЗрж░ рж╕рзНржХрзЗрж╛рж░ ржЫржпрж╝ ржЙржЗржХрзЗржЯрзЗ рззрзкрзк рж░рж╛ржиред ржжрж┐ржирж╢рзЗрж╖рзЗ ржнрж╛рж░рждрзЗрж░ рж╕рзНржХрзЗрж╛рж░ ржЫржпрж╝ ржЙржЗржХрзЗржЯрзЗрж░ ржмрж┐ржирж┐ржоржпрж╝рзЗ рзйрзйрзп рж░рж╛ржиред ржЕрж╢рзНржмрж┐ржи ржПржХрзЗржмрж╛рж░рзЗржЗ рж╢рзБрж░рзБ ржерзЗржХрзЗ ржирзЗржорзЗ ржжрзБрж░ржирзНржд ржЖржЧрзНрж░рж╛рж╕рзА ржмрзНржпрж╛ржЯрж┐ржВ ржХрж░рзЗржиред ржирж┐ржЬрзЗрж░ рж╖рж╖рзНржа рж╢рждрж░рж╛ржи ржкрзВрж░ржг ржХрж░рзЗржи рждрж┐ржирж┐ред ржЬрж╛ржбрзЗржЬрж╛ржУ рж╕рзЗржЮрзНржЪрзБрж░рж┐ рж╣рж╛ржБржХрж╛рждрзЗ ржкрж╛рж░рзЗржи ржХрж┐ ржирж╛, рж╕рзЗржЯрж╛ржЗ ржжрзЗржЦрж╛рж░ ржмрж┐рж╖ржпрж╝ред ржЖржкржирж╛рж░ ржкржЫржирзНржжрзЗрж░ ржЦржмрж░ ржЖрж░ ржЖржкржбрзЗржЯ ржкрж╛ржмрзЗржи ржЖржкржирж╛рж░ ржкржЫржирзНржжрзЗрж░ ржЪрзНржпрж╛ржЯрж┐ржВ ржкрзНрж▓рзНржпрж╛ржЯржлрж░рзНржо рж╣рзЗрж╛ржпрж╝рж╛ржЯрж╕ ржЕрзНржпрж╛ржкрзЗржУред ржпрзБржХрзНржд рж╣рзЗрж╛ржи ABP Ananda рж╣рзЗрж╛ржпрж╝рж╛ржЯрж╕ ржЕрзНржпрж╛ржк ржЪрзНржпрж╛ржирзЗрж▓рзЗредржЖрж░ржУ ржкржбрж╝рзБржи: ржЯрзЗрж╕рзНржЯ ржЗрждрж┐рж╣рж╛рж╕рзЗ ржПрж░ ржЖржЧрзЗ ржХржЦржиржУ рж╣ржпрж╝ржирж┐, ржЪрзЗржирзНржирж╛ржЗржпрж╝рзЗ рж╣рж╛ржлрж╕рзЗржЮрзНржЪрзБрж░рж┐ рж╣рж╛ржБржХрж┐ржпрж╝рзЗ ржПржоржиржЗ ржХрзГрждрж┐рждрзНржм ржЧржбрж╝рж▓рзЗржи ржпрж╢рж╕рзНржмрзА","content":"ONLY AVAILABLE IN PAID PLANS","pubDate":"2024-09-19 15:58:08","pubDateTZ":"UTC","image_url":"https://feeds.abplive.com/onecms/images/uploaded-images/2024/09/19/471cd0b36a7eddb07d70faf378b059c91726761215705507_original.jpg","source_id":"abplive","source_priority":7754,"source_name":"Abp News","source_url":"http://abplive.com","source_icon":"https://i.bytvi.com/domain_icons/abplive.jpg","language":"bengali","country":["india"],"category":["sports"],"ai_tag":"ONLY AVAILABLE IN PROFESSIONAL AND CORPORATE PLANS","sentiment":"ONLY AVAILABLE IN PROFESSIONAL AND CORPORATE PLANS","sentiment_stats":"ONLY AVAILABLE IN PROFESSIONAL AND CORPORATE PLANS","ai_region":"ONLY AVAILABLE IN CORPORATE PLANS","ai_org":"ONLY AVAILABLE IN CORPORATE PLANS","duplicate":false},{"article_id":"79b613a0a4bf939547875a8ee86dbf40","title":"рдЪреЗрдиреНрдирдИ рдЯреЗрд╕реНрдЯ рдореЗрдВ рдЯреАрдо рдЗрдВрдбрд┐рдпрд╛ рдХреА рдЬреАрдд рдкрд╣рд▓реЗ рд╣реА рджрд┐рди рд╣реБрдИ рддрдп! рдорд┐рд▓ рдЧрдИ рдореБрдХрд╛рдмрд▓рд╛ рдирд╛ рд╣рд╛рд░рдиреЗ рдХреА рдЧрд╛рд░рдВрдЯреА","link":"https://www.tv9hindi.com/sports/cricket-news/team-india-never-lost-any-match-whenever-r-ashwin-has-scored-century-2839516.html","keywords":null,"creator":["TV9 Bharatvarsh"],"video_url":null,"description":"рдЪреЗрдиреНрдирдИ рдЯреЗрд╕реНрдЯ рдХреЗ рдкрд╣рд▓реЗ рджрд┐рди рдЯреАрдо рдЗрдВрдбрд┐рдпрд╛ рдиреЗ 6 рд╡рд┐рдХреЗрдЯ рдХреЗ рдиреБрдХрд╕рд╛рди рдкрд░ 339 рд░рди рдмрдирд╛рдП. рд░рд╡реАрдВрджреНрд░ рдЬрдбреЗрдЬрд╛ рдФрд░ рдЖрд░ рдЕрд╢реНрд╡рд┐рди рдХреА рдУрд░ рд╕реЗ рдХрдорд╛рд▓ рдХреА рдкрд╛рд░рд┐рдпрд╛рдВ рджреЗрдЦрдиреЗ рдХреЛ рдорд┐рд▓реА. рдпреЗ рджреЛрдиреЛрдВ рдмрд▓реНрд▓реЗрдмрд╛рдЬ рдЕрднреА рднреА рдирд╛рдмрд╛рдж рд╣реИрдВ рдФрд░ рдЦреЗрд▓ рдХреЗ рджреВрд╕рд░реЗ рджрд┐рди рдЯреАрдо рдХреЛ рдмрдбрд╝реЗ рд╕реНрдХреЛрд░ рддрдХ рдкрд╣реБрдВрдЪрд╛рдиреЗ рдХреЗ рд▓рд┐рдП рдореИрджрд╛рди рдкрд░ рдЙрддрд░реЗрдВрдЧреЗ.","content":"ONLY AVAILABLE IN PAID PLANS","pubDate":"2024-09-19 15:57:29","pubDateTZ":"UTC","image_url":"https://images.tv9hindi.com/wp-content/uploads/2024/09/r-ashwin-1.jpg","source_id":"tv9bharatvarsh","source_priority":40538658,"source_name":"Tv9 Bharatvarsh","source_url":"https://www.tv9hindi.com","source_icon":null,"language":"hindi","country":["india"],"category":["sports"],"ai_tag":"ONLY AVAILABLE IN PROFESSIONAL AND CORPORATE PLANS","sentiment":"ONLY AVAILABLE IN PROFESSIONAL AND CORPORATE PLANS","sentiment_stats":"ONLY AVAILABLE IN PROFESSIONAL AND CORPORATE PLANS","ai_region":"ONLY AVAILABLE IN CORPORATE PLANS","ai_org":"ONLY AVAILABLE IN CORPORATE PLANS","duplicate":false},{"article_id":"4e14361ad73be6754a94a6f1ea345ad2","title":"Bangladesh A complete T20 WC tune-up with series win in Sri Lanka","link":"https://www.thedailystar.net/sports/cricket/news/bangladesh-complete-t20-wc-tune-series-win-sri-lanka-3707241","keywords":null,"creator":null,"video_url":null,"description":"Bangladesh WomenтАЩs A team bowlers stood out in the final T20 of the five-match series against Sri Lankan A to help their side register an eight-wicket win and clinch a 4-1 series win at the Colts in Colombo today.","content":"ONLY AVAILABLE IN PAID PLANS","pubDate":"2024-09-19 15:55:06","pubDateTZ":"UTC","image_url":"https://www.thedailystar.net/sites/default/files/styles/big_202/public/images/2024/09/19/jdgklfk.jpg","source_id":"thedailystar","source_priority":32093,"source_name":"The Daily Star","source_url":"https://www.thedailystar.com","source_icon":"https://i.bytvi.com/domain_icons/thedailystar.png","language":"english","country":["bangladesh"],"category":["sports"],"ai_tag":"ONLY AVAILABLE IN PROFESSIONAL AND CORPORATE PLANS","sentiment":"ONLY AVAILABLE IN PROFESSIONAL AND CORPORATE PLANS","sentiment_stats":"ONLY AVAILABLE IN PROFESSIONAL AND CORPORATE PLANS","ai_region":"ONLY AVAILABLE IN CORPORATE PLANS","ai_org":"ONLY AVAILABLE IN CORPORATE PLANS","duplicate":false},{"article_id":"c1907499e505bfaa41dfe0f375440c9e","title":"IND vs BAN: ржмрж╛ржШ ржжрзЗржЦрж▓рзЗржЗ рж╢рж┐ржХрж╛рж░рзЗ ржмрзЗрж░рзЗрж╛ржи! ржЖржмрж╛рж░ржУ тАШрждрж▓рзЗрж╛ржпрж╝рж╛рж░-ржмрж╛ржЬрж┐тАЩ ржЬрж╛ржбрзЗржЬрж╛рж░","link":"https://tv9bangla.com/sports/cricket-news/ind-vs-ban-ravindra-jadejas-consistent-performance-against-bangladesh-in-test-1120894.html","keywords":["ржХрзНрж░рж┐ржХрзЗржЯ","ржЦрзЗрж▓рж╛-sports news"],"creator":["TV9 Bangla"],"video_url":null,"description":"India vs Bangladesh 1st Test: рж░рзЗрж╛рж╣рж┐ржд рж╢рж░рзНржорж╛, ржмрж┐рж░рж╛ржЯ ржХрзЗрж╛рж╣рж▓рж┐, рж╢рзБржнржоржи ржЧрж┐рж▓рж░рж╛ ржнрж░рж╕рж╛ ржжрж┐рждрзЗ ржкрж╛рж░рзЗржиржирж┐ред ржпрж╢рж╕рзНржмрзА рж╣рж╛ржлрж╕рзЗржЮрзНржЪрзБрж░рж┐ ржХрж░рж▓рзЗржУ ржпржерзЗрж╖рзНржЯ ржЫрж┐рж▓ ржирж╛ред ржорзНржпрж╛ржЪрзЗ ржкрж╛рж░рзНржержХрзНржп ржЧржбрж╝рзЗ ржжрж┐рж▓ ржЕрж╢рзНржмрж┐ржи-ржЬрж╛ржбрзЗржЬрж╛ ржЬрзБржЯрж┐ржЗред ржЕрждрж┐рж░рж┐ржХрзНржд ржбрж┐ржлрзЗржирзНрж╕ ржиржпрж╝, ржмрж░ржВ ржкрж╛рж▓рзНржЯрж╛ ржЖржХрзНрж░ржоржгрзЗ ржмрж╛ржВрж▓рж╛ржжрзЗрж╢ржХрзЗ ржЪрж╛ржкрзЗ ржлрзЗрж▓рзЗржи ржЕрж╢рзНржмрж┐ржи ржУ ржЬрж╛ржбрзЗржЬрж╛ред","content":"ONLY AVAILABLE IN PAID PLANS","pubDate":"2024-09-19 15:55:05","pubDateTZ":"UTC","image_url":"https://images.tv9bangla.com/wp-content/uploads/2024/09/IND-vs-BAN-Ravindra-Jadejas-consistent-Performance-against-Bangladesh-in-Test.jpg?w=1280","source_id":"tv9bangla","source_priority":32033,"source_name":"Tv9 Bangla News","source_url":"https://tv9bangla.com","source_icon":"https://i.bytvi.com/domain_icons/tv9bangla.png","language":"bengali","country":["india"],"category":["sports"],"ai_tag":"ONLY AVAILABLE IN PROFESSIONAL AND CORPORATE PLANS","sentiment":"ONLY AVAILABLE IN PROFESSIONAL AND CORPORATE PLANS","sentiment_stats":"ONLY AVAILABLE IN PROFESSIONAL AND CORPORATE PLANS","ai_region":"ONLY AVAILABLE IN CORPORATE PLANS","ai_org":"ONLY AVAILABLE IN CORPORATE PLANS","duplicate":false}]}