{"newsArray":[{"article_id":"97250519d26dfaaa38bcafc650196e9b","title":"ICC Rankings: यशस्वी जायसवाल को बड़ा फायदा, टी20 वर्ल्ड कप से पहले आईसीसी रैंकिंग में छठे पायदान पर पहुंचे","link":"https://www.prabhasakshi.com/cricket/icc-rankings-yashasvi-jaiswal-spot-in-no-6-ahead-of-t20-world-cup-know-all-detalis","keywords":null,"creator":["प्रभासाक्षी न्यूज नेटवर्क"],"video_url":null,"description":"टी20 वर्ल्ड कप की मेजबानी के लिए अमेरिका और वेस्टइंडीज तैयार है। इस टूर्नामेंट का आगाज 2 जून से हो रहा है। वहीं, रोहित शर्मा की अगुवाई वाली भारतीय टीम अपने वर्ल्ड कप अभियान की शुरुआत आयरलैंड के खिलाफ 5 जून को करेगी। इसके बाद भारत और पाकिस्तान की टीमें 9 जून को आमने-सामने होगी। बहरहाल, इस टूर्नामेंट से पहले टीम इंडिया के लिए अच्छी खबर है। दरअसल, भारतीय टीम के ओपनर यशस्वी जायसवाल ने आईसीसी रैंकिंग्स में बड़ी छलांग लगाई है। यशस्वी आईसीसी टी20 रैंकिंग्स में छठे पायदान पर पहुंच गए हैं। हालांकि, भारतीय टीम के दिग्गज बल्लेबाज सूर्यकुमार यादव पहले नंबर पर बने हुए हैं। इसके अलावा ऑस्ट्रेलिया के ओपनर ट्रेविस हेड को आईसीसी रैंकिंग्स में बड़ा फायदा मिला है। दरअसल, ट्रेविस हेड रैंकिंग में 16वें नंबर पर काबिज हैं। साथ ही वेस्टइंडीज के जॉनसन चार्ल्स और ऑस्ट्रेलिया के टिम डेविड की रैंकिंग में सुधा हुआ है। भारतीय टीम के ताबड़तोड़ फिनिशर रिंकू सिंह और आईसीसी टी20 रैंकिंग्स में 32वें नंबर पर काबिज है। वहीं आईसीसी टी20 रैंकिंग्स में भारतीय टीम पहले नंबर काबिज है। इसे अलावा ऑस्ट्रेलिया 257 रेटिंग प्वाइंट्स के साथ दूसरे स्थान पर है। टीम इंडिया के 264 रेटिंग प्वाइंट्स हैं। इस तरह भारत और ऑस्ट्रेलिया के 7 रेटिंग प्वॉइंट्स का अंतर है।","content":"ONLY AVAILABLE IN PAID PLANS","pubDate":"2024-05-30 13:36:00","image_url":"https://images.prabhasakshi.com/2024/5/30/yashasvi-jaiswal_large_1906_150.webp","source_id":"prabhasakshi","source_priority":4167978,"source_url":"https://www.prabhasakshi.com","source_icon":"https://i.bytvi.com/domain_icons/prabhasakshi.png","language":"hindi","country":["india"],"category":["sports"],"ai_tag":"ONLY AVAILABLE IN PROFESSIONAL AND CORPORATE PLANS","sentiment":"ONLY AVAILABLE IN PROFESSIONAL AND CORPORATE PLANS","sentiment_stats":"ONLY AVAILABLE IN PROFESSIONAL AND CORPORATE PLANS","ai_region":"ONLY AVAILABLE IN CORPORATE PLANS","ai_org":"ONLY AVAILABLE IN CORPORATE PLANS"},{"article_id":"b2a6cbb1273ff857080a4199e0d227ed","title":"T20 World Cup 2024: अमेरिका ही क्यों? नहीं मिला कोई और देश; टी20 वर्ल्ड कप का फ्यूचर दांव पर","link":"https://www.abplive.com/sports/cricket/why-usa-t20-world-cup-2024-host-united-states-of-america-with-west-indies-know-full-reason-2702732","keywords":["क्रिकेट"],"creator":["नीरज शर्मा"],"video_url":null,"description":"T20 World Cup 2024: कुछ साल पहले तक किसी ने सुना भी नहीं था कि यूएसए की भी क्रिकेट टीम है. फिर 2021 में इंटरनेशनल क्रिकेट काउंसिल (ICC) ने बताया कि 2024 का वर्ल्ड कप यूएसए और वेस्टइंडीज में खेला जाएगा. वेस्टइंडीज पहले से क्रिकेट में एक जाना-माना नाम है, लेकिन पिछले 3 साल के अंदर यूएसए के अंदर विश्व स्तरीय मैदान बनाए गए हैं. आगामी वर्ल्ड कप की शुरुआत 2 जून से होगी, जिसमें 20 टीम भाग लेंगी. चूंकि अमेरिका में क्रिकेट ज्यादा फेमस नहीं है, इसलिए सवाल उठता है कि आखिर आईसीसी ने यहां वर्ल्ड कप जैसा बड़ा टूर्नामेंट करवाने का फैसला क्यों लिया है.प्रयोग के तौर पर यूएसए का हुआ है चयन!चूंकि यूएसए में क्रिकेट फैंस की संख्या बहुत कम है, इसलिए मैदानों में सीटें भरना स्टेडियम के मैनेजमेंट के लिए बहुत जटिल काम हो सकता है. विशेष रूप से छोटी टीमों के मैचों में क्राउड कैसे बटोरा जाएगा. इसी समस्या से निजात पाने के लिए केवल 16 मैचों को यूएसए में करवाने का फैसला लिया गया. टूर्नामेंट में कुल 20 टीम हैं, जिनके बीच फाइनल तक 55 मुकाबले खेले जाएंगे. इनमें से 16 मैच यूएसए और बाकी 39 मुकाबले वेस्टइंडीज में खेले जाएंगे, जहां क्रिकेट पहले ही फेमस है.ओलंपिक में हो रही है क्रिकेट की वापसीकुछ समय पहले घोषणा की गई थी कि 2028 ओलंपिक्स में क्रिकेट को वापस लाया जा रहा है. तो भला 2028 ओलंपिक्स में क्रिकेट की वापसी से टी20 वर्ल्ड कप 2024 को यूएसए में करवाने का क्या मेल? बता दें कि 2028 के ओलंपिक खेल अमेरिका के लॉस एंजेलिस में होने हैं और तब तक आईसीसी, क्रिकेट के खेल को यूएस के अंदर प्रमोट करने का हर संभव प्रयास करेगी.पश्चिमी देशों से अछूता रहा है क्रिकेटक्रिकेट का जन्मदाता इंग्लैंड है और उसके बाद जिन भी देशों पर ब्रिटिश राज रहा, वहां-वहां क्रिकेट के खेल को भी लोकप्रियता रही. आज क्रिकेट एशिया, यूरोप, ऑस्ट्रेलिया और अफ्रीकी महाद्वीप में भी खूब लोकप्रिय बन चुका है. मगर पश्चिमी देशों से क्रिकेट अब भी अछूता रहा है. ऐसे में यूएसए को एक मोहरे के तौर पर इस्तेमाल किया जा सकता है. यदि यूएसए में क्रिकेट अपनी पैठ बनाने में सफल रहा तो मेक्सिको, ब्राजील और अर्जेंटीना जैसे देश भी क्रिकेट में आगे बढ़ने के लिए प्रोत्साहित हो सकते हैं.वर्ल्ड कप के लिए चुने गए यूएसए के 3 मैदानटी20 वर्ल्ड कप 2024 के लिए 9 मैदान चुने गए हैं, जिनमें से 6 कैरेबियाई द्वीपों पर हैं और बाकी तीन यूएसए में हैं. नसाऊ काउंटी स्टेडियम (न्यूयॉर्क), सेंट्रल ब्रोवार्ड पार्क (फ्लॉरिडा) और ग्रैंड प्रेयेर स्टेडियम (टेक्सास), यूएसए के वो तीन मैदान हैं जिनमें वर्ल्ड कप के मैच खेले जाएंगे. टूर्नामेंट का सबसे पहला मैच 1 जून को यूएसए और कनाडा के बीच ग्रैंड प्रेयेर स्टेडियम में खेला जाएगा. वहीं भारतीय टीम अपना पहला मैच न्यूयॉर्क में स्थित नसाऊ स्टेडियम में खेलेगी.यह भी पढ़ें:टी20 वर्ल्ड कप से पहले नेपाल टीम पर आया संकट, जमकर हुआ था हंगामा; फिर भी संदीप लामिछाने को नहीं मिला वीजा","content":"ONLY AVAILABLE IN PAID PLANS","pubDate":"2024-05-30 13:35:04","image_url":"https://feeds.abplive.com/onecms/images/uploaded-images/2024/05/30/472d76c7e44bd8307a8db06fe05d9b3c1717075952340975_original.jpg","source_id":"abplive","source_priority":10959,"source_url":"http://abplive.com","source_icon":"https://i.bytvi.com/domain_icons/abplive.jpg","language":"hindi","country":["india"],"category":["sports"],"ai_tag":"ONLY AVAILABLE IN PROFESSIONAL AND CORPORATE PLANS","sentiment":"ONLY AVAILABLE IN PROFESSIONAL AND CORPORATE PLANS","sentiment_stats":"ONLY AVAILABLE IN PROFESSIONAL AND CORPORATE PLANS","ai_region":"ONLY AVAILABLE IN CORPORATE PLANS","ai_org":"ONLY AVAILABLE IN CORPORATE PLANS"},{"article_id":"6c5439095e5ecbba9f439f1543a755e0","title":"T20 World Cup: নিউ ইয়র্কে ভারতীয় শিবিরে যোগ দিলেন রিঙ্কু, কথা রাখতে পারবেন তো নাইট তারকা?","link":"https://bengali.abplive.com/sports/cricket/t20-world-cup-2024-ipl-winner-rinku-singh-links-up-with-indian-squad-in-new-york-1070695","keywords":["ক্রিকেট"],"creator":["ABP Ananda"],"video_url":null,"description":"নিউ ইয়র্ক: টি-টোয়েন্টি বিশ্বকাপের দামামা বেজে গিয়েছে। সব দলই পৌঁছে গিয়েছে প্রায়। ওয়ার্ম আপ ম্য়াচও খেলা হচ্ছে। ভারতীয় দলও আগামী ১ জুন নিজেদের একমাত্র ওয়ার্ম আপ ম্য়াচ খেলতে নামবে বাংলাদেশের বিরুদ্ধে। তার আগে দলের সঙ্গে যোগ দিলেন আইপিএল জয়ী কেকেআর দলের সদস্য রিঙ্কু সিংহ। গত ২৬ মে সানরাইজার্স হায়দরাবাদের বিরুদ্ধে ফাইনালে জয় ছিনিয়ে নিয়েছিল কলকাতা নাইট রাইডার্স। তৃতীয়বারের জন্য আইপিএল খেতাব জিতে নেয় কেকেআর। ট্রফি হাতে নিয়ে, ট্রফি জড়িয়ে ধরে রিঙ্কুর বিভিন্ন ছবি ভাইরাল হয়েছে সোশ্যাল মিডিয়ায়। তিনি নিজেই বলেছিলেন যে এভাবেই বিশ্বকাপ ট্রফিও জিততে চান। এবার সেই লক্ষ্য নিয়েই নিউ ইয়র্কে পা রাখলেন তরুণ বাঁহাতি এই মিডল অর্ডার ব্যাটার। ১৫ সদস্যের যে ভারতীয় দল টি-টোয়েন্টি বিশ্বকাপের জন্য ঘোষণা করা হয়েছে, তাতে রিঙ্কু নেই। তিনি রিজার্ভ প্লেয়ার হিসেবে দলের সঙ্গে থাকবেন। মূল দলের কোনও প্লেয়ার যদি চোটের কারণে ছিটকে যান, তবেই রিঙ্কুকে অন্তর্ভূক্ত করা হবে দলে। এক্ষেত্রে কেকেআর তারকার কাছে কিন্তু নেট সেশন ও প্রস্তুতি ম্য়াচ বেশ গুরুত্বপূর্ণ।","content":"ONLY AVAILABLE IN PAID PLANS","pubDate":"2024-05-30 13:34:59","image_url":"https://feeds.abplive.com/onecms/images/uploaded-images/2024/05/30/ffc322542ea30b174b9a0cd9fa34aab41717075883802206_original.jpg","source_id":"abplive","source_priority":10959,"source_url":"http://abplive.com","source_icon":"https://i.bytvi.com/domain_icons/abplive.jpg","language":"bengali","country":["india"],"category":["sports"],"ai_tag":"ONLY AVAILABLE IN PROFESSIONAL AND CORPORATE PLANS","sentiment":"ONLY AVAILABLE IN PROFESSIONAL AND CORPORATE PLANS","sentiment_stats":"ONLY AVAILABLE IN PROFESSIONAL AND CORPORATE PLANS","ai_region":"ONLY AVAILABLE IN CORPORATE PLANS","ai_org":"ONLY AVAILABLE IN CORPORATE PLANS"},{"article_id":"69050ab332dfbc9c68eb1bab64868ec4","title":"இந்திய அணிக்கு ஐசிசி சொன்ன மகிழ்ச்சியான செய்தி","link":"https://tamil.news18.com/sports/cricket-icc-world-cup-t20-team-india-holding-1st-place-in-icc-t20-teams-ranking-1471748.html","keywords":["கிரிக்கெட்"],"creator":null,"video_url":null,"description":"பேட்ஸ்மேன்கள் தரவரிசையில் இந்தியாவின் சூர்ய குமார் யாதவ் 861 புள்ளிகளுடன் முதலிடத்தில் உள்ளார்.","content":"ONLY AVAILABLE IN PAID PLANS","pubDate":"2024-05-30 13:34:38","image_url":"https://images.news18.com/tamil/uploads/2024/05/news-18-images-54-2024-05-f35b0b349a98691fea522107c9f92896-3x2.jpg","source_id":"tamil_news18","source_priority":5991,"source_url":"https://tamil.news18.com","source_icon":"https://i.bytvi.com/domain_icons/tamil_news18.png","language":"tamil","country":["india"],"category":["sports"],"ai_tag":"ONLY AVAILABLE IN PROFESSIONAL AND CORPORATE PLANS","sentiment":"ONLY AVAILABLE IN PROFESSIONAL AND CORPORATE PLANS","sentiment_stats":"ONLY AVAILABLE IN PROFESSIONAL AND CORPORATE PLANS","ai_region":"ONLY AVAILABLE IN CORPORATE PLANS","ai_org":"ONLY AVAILABLE IN CORPORATE PLANS"},{"article_id":"da19e734fca2c3aee36f6a367e986ad2","title":"क्या वर्ल्ड कप देखने के लिए खराब करनी होगी नींद? कब शुरू होंगे मुकाबले","link":"https://hindi.news18.com/cricket/t20-world-cup-2024-when-will-the-matches-start-where-to-watch-free-live-streaming-live-telecast-icc-t20-wc-matches-in-india-8366678.html","keywords":["क्रिकेट"],"creator":["News18 Hindi"],"video_url":null,"description":"टी20 वर्ल्ड कप 2024 का आगाज 2 जून से हो जाएगा. चूंकि इस बार टी20 विश्व कप के मुकाबले अमेरिका और विंडीज में खेले जाएंगे, ऐसे में लोग जानने को उत्सुक हैं कि क्या उन्हें रातों की नींद खराब करनी पड़ेगी? भारत, विंडीज और अमेरिका के समय में काफी अंतर है. विश्व कप में 55 मैच खेले जाएंगे. 20 टीमों को 4 ग्रुप में बांटा गया है. ग्रुप स्टेज में 24 मैच खेले जाएंगे.","content":"ONLY AVAILABLE IN PAID PLANS","pubDate":"2024-05-30 13:34:07","image_url":"https://images.news18.com/ibnkhabar/uploads/2024/05/t20-world-cup-2024-05-27cc2c810b58a770ad3a1fd372cda46a-3x2.jpg","source_id":"hindinews18","source_priority":6509,"source_url":"https://hindi.news18.com","source_icon":null,"language":"hindi","country":["india"],"category":["sports"],"ai_tag":"ONLY AVAILABLE IN PROFESSIONAL AND CORPORATE PLANS","sentiment":"ONLY AVAILABLE IN PROFESSIONAL AND CORPORATE PLANS","sentiment_stats":"ONLY AVAILABLE IN PROFESSIONAL AND CORPORATE PLANS","ai_region":"ONLY AVAILABLE IN CORPORATE PLANS","ai_org":"ONLY AVAILABLE IN CORPORATE PLANS"},{"article_id":"1525bc826ab13a4501dcd314c56104d9","title":"Youll Have to Take Me...: Riyan Parag Confident of Playing For India in Future","link":"https://www.news18.com/videos/cricket/riyan-parag-rajasthan-royals-ipl-2024-india-future-8910588.html","keywords":["cricket"],"creator":null,"video_url":null,"description":"Rajasthan Royals star Riyan Parag said he has the belief that someday he will be a part of the senior Indian men’s team.","content":"ONLY AVAILABLE IN PAID PLANS","pubDate":"2024-05-30 13:32:11","image_url":"https://images.news18.com/ibnlive/uploads/2024/05/whatsapp-image-2024-05-30-at-17.52.07_bbdcdee2-2024-05-f1fac8d63503ced5ebcdeb52d6fe7d73-3x2.jpg","source_id":"news18","source_priority":6644,"source_url":"https://www.news18.com","source_icon":"https://i.bytvi.com/domain_icons/news18.png","language":"english","country":["india"],"category":["sports"],"ai_tag":"ONLY AVAILABLE IN PROFESSIONAL AND CORPORATE PLANS","sentiment":"ONLY AVAILABLE IN PROFESSIONAL AND CORPORATE PLANS","sentiment_stats":"ONLY AVAILABLE IN PROFESSIONAL AND CORPORATE PLANS","ai_region":"ONLY AVAILABLE IN CORPORATE PLANS","ai_org":"ONLY AVAILABLE IN CORPORATE PLANS"},{"article_id":"15bb6c1ac6553a3c0f5fc5086b15a075","title":"Sir Vivian Richards Stadium","link":"https://www.indiatoday.in/sports/t20-world-cup-2024/story/west-indies-venue-sir-vivian-richards-stadium-north-sound-antigua-fixtures-full-details-2545828-2024-05-30?utm_source=rss","keywords":null,"creator":null,"video_url":null,"description":"Sir Vivian Richards Stadium","content":"ONLY AVAILABLE IN PAID PLANS","pubDate":"2024-05-30 13:28:39","image_url":"https://akm-img-a-in.tosshub.com/indiatoday/images/story/202405/sir-vivian-richards-stadium-300907999-16x9_0.jpg?VersionId=9xhlmmBCL5WRsOwMpoaqQ_CZyZJIo2r0","source_id":"indiatoday","source_priority":2885,"source_url":"https://www.indiatoday.in","source_icon":"https://i.bytvi.com/domain_icons/indiatoday.png","language":"english","country":["india"],"category":["sports"],"ai_tag":"ONLY AVAILABLE IN PROFESSIONAL AND CORPORATE PLANS","sentiment":"ONLY AVAILABLE IN PROFESSIONAL AND CORPORATE PLANS","sentiment_stats":"ONLY AVAILABLE IN PROFESSIONAL AND CORPORATE PLANS","ai_region":"ONLY AVAILABLE IN CORPORATE PLANS","ai_org":"ONLY AVAILABLE IN CORPORATE PLANS"},{"article_id":"0635b67c31b72475f9fb448c2ef086b8","title":"Jio Cinema पर आईपीएल की दर्शक संख्या में 53 प्रतिशत का उछाल","link":"https://www.prabhasakshi.com/cricket/53-percent-jump-in-ipl-viewership-on-jio-cinema","keywords":null,"creator":["प्रभासाक्षी न्यूज नेटवर्क"],"video_url":null,"description":"रिलायंस के स्वामित्व वाले ओटीटी मंच जियो सिनेमा पर आईपीएल टूर्नामेंट के मुकाबले देखने वाले दर्शकों की कुल संख्या 53 प्रतिशत उछलकर 2,600 करोड़ हो गई। टाटा आईपीएल मैचों के डिजिटल प्रसारण का अधिकार जियो सिनेमा के पास है। दो महीने तक चला यह टूर्नामेंट 26 मई को समाप्त हुआ है। जियो सिनेमा ने एक बयान में कहा कि आईपीएल के इस सत्र में रिकॉर्ड 35,000 करोड़ मिनट ‘वॉच-टाइम’ दर्ज किया गया है। इस दौरान प्रति दर्शक औसत समय पिछले सत्र के 60 मिनट से बढ़कर 75 मिनट तक पहुंच गया। जियो सिनेमा ने कहा, “पहले मैच में अभूतपूर्व दर्शक संख्या मिलने के बाद इसे आगे भी कायम रखते हुए लगभग 38 प्रतिशत वृद्धि हुई। सत्र का समापन लगभग 62 करोड़ दर्शक संख्या के साथ हुआ।”इस सत्र में जियो सिनेमा के पास रिकॉर्ड 28 प्रायोजक और 1,400 से ज्यादा विज्ञापनदाता थे।रिलायंस-समर्थित वायकॉम18 ने जून, 2022 में 20,500 करोड़ रुपये मेंआईपीएल के डिजिटल प्रसारण अधिकार हासिल किए थे। भारतीय उपमहाद्वीप के लिए टेलीविजन प्रसारण अधिकार डिज्नी स्टार के पास हैं। इसका आंकड़ा अभी नहीं आया है।","content":"ONLY AVAILABLE IN PAID PLANS","pubDate":"2024-05-30 13:27:00","image_url":"https://images.prabhasakshi.com/2024/5/30/jio-cinema_large_1857_153.webp","source_id":"prabhasakshi","source_priority":4167978,"source_url":"https://www.prabhasakshi.com","source_icon":"https://i.bytvi.com/domain_icons/prabhasakshi.png","language":"hindi","country":["india"],"category":["sports"],"ai_tag":"ONLY AVAILABLE IN PROFESSIONAL AND CORPORATE PLANS","sentiment":"ONLY AVAILABLE IN PROFESSIONAL AND CORPORATE PLANS","sentiment_stats":"ONLY AVAILABLE IN PROFESSIONAL AND CORPORATE PLANS","ai_region":"ONLY AVAILABLE IN CORPORATE PLANS","ai_org":"ONLY AVAILABLE IN CORPORATE PLANS"},{"article_id":"23906a17491df5aaa3e91258bcf6aa17","title":"At Hardik's wedding, this cricketer took on the role of performing Natasa Stankovic's kanyadaan","link":"https://www.dnaindia.com/cricket/report-at-hardik-wedding-this-cricketer-took-on-the-role-of-performing-natasa-stankovic-kanyadaan-3091284","keywords":["sports","cricket"],"creator":["Chankesh Rao"],"video_url":null,"description":"Serbian model Natasa and Pandya tied the knot in Udaipur in 2023. They had a wedding that combined Hindu and Christian traditions.","content":"ONLY AVAILABLE IN PAID PLANS","pubDate":"2024-05-30 13:25:00","image_url":"https://cdn.dnaindia.com/sites/default/files/styles/third/public/2024/05/30/2636265-untitled-design-69.jpg","source_id":"dnaindia","source_priority":18388,"source_url":"https://www.dnaindia.com","source_icon":null,"language":"english","country":["india"],"category":["sports"],"ai_tag":"ONLY AVAILABLE IN PROFESSIONAL AND CORPORATE PLANS","sentiment":"ONLY AVAILABLE IN PROFESSIONAL AND CORPORATE PLANS","sentiment_stats":"ONLY AVAILABLE IN PROFESSIONAL AND CORPORATE PLANS","ai_region":"ONLY AVAILABLE IN CORPORATE PLANS","ai_org":"ONLY AVAILABLE IN CORPORATE PLANS"},{"article_id":"6e233ffad5a97db48ea3dce8ba718246","title":"Five top Batters with most runs in T20 World Cup","link":"https://www.cricketcountry.com/hi/photos/five-top-batters-with-most-runs-in-t20-world-cup-1154293/","keywords":null,"creator":["Akhilesh Tripathi"],"video_url":null,"description":"टी-20 विश्व कप में सबसे ज्यादा रन बनाने का रिकॉर्ड भारतीय खिलाड़ी विराट कोहली के नाम है. सर्वाधिक रन बनाने वाले बल्लेबाजों की लिस्ट में टॉप-5 में कोहली के अलावा रोहित शर्मा भी शामिल हैं. The post Five top Batters with most runs in T20 World Cup appeared first on Cricket Country.","content":"ONLY AVAILABLE IN PAID PLANS","pubDate":"2024-05-30 13:20:32","image_url":"https://www.cricketcountry.com/wp-content/uploads/2024/05/Virat-Kohli-29-1024x576.jpg","source_id":"cricketcountry","source_priority":104348,"source_url":"https://www.cricketcountry.com","source_icon":"https://i.bytvi.com/domain_icons/cricketcountry.jpg","language":"english","country":["india"],"category":["sports"],"ai_tag":"ONLY AVAILABLE IN PROFESSIONAL AND CORPORATE PLANS","sentiment":"ONLY AVAILABLE IN PROFESSIONAL AND CORPORATE PLANS","sentiment_stats":"ONLY AVAILABLE IN PROFESSIONAL AND CORPORATE PLANS","ai_region":"ONLY AVAILABLE IN CORPORATE PLANS","ai_org":"ONLY AVAILABLE IN CORPORATE PLANS"},{"article_id":"97250519d26dfaaa38bcafc650196e9b","title":"ICC Rankings: यशस्वी जायसवाल को बड़ा फायदा, टी20 वर्ल्ड कप से पहले आईसीसी रैंकिंग में छठे पायदान पर पहुंचे","link":"https://www.prabhasakshi.com/cricket/icc-rankings-yashasvi-jaiswal-spot-in-no-6-ahead-of-t20-world-cup-know-all-detalis","keywords":null,"creator":["प्रभासाक्षी न्यूज नेटवर्क"],"video_url":null,"description":"टी20 वर्ल्ड कप की मेजबानी के लिए अमेरिका और वेस्टइंडीज तैयार है। इस टूर्नामेंट का आगाज 2 जून से हो रहा है। वहीं, रोहित शर्मा की अगुवाई वाली भारतीय टीम अपने वर्ल्ड कप अभियान की शुरुआत आयरलैंड के खिलाफ 5 जून को करेगी। इसके बाद भारत और पाकिस्तान की टीमें 9 जून को आमने-सामने होगी। बहरहाल, इस टूर्नामेंट से पहले टीम इंडिया के लिए अच्छी खबर है। दरअसल, भारतीय टीम के ओपनर यशस्वी जायसवाल ने आईसीसी रैंकिंग्स में बड़ी छलांग लगाई है। यशस्वी आईसीसी टी20 रैंकिंग्स में छठे पायदान पर पहुंच गए हैं। हालांकि, भारतीय टीम के दिग्गज बल्लेबाज सूर्यकुमार यादव पहले नंबर पर बने हुए हैं। इसके अलावा ऑस्ट्रेलिया के ओपनर ट्रेविस हेड को आईसीसी रैंकिंग्स में बड़ा फायदा मिला है। दरअसल, ट्रेविस हेड रैंकिंग में 16वें नंबर पर काबिज हैं। साथ ही वेस्टइंडीज के जॉनसन चार्ल्स और ऑस्ट्रेलिया के टिम डेविड की रैंकिंग में सुधा हुआ है। भारतीय टीम के ताबड़तोड़ फिनिशर रिंकू सिंह और आईसीसी टी20 रैंकिंग्स में 32वें नंबर पर काबिज है। वहीं आईसीसी टी20 रैंकिंग्स में भारतीय टीम पहले नंबर काबिज है। इसे अलावा ऑस्ट्रेलिया 257 रेटिंग प्वाइंट्स के साथ दूसरे स्थान पर है। टीम इंडिया के 264 रेटिंग प्वाइंट्स हैं। इस तरह भारत और ऑस्ट्रेलिया के 7 रेटिंग प्वॉइंट्स का अंतर है।","content":"ONLY AVAILABLE IN PAID PLANS","pubDate":"2024-05-30 13:36:00","image_url":"https://images.prabhasakshi.com/2024/5/30/yashasvi-jaiswal_large_1906_150.webp","source_id":"prabhasakshi","source_priority":4167978,"source_url":"https://www.prabhasakshi.com","source_icon":"https://i.bytvi.com/domain_icons/prabhasakshi.png","language":"hindi","country":["india"],"category":["sports"],"ai_tag":"ONLY AVAILABLE IN PROFESSIONAL AND CORPORATE PLANS","sentiment":"ONLY AVAILABLE IN PROFESSIONAL AND CORPORATE PLANS","sentiment_stats":"ONLY AVAILABLE IN PROFESSIONAL AND CORPORATE PLANS","ai_region":"ONLY AVAILABLE IN CORPORATE PLANS","ai_org":"ONLY AVAILABLE IN CORPORATE PLANS"},{"article_id":"b2a6cbb1273ff857080a4199e0d227ed","title":"T20 World Cup 2024: अमेरिका ही क्यों? नहीं मिला कोई और देश; टी20 वर्ल्ड कप का फ्यूचर दांव पर","link":"https://www.abplive.com/sports/cricket/why-usa-t20-world-cup-2024-host-united-states-of-america-with-west-indies-know-full-reason-2702732","keywords":["क्रिकेट"],"creator":["नीरज शर्मा"],"video_url":null,"description":"T20 World Cup 2024: कुछ साल पहले तक किसी ने सुना भी नहीं था कि यूएसए की भी क्रिकेट टीम है. फिर 2021 में इंटरनेशनल क्रिकेट काउंसिल (ICC) ने बताया कि 2024 का वर्ल्ड कप यूएसए और वेस्टइंडीज में खेला जाएगा. वेस्टइंडीज पहले से क्रिकेट में एक जाना-माना नाम है, लेकिन पिछले 3 साल के अंदर यूएसए के अंदर विश्व स्तरीय मैदान बनाए गए हैं. आगामी वर्ल्ड कप की शुरुआत 2 जून से होगी, जिसमें 20 टीम भाग लेंगी. चूंकि अमेरिका में क्रिकेट ज्यादा फेमस नहीं है, इसलिए सवाल उठता है कि आखिर आईसीसी ने यहां वर्ल्ड कप जैसा बड़ा टूर्नामेंट करवाने का फैसला क्यों लिया है.प्रयोग के तौर पर यूएसए का हुआ है चयन!चूंकि यूएसए में क्रिकेट फैंस की संख्या बहुत कम है, इसलिए मैदानों में सीटें भरना स्टेडियम के मैनेजमेंट के लिए बहुत जटिल काम हो सकता है. विशेष रूप से छोटी टीमों के मैचों में क्राउड कैसे बटोरा जाएगा. इसी समस्या से निजात पाने के लिए केवल 16 मैचों को यूएसए में करवाने का फैसला लिया गया. टूर्नामेंट में कुल 20 टीम हैं, जिनके बीच फाइनल तक 55 मुकाबले खेले जाएंगे. इनमें से 16 मैच यूएसए और बाकी 39 मुकाबले वेस्टइंडीज में खेले जाएंगे, जहां क्रिकेट पहले ही फेमस है.ओलंपिक में हो रही है क्रिकेट की वापसीकुछ समय पहले घोषणा की गई थी कि 2028 ओलंपिक्स में क्रिकेट को वापस लाया जा रहा है. तो भला 2028 ओलंपिक्स में क्रिकेट की वापसी से टी20 वर्ल्ड कप 2024 को यूएसए में करवाने का क्या मेल? बता दें कि 2028 के ओलंपिक खेल अमेरिका के लॉस एंजेलिस में होने हैं और तब तक आईसीसी, क्रिकेट के खेल को यूएस के अंदर प्रमोट करने का हर संभव प्रयास करेगी.पश्चिमी देशों से अछूता रहा है क्रिकेटक्रिकेट का जन्मदाता इंग्लैंड है और उसके बाद जिन भी देशों पर ब्रिटिश राज रहा, वहां-वहां क्रिकेट के खेल को भी लोकप्रियता रही. आज क्रिकेट एशिया, यूरोप, ऑस्ट्रेलिया और अफ्रीकी महाद्वीप में भी खूब लोकप्रिय बन चुका है. मगर पश्चिमी देशों से क्रिकेट अब भी अछूता रहा है. ऐसे में यूएसए को एक मोहरे के तौर पर इस्तेमाल किया जा सकता है. यदि यूएसए में क्रिकेट अपनी पैठ बनाने में सफल रहा तो मेक्सिको, ब्राजील और अर्जेंटीना जैसे देश भी क्रिकेट में आगे बढ़ने के लिए प्रोत्साहित हो सकते हैं.वर्ल्ड कप के लिए चुने गए यूएसए के 3 मैदानटी20 वर्ल्ड कप 2024 के लिए 9 मैदान चुने गए हैं, जिनमें से 6 कैरेबियाई द्वीपों पर हैं और बाकी तीन यूएसए में हैं. नसाऊ काउंटी स्टेडियम (न्यूयॉर्क), सेंट्रल ब्रोवार्ड पार्क (फ्लॉरिडा) और ग्रैंड प्रेयेर स्टेडियम (टेक्सास), यूएसए के वो तीन मैदान हैं जिनमें वर्ल्ड कप के मैच खेले जाएंगे. टूर्नामेंट का सबसे पहला मैच 1 जून को यूएसए और कनाडा के बीच ग्रैंड प्रेयेर स्टेडियम में खेला जाएगा. वहीं भारतीय टीम अपना पहला मैच न्यूयॉर्क में स्थित नसाऊ स्टेडियम में खेलेगी.यह भी पढ़ें:टी20 वर्ल्ड कप से पहले नेपाल टीम पर आया संकट, जमकर हुआ था हंगामा; फिर भी संदीप लामिछाने को नहीं मिला वीजा","content":"ONLY AVAILABLE IN PAID PLANS","pubDate":"2024-05-30 13:35:04","image_url":"https://feeds.abplive.com/onecms/images/uploaded-images/2024/05/30/472d76c7e44bd8307a8db06fe05d9b3c1717075952340975_original.jpg","source_id":"abplive","source_priority":10959,"source_url":"http://abplive.com","source_icon":"https://i.bytvi.com/domain_icons/abplive.jpg","language":"hindi","country":["india"],"category":["sports"],"ai_tag":"ONLY AVAILABLE IN PROFESSIONAL AND CORPORATE PLANS","sentiment":"ONLY AVAILABLE IN PROFESSIONAL AND CORPORATE PLANS","sentiment_stats":"ONLY AVAILABLE IN PROFESSIONAL AND CORPORATE PLANS","ai_region":"ONLY AVAILABLE IN CORPORATE PLANS","ai_org":"ONLY AVAILABLE IN CORPORATE PLANS"},{"article_id":"6c5439095e5ecbba9f439f1543a755e0","title":"T20 World Cup: নিউ ইয়র্কে ভারতীয় শিবিরে যোগ দিলেন রিঙ্কু, কথা রাখতে পারবেন তো নাইট তারকা?","link":"https://bengali.abplive.com/sports/cricket/t20-world-cup-2024-ipl-winner-rinku-singh-links-up-with-indian-squad-in-new-york-1070695","keywords":["ক্রিকেট"],"creator":["ABP Ananda"],"video_url":null,"description":"নিউ ইয়র্ক: টি-টোয়েন্টি বিশ্বকাপের দামামা বেজে গিয়েছে। সব দলই পৌঁছে গিয়েছে প্রায়। ওয়ার্ম আপ ম্য়াচও খেলা হচ্ছে। ভারতীয় দলও আগামী ১ জুন নিজেদের একমাত্র ওয়ার্ম আপ ম্য়াচ খেলতে নামবে বাংলাদেশের বিরুদ্ধে। তার আগে দলের সঙ্গে যোগ দিলেন আইপিএল জয়ী কেকেআর দলের সদস্য রিঙ্কু সিংহ। গত ২৬ মে সানরাইজার্স হায়দরাবাদের বিরুদ্ধে ফাইনালে জয় ছিনিয়ে নিয়েছিল কলকাতা নাইট রাইডার্স। তৃতীয়বারের জন্য আইপিএল খেতাব জিতে নেয় কেকেআর। ট্রফি হাতে নিয়ে, ট্রফি জড়িয়ে ধরে রিঙ্কুর বিভিন্ন ছবি ভাইরাল হয়েছে সোশ্যাল মিডিয়ায়। তিনি নিজেই বলেছিলেন যে এভাবেই বিশ্বকাপ ট্রফিও জিততে চান। এবার সেই লক্ষ্য নিয়েই নিউ ইয়র্কে পা রাখলেন তরুণ বাঁহাতি এই মিডল অর্ডার ব্যাটার। ১৫ সদস্যের যে ভারতীয় দল টি-টোয়েন্টি বিশ্বকাপের জন্য ঘোষণা করা হয়েছে, তাতে রিঙ্কু নেই। তিনি রিজার্ভ প্লেয়ার হিসেবে দলের সঙ্গে থাকবেন। মূল দলের কোনও প্লেয়ার যদি চোটের কারণে ছিটকে যান, তবেই রিঙ্কুকে অন্তর্ভূক্ত করা হবে দলে। এক্ষেত্রে কেকেআর তারকার কাছে কিন্তু নেট সেশন ও প্রস্তুতি ম্য়াচ বেশ গুরুত্বপূর্ণ।","content":"ONLY AVAILABLE IN PAID PLANS","pubDate":"2024-05-30 13:34:59","image_url":"https://feeds.abplive.com/onecms/images/uploaded-images/2024/05/30/ffc322542ea30b174b9a0cd9fa34aab41717075883802206_original.jpg","source_id":"abplive","source_priority":10959,"source_url":"http://abplive.com","source_icon":"https://i.bytvi.com/domain_icons/abplive.jpg","language":"bengali","country":["india"],"category":["sports"],"ai_tag":"ONLY AVAILABLE IN PROFESSIONAL AND CORPORATE PLANS","sentiment":"ONLY AVAILABLE IN PROFESSIONAL AND CORPORATE PLANS","sentiment_stats":"ONLY AVAILABLE IN PROFESSIONAL AND CORPORATE PLANS","ai_region":"ONLY AVAILABLE IN CORPORATE PLANS","ai_org":"ONLY AVAILABLE IN CORPORATE PLANS"},{"article_id":"69050ab332dfbc9c68eb1bab64868ec4","title":"இந்திய அணிக்கு ஐசிசி சொன்ன மகிழ்ச்சியான செய்தி","link":"https://tamil.news18.com/sports/cricket-icc-world-cup-t20-team-india-holding-1st-place-in-icc-t20-teams-ranking-1471748.html","keywords":["கிரிக்கெட்"],"creator":null,"video_url":null,"description":"பேட்ஸ்மேன்கள் தரவரிசையில் இந்தியாவின் சூர்ய குமார் யாதவ் 861 புள்ளிகளுடன் முதலிடத்தில் உள்ளார்.","content":"ONLY AVAILABLE IN PAID PLANS","pubDate":"2024-05-30 13:34:38","image_url":"https://images.news18.com/tamil/uploads/2024/05/news-18-images-54-2024-05-f35b0b349a98691fea522107c9f92896-3x2.jpg","source_id":"tamil_news18","source_priority":5991,"source_url":"https://tamil.news18.com","source_icon":"https://i.bytvi.com/domain_icons/tamil_news18.png","language":"tamil","country":["india"],"category":["sports"],"ai_tag":"ONLY AVAILABLE IN PROFESSIONAL AND CORPORATE PLANS","sentiment":"ONLY AVAILABLE IN PROFESSIONAL AND CORPORATE PLANS","sentiment_stats":"ONLY AVAILABLE IN PROFESSIONAL AND CORPORATE PLANS","ai_region":"ONLY AVAILABLE IN CORPORATE PLANS","ai_org":"ONLY AVAILABLE IN CORPORATE PLANS"},{"article_id":"da19e734fca2c3aee36f6a367e986ad2","title":"क्या वर्ल्ड कप देखने के लिए खराब करनी होगी नींद? कब शुरू होंगे मुकाबले","link":"https://hindi.news18.com/cricket/t20-world-cup-2024-when-will-the-matches-start-where-to-watch-free-live-streaming-live-telecast-icc-t20-wc-matches-in-india-8366678.html","keywords":["क्रिकेट"],"creator":["News18 Hindi"],"video_url":null,"description":"टी20 वर्ल्ड कप 2024 का आगाज 2 जून से हो जाएगा. चूंकि इस बार टी20 विश्व कप के मुकाबले अमेरिका और विंडीज में खेले जाएंगे, ऐसे में लोग जानने को उत्सुक हैं कि क्या उन्हें रातों की नींद खराब करनी पड़ेगी? भारत, विंडीज और अमेरिका के समय में काफी अंतर है. विश्व कप में 55 मैच खेले जाएंगे. 20 टीमों को 4 ग्रुप में बांटा गया है. ग्रुप स्टेज में 24 मैच खेले जाएंगे.","content":"ONLY AVAILABLE IN PAID PLANS","pubDate":"2024-05-30 13:34:07","image_url":"https://images.news18.com/ibnkhabar/uploads/2024/05/t20-world-cup-2024-05-27cc2c810b58a770ad3a1fd372cda46a-3x2.jpg","source_id":"hindinews18","source_priority":6509,"source_url":"https://hindi.news18.com","source_icon":null,"language":"hindi","country":["india"],"category":["sports"],"ai_tag":"ONLY AVAILABLE IN PROFESSIONAL AND CORPORATE PLANS","sentiment":"ONLY AVAILABLE IN PROFESSIONAL AND CORPORATE PLANS","sentiment_stats":"ONLY AVAILABLE IN PROFESSIONAL AND CORPORATE PLANS","ai_region":"ONLY AVAILABLE IN CORPORATE PLANS","ai_org":"ONLY AVAILABLE IN CORPORATE PLANS"},{"article_id":"1525bc826ab13a4501dcd314c56104d9","title":"Youll Have to Take Me...: Riyan Parag Confident of Playing For India in Future","link":"https://www.news18.com/videos/cricket/riyan-parag-rajasthan-royals-ipl-2024-india-future-8910588.html","keywords":["cricket"],"creator":null,"video_url":null,"description":"Rajasthan Royals star Riyan Parag said he has the belief that someday he will be a part of the senior Indian men’s team.","content":"ONLY AVAILABLE IN PAID PLANS","pubDate":"2024-05-30 13:32:11","image_url":"https://images.news18.com/ibnlive/uploads/2024/05/whatsapp-image-2024-05-30-at-17.52.07_bbdcdee2-2024-05-f1fac8d63503ced5ebcdeb52d6fe7d73-3x2.jpg","source_id":"news18","source_priority":6644,"source_url":"https://www.news18.com","source_icon":"https://i.bytvi.com/domain_icons/news18.png","language":"english","country":["india"],"category":["sports"],"ai_tag":"ONLY AVAILABLE IN PROFESSIONAL AND CORPORATE PLANS","sentiment":"ONLY AVAILABLE IN PROFESSIONAL AND CORPORATE PLANS","sentiment_stats":"ONLY AVAILABLE IN PROFESSIONAL AND CORPORATE PLANS","ai_region":"ONLY AVAILABLE IN CORPORATE PLANS","ai_org":"ONLY AVAILABLE IN CORPORATE PLANS"},{"article_id":"15bb6c1ac6553a3c0f5fc5086b15a075","title":"Sir Vivian Richards Stadium","link":"https://www.indiatoday.in/sports/t20-world-cup-2024/story/west-indies-venue-sir-vivian-richards-stadium-north-sound-antigua-fixtures-full-details-2545828-2024-05-30?utm_source=rss","keywords":null,"creator":null,"video_url":null,"description":"Sir Vivian Richards Stadium","content":"ONLY AVAILABLE IN PAID PLANS","pubDate":"2024-05-30 13:28:39","image_url":"https://akm-img-a-in.tosshub.com/indiatoday/images/story/202405/sir-vivian-richards-stadium-300907999-16x9_0.jpg?VersionId=9xhlmmBCL5WRsOwMpoaqQ_CZyZJIo2r0","source_id":"indiatoday","source_priority":2885,"source_url":"https://www.indiatoday.in","source_icon":"https://i.bytvi.com/domain_icons/indiatoday.png","language":"english","country":["india"],"category":["sports"],"ai_tag":"ONLY AVAILABLE IN PROFESSIONAL AND CORPORATE PLANS","sentiment":"ONLY AVAILABLE IN PROFESSIONAL AND CORPORATE PLANS","sentiment_stats":"ONLY AVAILABLE IN PROFESSIONAL AND CORPORATE PLANS","ai_region":"ONLY AVAILABLE IN CORPORATE PLANS","ai_org":"ONLY AVAILABLE IN CORPORATE PLANS"},{"article_id":"0635b67c31b72475f9fb448c2ef086b8","title":"Jio Cinema पर आईपीएल की दर्शक संख्या में 53 प्रतिशत का उछाल","link":"https://www.prabhasakshi.com/cricket/53-percent-jump-in-ipl-viewership-on-jio-cinema","keywords":null,"creator":["प्रभासाक्षी न्यूज नेटवर्क"],"video_url":null,"description":"रिलायंस के स्वामित्व वाले ओटीटी मंच जियो सिनेमा पर आईपीएल टूर्नामेंट के मुकाबले देखने वाले दर्शकों की कुल संख्या 53 प्रतिशत उछलकर 2,600 करोड़ हो गई। टाटा आईपीएल मैचों के डिजिटल प्रसारण का अधिकार जियो सिनेमा के पास है। दो महीने तक चला यह टूर्नामेंट 26 मई को समाप्त हुआ है। जियो सिनेमा ने एक बयान में कहा कि आईपीएल के इस सत्र में रिकॉर्ड 35,000 करोड़ मिनट ‘वॉच-टाइम’ दर्ज किया गया है। इस दौरान प्रति दर्शक औसत समय पिछले सत्र के 60 मिनट से बढ़कर 75 मिनट तक पहुंच गया। जियो सिनेमा ने कहा, “पहले मैच में अभूतपूर्व दर्शक संख्या मिलने के बाद इसे आगे भी कायम रखते हुए लगभग 38 प्रतिशत वृद्धि हुई। सत्र का समापन लगभग 62 करोड़ दर्शक संख्या के साथ हुआ।”इस सत्र में जियो सिनेमा के पास रिकॉर्ड 28 प्रायोजक और 1,400 से ज्यादा विज्ञापनदाता थे।रिलायंस-समर्थित वायकॉम18 ने जून, 2022 में 20,500 करोड़ रुपये मेंआईपीएल के डिजिटल प्रसारण अधिकार हासिल किए थे। भारतीय उपमहाद्वीप के लिए टेलीविजन प्रसारण अधिकार डिज्नी स्टार के पास हैं। इसका आंकड़ा अभी नहीं आया है।","content":"ONLY AVAILABLE IN PAID PLANS","pubDate":"2024-05-30 13:27:00","image_url":"https://images.prabhasakshi.com/2024/5/30/jio-cinema_large_1857_153.webp","source_id":"prabhasakshi","source_priority":4167978,"source_url":"https://www.prabhasakshi.com","source_icon":"https://i.bytvi.com/domain_icons/prabhasakshi.png","language":"hindi","country":["india"],"category":["sports"],"ai_tag":"ONLY AVAILABLE IN PROFESSIONAL AND CORPORATE PLANS","sentiment":"ONLY AVAILABLE IN PROFESSIONAL AND CORPORATE PLANS","sentiment_stats":"ONLY AVAILABLE IN PROFESSIONAL AND CORPORATE PLANS","ai_region":"ONLY AVAILABLE IN CORPORATE PLANS","ai_org":"ONLY AVAILABLE IN CORPORATE PLANS"},{"article_id":"23906a17491df5aaa3e91258bcf6aa17","title":"At Hardik's wedding, this cricketer took on the role of performing Natasa Stankovic's kanyadaan","link":"https://www.dnaindia.com/cricket/report-at-hardik-wedding-this-cricketer-took-on-the-role-of-performing-natasa-stankovic-kanyadaan-3091284","keywords":["sports","cricket"],"creator":["Chankesh Rao"],"video_url":null,"description":"Serbian model Natasa and Pandya tied the knot in Udaipur in 2023. They had a wedding that combined Hindu and Christian traditions.","content":"ONLY AVAILABLE IN PAID PLANS","pubDate":"2024-05-30 13:25:00","image_url":"https://cdn.dnaindia.com/sites/default/files/styles/third/public/2024/05/30/2636265-untitled-design-69.jpg","source_id":"dnaindia","source_priority":18388,"source_url":"https://www.dnaindia.com","source_icon":null,"language":"english","country":["india"],"category":["sports"],"ai_tag":"ONLY AVAILABLE IN PROFESSIONAL AND CORPORATE PLANS","sentiment":"ONLY AVAILABLE IN PROFESSIONAL AND CORPORATE PLANS","sentiment_stats":"ONLY AVAILABLE IN PROFESSIONAL AND CORPORATE PLANS","ai_region":"ONLY AVAILABLE IN CORPORATE PLANS","ai_org":"ONLY AVAILABLE IN CORPORATE PLANS"},{"article_id":"6e233ffad5a97db48ea3dce8ba718246","title":"Five top Batters with most runs in T20 World Cup","link":"https://www.cricketcountry.com/hi/photos/five-top-batters-with-most-runs-in-t20-world-cup-1154293/","keywords":null,"creator":["Akhilesh Tripathi"],"video_url":null,"description":"टी-20 विश्व कप में सबसे ज्यादा रन बनाने का रिकॉर्ड भारतीय खिलाड़ी विराट कोहली के नाम है. सर्वाधिक रन बनाने वाले बल्लेबाजों की लिस्ट में टॉप-5 में कोहली के अलावा रोहित शर्मा भी शामिल हैं. The post Five top Batters with most runs in T20 World Cup appeared first on Cricket Country.","content":"ONLY AVAILABLE IN PAID PLANS","pubDate":"2024-05-30 13:20:32","image_url":"https://www.cricketcountry.com/wp-content/uploads/2024/05/Virat-Kohli-29-1024x576.jpg","source_id":"cricketcountry","source_priority":104348,"source_url":"https://www.cricketcountry.com","source_icon":"https://i.bytvi.com/domain_icons/cricketcountry.jpg","language":"english","country":["india"],"category":["sports"],"ai_tag":"ONLY AVAILABLE IN PROFESSIONAL AND CORPORATE PLANS","sentiment":"ONLY AVAILABLE IN PROFESSIONAL AND CORPORATE PLANS","sentiment_stats":"ONLY AVAILABLE IN PROFESSIONAL AND CORPORATE PLANS","ai_region":"ONLY AVAILABLE IN CORPORATE PLANS","ai_org":"ONLY AVAILABLE IN CORPORATE PLANS"},{"article_id":"97250519d26dfaaa38bcafc650196e9b","title":"ICC Rankings: यशस्वी जायसवाल को बड़ा फायदा, टी20 वर्ल्ड कप से पहले आईसीसी रैंकिंग में छठे पायदान पर पहुंचे","link":"https://www.prabhasakshi.com/cricket/icc-rankings-yashasvi-jaiswal-spot-in-no-6-ahead-of-t20-world-cup-know-all-detalis","keywords":null,"creator":["प्रभासाक्षी न्यूज नेटवर्क"],"video_url":null,"description":"टी20 वर्ल्ड कप की मेजबानी के लिए अमेरिका और वेस्टइंडीज तैयार है। इस टूर्नामेंट का आगाज 2 जून से हो रहा है। वहीं, रोहित शर्मा की अगुवाई वाली भारतीय टीम अपने वर्ल्ड कप अभियान की शुरुआत आयरलैंड के खिलाफ 5 जून को करेगी। इसके बाद भारत और पाकिस्तान की टीमें 9 जून को आमने-सामने होगी। बहरहाल, इस टूर्नामेंट से पहले टीम इंडिया के लिए अच्छी खबर है। दरअसल, भारतीय टीम के ओपनर यशस्वी जायसवाल ने आईसीसी रैंकिंग्स में बड़ी छलांग लगाई है। यशस्वी आईसीसी टी20 रैंकिंग्स में छठे पायदान पर पहुंच गए हैं। हालांकि, भारतीय टीम के दिग्गज बल्लेबाज सूर्यकुमार यादव पहले नंबर पर बने हुए हैं। इसके अलावा ऑस्ट्रेलिया के ओपनर ट्रेविस हेड को आईसीसी रैंकिंग्स में बड़ा फायदा मिला है। दरअसल, ट्रेविस हेड रैंकिंग में 16वें नंबर पर काबिज हैं। साथ ही वेस्टइंडीज के जॉनसन चार्ल्स और ऑस्ट्रेलिया के टिम डेविड की रैंकिंग में सुधा हुआ है। भारतीय टीम के ताबड़तोड़ फिनिशर रिंकू सिंह और आईसीसी टी20 रैंकिंग्स में 32वें नंबर पर काबिज है। वहीं आईसीसी टी20 रैंकिंग्स में भारतीय टीम पहले नंबर काबिज है। इसे अलावा ऑस्ट्रेलिया 257 रेटिंग प्वाइंट्स के साथ दूसरे स्थान पर है। टीम इंडिया के 264 रेटिंग प्वाइंट्स हैं। इस तरह भारत और ऑस्ट्रेलिया के 7 रेटिंग प्वॉइंट्स का अंतर है।","content":"ONLY AVAILABLE IN PAID PLANS","pubDate":"2024-05-30 13:36:00","image_url":"https://images.prabhasakshi.com/2024/5/30/yashasvi-jaiswal_large_1906_150.webp","source_id":"prabhasakshi","source_priority":4167978,"source_url":"https://www.prabhasakshi.com","source_icon":"https://i.bytvi.com/domain_icons/prabhasakshi.png","language":"hindi","country":["india"],"category":["sports"],"ai_tag":"ONLY AVAILABLE IN PROFESSIONAL AND CORPORATE PLANS","sentiment":"ONLY AVAILABLE IN PROFESSIONAL AND CORPORATE PLANS","sentiment_stats":"ONLY AVAILABLE IN PROFESSIONAL AND CORPORATE PLANS","ai_region":"ONLY AVAILABLE IN CORPORATE PLANS","ai_org":"ONLY AVAILABLE IN CORPORATE PLANS"},{"article_id":"b2a6cbb1273ff857080a4199e0d227ed","title":"T20 World Cup 2024: अमेरिका ही क्यों? नहीं मिला कोई और देश; टी20 वर्ल्ड कप का फ्यूचर दांव पर","link":"https://www.abplive.com/sports/cricket/why-usa-t20-world-cup-2024-host-united-states-of-america-with-west-indies-know-full-reason-2702732","keywords":["क्रिकेट"],"creator":["नीरज शर्मा"],"video_url":null,"description":"T20 World Cup 2024: कुछ साल पहले तक किसी ने सुना भी नहीं था कि यूएसए की भी क्रिकेट टीम है. फिर 2021 में इंटरनेशनल क्रिकेट काउंसिल (ICC) ने बताया कि 2024 का वर्ल्ड कप यूएसए और वेस्टइंडीज में खेला जाएगा. वेस्टइंडीज पहले से क्रिकेट में एक जाना-माना नाम है, लेकिन पिछले 3 साल के अंदर यूएसए के अंदर विश्व स्तरीय मैदान बनाए गए हैं. आगामी वर्ल्ड कप की शुरुआत 2 जून से होगी, जिसमें 20 टीम भाग लेंगी. चूंकि अमेरिका में क्रिकेट ज्यादा फेमस नहीं है, इसलिए सवाल उठता है कि आखिर आईसीसी ने यहां वर्ल्ड कप जैसा बड़ा टूर्नामेंट करवाने का फैसला क्यों लिया है.प्रयोग के तौर पर यूएसए का हुआ है चयन!चूंकि यूएसए में क्रिकेट फैंस की संख्या बहुत कम है, इसलिए मैदानों में सीटें भरना स्टेडियम के मैनेजमेंट के लिए बहुत जटिल काम हो सकता है. विशेष रूप से छोटी टीमों के मैचों में क्राउड कैसे बटोरा जाएगा. इसी समस्या से निजात पाने के लिए केवल 16 मैचों को यूएसए में करवाने का फैसला लिया गया. टूर्नामेंट में कुल 20 टीम हैं, जिनके बीच फाइनल तक 55 मुकाबले खेले जाएंगे. इनमें से 16 मैच यूएसए और बाकी 39 मुकाबले वेस्टइंडीज में खेले जाएंगे, जहां क्रिकेट पहले ही फेमस है.ओलंपिक में हो रही है क्रिकेट की वापसीकुछ समय पहले घोषणा की गई थी कि 2028 ओलंपिक्स में क्रिकेट को वापस लाया जा रहा है. तो भला 2028 ओलंपिक्स में क्रिकेट की वापसी से टी20 वर्ल्ड कप 2024 को यूएसए में करवाने का क्या मेल? बता दें कि 2028 के ओलंपिक खेल अमेरिका के लॉस एंजेलिस में होने हैं और तब तक आईसीसी, क्रिकेट के खेल को यूएस के अंदर प्रमोट करने का हर संभव प्रयास करेगी.पश्चिमी देशों से अछूता रहा है क्रिकेटक्रिकेट का जन्मदाता इंग्लैंड है और उसके बाद जिन भी देशों पर ब्रिटिश राज रहा, वहां-वहां क्रिकेट के खेल को भी लोकप्रियता रही. आज क्रिकेट एशिया, यूरोप, ऑस्ट्रेलिया और अफ्रीकी महाद्वीप में भी खूब लोकप्रिय बन चुका है. मगर पश्चिमी देशों से क्रिकेट अब भी अछूता रहा है. ऐसे में यूएसए को एक मोहरे के तौर पर इस्तेमाल किया जा सकता है. यदि यूएसए में क्रिकेट अपनी पैठ बनाने में सफल रहा तो मेक्सिको, ब्राजील और अर्जेंटीना जैसे देश भी क्रिकेट में आगे बढ़ने के लिए प्रोत्साहित हो सकते हैं.वर्ल्ड कप के लिए चुने गए यूएसए के 3 मैदानटी20 वर्ल्ड कप 2024 के लिए 9 मैदान चुने गए हैं, जिनमें से 6 कैरेबियाई द्वीपों पर हैं और बाकी तीन यूएसए में हैं. नसाऊ काउंटी स्टेडियम (न्यूयॉर्क), सेंट्रल ब्रोवार्ड पार्क (फ्लॉरिडा) और ग्रैंड प्रेयेर स्टेडियम (टेक्सास), यूएसए के वो तीन मैदान हैं जिनमें वर्ल्ड कप के मैच खेले जाएंगे. टूर्नामेंट का सबसे पहला मैच 1 जून को यूएसए और कनाडा के बीच ग्रैंड प्रेयेर स्टेडियम में खेला जाएगा. वहीं भारतीय टीम अपना पहला मैच न्यूयॉर्क में स्थित नसाऊ स्टेडियम में खेलेगी.यह भी पढ़ें:टी20 वर्ल्ड कप से पहले नेपाल टीम पर आया संकट, जमकर हुआ था हंगामा; फिर भी संदीप लामिछाने को नहीं मिला वीजा","content":"ONLY AVAILABLE IN PAID PLANS","pubDate":"2024-05-30 13:35:04","image_url":"https://feeds.abplive.com/onecms/images/uploaded-images/2024/05/30/472d76c7e44bd8307a8db06fe05d9b3c1717075952340975_original.jpg","source_id":"abplive","source_priority":10959,"source_url":"http://abplive.com","source_icon":"https://i.bytvi.com/domain_icons/abplive.jpg","language":"hindi","country":["india"],"category":["sports"],"ai_tag":"ONLY AVAILABLE IN PROFESSIONAL AND CORPORATE PLANS","sentiment":"ONLY AVAILABLE IN PROFESSIONAL AND CORPORATE PLANS","sentiment_stats":"ONLY AVAILABLE IN PROFESSIONAL AND CORPORATE PLANS","ai_region":"ONLY AVAILABLE IN CORPORATE PLANS","ai_org":"ONLY AVAILABLE IN CORPORATE PLANS"},{"article_id":"6c5439095e5ecbba9f439f1543a755e0","title":"T20 World Cup: নিউ ইয়র্কে ভারতীয় শিবিরে যোগ দিলেন রিঙ্কু, কথা রাখতে পারবেন তো নাইট তারকা?","link":"https://bengali.abplive.com/sports/cricket/t20-world-cup-2024-ipl-winner-rinku-singh-links-up-with-indian-squad-in-new-york-1070695","keywords":["ক্রিকেট"],"creator":["ABP Ananda"],"video_url":null,"description":"নিউ ইয়র্ক: টি-টোয়েন্টি বিশ্বকাপের দামামা বেজে গিয়েছে। সব দলই পৌঁছে গিয়েছে প্রায়। ওয়ার্ম আপ ম্য়াচও খেলা হচ্ছে। ভারতীয় দলও আগামী ১ জুন নিজেদের একমাত্র ওয়ার্ম আপ ম্য়াচ খেলতে নামবে বাংলাদেশের বিরুদ্ধে। তার আগে দলের সঙ্গে যোগ দিলেন আইপিএল জয়ী কেকেআর দলের সদস্য রিঙ্কু সিংহ। গত ২৬ মে সানরাইজার্স হায়দরাবাদের বিরুদ্ধে ফাইনালে জয় ছিনিয়ে নিয়েছিল কলকাতা নাইট রাইডার্স। তৃতীয়বারের জন্য আইপিএল খেতাব জিতে নেয় কেকেআর। ট্রফি হাতে নিয়ে, ট্রফি জড়িয়ে ধরে রিঙ্কুর বিভিন্ন ছবি ভাইরাল হয়েছে সোশ্যাল মিডিয়ায়। তিনি নিজেই বলেছিলেন যে এভাবেই বিশ্বকাপ ট্রফিও জিততে চান। এবার সেই লক্ষ্য নিয়েই নিউ ইয়র্কে পা রাখলেন তরুণ বাঁহাতি এই মিডল অর্ডার ব্যাটার। ১৫ সদস্যের যে ভারতীয় দল টি-টোয়েন্টি বিশ্বকাপের জন্য ঘোষণা করা হয়েছে, তাতে রিঙ্কু নেই। তিনি রিজার্ভ প্লেয়ার হিসেবে দলের সঙ্গে থাকবেন। মূল দলের কোনও প্লেয়ার যদি চোটের কারণে ছিটকে যান, তবেই রিঙ্কুকে অন্তর্ভূক্ত করা হবে দলে। এক্ষেত্রে কেকেআর তারকার কাছে কিন্তু নেট সেশন ও প্রস্তুতি ম্য়াচ বেশ গুরুত্বপূর্ণ।","content":"ONLY AVAILABLE IN PAID PLANS","pubDate":"2024-05-30 13:34:59","image_url":"https://feeds.abplive.com/onecms/images/uploaded-images/2024/05/30/ffc322542ea30b174b9a0cd9fa34aab41717075883802206_original.jpg","source_id":"abplive","source_priority":10959,"source_url":"http://abplive.com","source_icon":"https://i.bytvi.com/domain_icons/abplive.jpg","language":"bengali","country":["india"],"category":["sports"],"ai_tag":"ONLY AVAILABLE IN PROFESSIONAL AND CORPORATE PLANS","sentiment":"ONLY AVAILABLE IN PROFESSIONAL AND CORPORATE PLANS","sentiment_stats":"ONLY AVAILABLE IN PROFESSIONAL AND CORPORATE PLANS","ai_region":"ONLY AVAILABLE IN CORPORATE PLANS","ai_org":"ONLY AVAILABLE IN CORPORATE PLANS"},{"article_id":"69050ab332dfbc9c68eb1bab64868ec4","title":"இந்திய அணிக்கு ஐசிசி சொன்ன மகிழ்ச்சியான செய்தி","link":"https://tamil.news18.com/sports/cricket-icc-world-cup-t20-team-india-holding-1st-place-in-icc-t20-teams-ranking-1471748.html","keywords":["கிரிக்கெட்"],"creator":null,"video_url":null,"description":"பேட்ஸ்மேன்கள் தரவரிசையில் இந்தியாவின் சூர்ய குமார் யாதவ் 861 புள்ளிகளுடன் முதலிடத்தில் உள்ளார்.","content":"ONLY AVAILABLE IN PAID PLANS","pubDate":"2024-05-30 13:34:38","image_url":"https://images.news18.com/tamil/uploads/2024/05/news-18-images-54-2024-05-f35b0b349a98691fea522107c9f92896-3x2.jpg","source_id":"tamil_news18","source_priority":5991,"source_url":"https://tamil.news18.com","source_icon":"https://i.bytvi.com/domain_icons/tamil_news18.png","language":"tamil","country":["india"],"category":["sports"],"ai_tag":"ONLY AVAILABLE IN PROFESSIONAL AND CORPORATE PLANS","sentiment":"ONLY AVAILABLE IN PROFESSIONAL AND CORPORATE PLANS","sentiment_stats":"ONLY AVAILABLE IN PROFESSIONAL AND CORPORATE PLANS","ai_region":"ONLY AVAILABLE IN CORPORATE PLANS","ai_org":"ONLY AVAILABLE IN CORPORATE PLANS"},{"article_id":"da19e734fca2c3aee36f6a367e986ad2","title":"क्या वर्ल्ड कप देखने के लिए खराब करनी होगी नींद? कब शुरू होंगे मुकाबले","link":"https://hindi.news18.com/cricket/t20-world-cup-2024-when-will-the-matches-start-where-to-watch-free-live-streaming-live-telecast-icc-t20-wc-matches-in-india-8366678.html","keywords":["क्रिकेट"],"creator":["News18 Hindi"],"video_url":null,"description":"टी20 वर्ल्ड कप 2024 का आगाज 2 जून से हो जाएगा. चूंकि इस बार टी20 विश्व कप के मुकाबले अमेरिका और विंडीज में खेले जाएंगे, ऐसे में लोग जानने को उत्सुक हैं कि क्या उन्हें रातों की नींद खराब करनी पड़ेगी? भारत, विंडीज और अमेरिका के समय में काफी अंतर है. विश्व कप में 55 मैच खेले जाएंगे. 20 टीमों को 4 ग्रुप में बांटा गया है. ग्रुप स्टेज में 24 मैच खेले जाएंगे.","content":"ONLY AVAILABLE IN PAID PLANS","pubDate":"2024-05-30 13:34:07","image_url":"https://images.news18.com/ibnkhabar/uploads/2024/05/t20-world-cup-2024-05-27cc2c810b58a770ad3a1fd372cda46a-3x2.jpg","source_id":"hindinews18","source_priority":6509,"source_url":"https://hindi.news18.com","source_icon":null,"language":"hindi","country":["india"],"category":["sports"],"ai_tag":"ONLY AVAILABLE IN PROFESSIONAL AND CORPORATE PLANS","sentiment":"ONLY AVAILABLE IN PROFESSIONAL AND CORPORATE PLANS","sentiment_stats":"ONLY AVAILABLE IN PROFESSIONAL AND CORPORATE PLANS","ai_region":"ONLY AVAILABLE IN CORPORATE PLANS","ai_org":"ONLY AVAILABLE IN CORPORATE PLANS"},{"article_id":"1525bc826ab13a4501dcd314c56104d9","title":"Youll Have to Take Me...: Riyan Parag Confident of Playing For India in Future","link":"https://www.news18.com/videos/cricket/riyan-parag-rajasthan-royals-ipl-2024-india-future-8910588.html","keywords":["cricket"],"creator":null,"video_url":null,"description":"Rajasthan Royals star Riyan Parag said he has the belief that someday he will be a part of the senior Indian men’s team.","content":"ONLY AVAILABLE IN PAID PLANS","pubDate":"2024-05-30 13:32:11","image_url":"https://images.news18.com/ibnlive/uploads/2024/05/whatsapp-image-2024-05-30-at-17.52.07_bbdcdee2-2024-05-f1fac8d63503ced5ebcdeb52d6fe7d73-3x2.jpg","source_id":"news18","source_priority":6644,"source_url":"https://www.news18.com","source_icon":"https://i.bytvi.com/domain_icons/news18.png","language":"english","country":["india"],"category":["sports"],"ai_tag":"ONLY AVAILABLE IN PROFESSIONAL AND CORPORATE PLANS","sentiment":"ONLY AVAILABLE IN PROFESSIONAL AND CORPORATE PLANS","sentiment_stats":"ONLY AVAILABLE IN PROFESSIONAL AND CORPORATE PLANS","ai_region":"ONLY AVAILABLE IN CORPORATE PLANS","ai_org":"ONLY AVAILABLE IN CORPORATE PLANS"},{"article_id":"15bb6c1ac6553a3c0f5fc5086b15a075","title":"Sir Vivian Richards Stadium","link":"https://www.indiatoday.in/sports/t20-world-cup-2024/story/west-indies-venue-sir-vivian-richards-stadium-north-sound-antigua-fixtures-full-details-2545828-2024-05-30?utm_source=rss","keywords":null,"creator":null,"video_url":null,"description":"Sir Vivian Richards Stadium","content":"ONLY AVAILABLE IN PAID PLANS","pubDate":"2024-05-30 13:28:39","image_url":"https://akm-img-a-in.tosshub.com/indiatoday/images/story/202405/sir-vivian-richards-stadium-300907999-16x9_0.jpg?VersionId=9xhlmmBCL5WRsOwMpoaqQ_CZyZJIo2r0","source_id":"indiatoday","source_priority":2885,"source_url":"https://www.indiatoday.in","source_icon":"https://i.bytvi.com/domain_icons/indiatoday.png","language":"english","country":["india"],"category":["sports"],"ai_tag":"ONLY AVAILABLE IN PROFESSIONAL AND CORPORATE PLANS","sentiment":"ONLY AVAILABLE IN PROFESSIONAL AND CORPORATE PLANS","sentiment_stats":"ONLY AVAILABLE IN PROFESSIONAL AND CORPORATE PLANS","ai_region":"ONLY AVAILABLE IN CORPORATE PLANS","ai_org":"ONLY AVAILABLE IN CORPORATE PLANS"},{"article_id":"0635b67c31b72475f9fb448c2ef086b8","title":"Jio Cinema पर आईपीएल की दर्शक संख्या में 53 प्रतिशत का उछाल","link":"https://www.prabhasakshi.com/cricket/53-percent-jump-in-ipl-viewership-on-jio-cinema","keywords":null,"creator":["प्रभासाक्षी न्यूज नेटवर्क"],"video_url":null,"description":"रिलायंस के स्वामित्व वाले ओटीटी मंच जियो सिनेमा पर आईपीएल टूर्नामेंट के मुकाबले देखने वाले दर्शकों की कुल संख्या 53 प्रतिशत उछलकर 2,600 करोड़ हो गई। टाटा आईपीएल मैचों के डिजिटल प्रसारण का अधिकार जियो सिनेमा के पास है। दो महीने तक चला यह टूर्नामेंट 26 मई को समाप्त हुआ है। जियो सिनेमा ने एक बयान में कहा कि आईपीएल के इस सत्र में रिकॉर्ड 35,000 करोड़ मिनट ‘वॉच-टाइम’ दर्ज किया गया है। इस दौरान प्रति दर्शक औसत समय पिछले सत्र के 60 मिनट से बढ़कर 75 मिनट तक पहुंच गया। जियो सिनेमा ने कहा, “पहले मैच में अभूतपूर्व दर्शक संख्या मिलने के बाद इसे आगे भी कायम रखते हुए लगभग 38 प्रतिशत वृद्धि हुई। सत्र का समापन लगभग 62 करोड़ दर्शक संख्या के साथ हुआ।”इस सत्र में जियो सिनेमा के पास रिकॉर्ड 28 प्रायोजक और 1,400 से ज्यादा विज्ञापनदाता थे।रिलायंस-समर्थित वायकॉम18 ने जून, 2022 में 20,500 करोड़ रुपये मेंआईपीएल के डिजिटल प्रसारण अधिकार हासिल किए थे। भारतीय उपमहाद्वीप के लिए टेलीविजन प्रसारण अधिकार डिज्नी स्टार के पास हैं। इसका आंकड़ा अभी नहीं आया है।","content":"ONLY AVAILABLE IN PAID PLANS","pubDate":"2024-05-30 13:27:00","image_url":"https://images.prabhasakshi.com/2024/5/30/jio-cinema_large_1857_153.webp","source_id":"prabhasakshi","source_priority":4167978,"source_url":"https://www.prabhasakshi.com","source_icon":"https://i.bytvi.com/domain_icons/prabhasakshi.png","language":"hindi","country":["india"],"category":["sports"],"ai_tag":"ONLY AVAILABLE IN PROFESSIONAL AND CORPORATE PLANS","sentiment":"ONLY AVAILABLE IN PROFESSIONAL AND CORPORATE PLANS","sentiment_stats":"ONLY AVAILABLE IN PROFESSIONAL AND CORPORATE PLANS","ai_region":"ONLY AVAILABLE IN CORPORATE PLANS","ai_org":"ONLY AVAILABLE IN CORPORATE PLANS"},{"article_id":"23906a17491df5aaa3e91258bcf6aa17","title":"At Hardik's wedding, this cricketer took on the role of performing Natasa Stankovic's kanyadaan","link":"https://www.dnaindia.com/cricket/report-at-hardik-wedding-this-cricketer-took-on-the-role-of-performing-natasa-stankovic-kanyadaan-3091284","keywords":["sports","cricket"],"creator":["Chankesh Rao"],"video_url":null,"description":"Serbian model Natasa and Pandya tied the knot in Udaipur in 2023. They had a wedding that combined Hindu and Christian traditions.","content":"ONLY AVAILABLE IN PAID PLANS","pubDate":"2024-05-30 13:25:00","image_url":"https://cdn.dnaindia.com/sites/default/files/styles/third/public/2024/05/30/2636265-untitled-design-69.jpg","source_id":"dnaindia","source_priority":18388,"source_url":"https://www.dnaindia.com","source_icon":null,"language":"english","country":["india"],"category":["sports"],"ai_tag":"ONLY AVAILABLE IN PROFESSIONAL AND CORPORATE PLANS","sentiment":"ONLY AVAILABLE IN PROFESSIONAL AND CORPORATE PLANS","sentiment_stats":"ONLY AVAILABLE IN PROFESSIONAL AND CORPORATE PLANS","ai_region":"ONLY AVAILABLE IN CORPORATE PLANS","ai_org":"ONLY AVAILABLE IN CORPORATE PLANS"},{"article_id":"6e233ffad5a97db48ea3dce8ba718246","title":"Five top Batters with most runs in T20 World Cup","link":"https://www.cricketcountry.com/hi/photos/five-top-batters-with-most-runs-in-t20-world-cup-1154293/","keywords":null,"creator":["Akhilesh Tripathi"],"video_url":null,"description":"टी-20 विश्व कप में सबसे ज्यादा रन बनाने का रिकॉर्ड भारतीय खिलाड़ी विराट कोहली के नाम है. सर्वाधिक रन बनाने वाले बल्लेबाजों की लिस्ट में टॉप-5 में कोहली के अलावा रोहित शर्मा भी शामिल हैं. The post Five top Batters with most runs in T20 World Cup appeared first on Cricket Country.","content":"ONLY AVAILABLE IN PAID PLANS","pubDate":"2024-05-30 13:20:32","image_url":"https://www.cricketcountry.com/wp-content/uploads/2024/05/Virat-Kohli-29-1024x576.jpg","source_id":"cricketcountry","source_priority":104348,"source_url":"https://www.cricketcountry.com","source_icon":"https://i.bytvi.com/domain_icons/cricketcountry.jpg","language":"english","country":["india"],"category":["sports"],"ai_tag":"ONLY AVAILABLE IN PROFESSIONAL AND CORPORATE PLANS","sentiment":"ONLY AVAILABLE IN PROFESSIONAL AND CORPORATE PLANS","sentiment_stats":"ONLY AVAILABLE IN PROFESSIONAL AND CORPORATE PLANS","ai_region":"ONLY AVAILABLE IN CORPORATE PLANS","ai_org":"ONLY AVAILABLE IN CORPORATE PLANS"}]}