{"newsArray":[{"article_id":"84e32b9788830b95cdb0846de8c60119","title":"Glenn Maxwell Returns from 'Mental Break', Roars After Dismissing Shubman Gill in Ahmedabad: WATCH","link":"https://www.news18.com/cricket/glenn-maxwell-returns-from-mental-break-roars-after-dismissing-shubman-gill-in-ahmedabad-watch-8869511.html","keywords":["cricket"],"creator":null,"video_url":null,"description":"Glenn Maxwell made an instinctive impact, picking up the prized wicket of GT skipper Shubman Gill to announce his comeback.","content":"ONLY AVAILABLE IN PAID PLANS","pubDate":"2024-04-28 12:11:19","image_url":"https://images.news18.com/ibnlive/uploads/2024/04/glenn-maxwell-announces-his-comeback-after-a-mental-break-2024-04-7ed4f7e210428f7de77643ed6baa365f-3x2.jpg","source_id":"news18","source_priority":6644,"source_url":"https://www.news18.com","source_icon":"https://i.bytvi.com/domain_icons/news18.png","language":"english","country":["india"],"category":["sports"],"ai_tag":"ONLY AVAILABLE IN PROFESSIONAL AND CORPORATE PLANS","sentiment":"ONLY AVAILABLE IN PROFESSIONAL AND CORPORATE PLANS","sentiment_stats":"ONLY AVAILABLE IN PROFESSIONAL AND CORPORATE PLANS","ai_region":"ONLY AVAILABLE IN CORPORATE PLANS"},{"article_id":"11eacd9a14d9592568f649154849cdfb","title":"GT vs RCB: Shahrukh reveals when he got to know about No.4 promoton after blitz","link":"https://www.indiatoday.in/sports/cricket/story/ipl-2024-gt-vs-rcb-shahrukh-khan-no4-ashish-nehra-ahmedabad-2532756-2024-04-28?utm_source=rss","keywords":null,"creator":null,"video_url":null,"description":"GT vs RCB: Shahrukh reveals when he got to know about No.4 promoton after blitz","content":"ONLY AVAILABLE IN PAID PLANS","pubDate":"2024-04-28 12:10:21","image_url":"https://akm-img-a-in.tosshub.com/indiatoday/images/story/202404/shahrukh-khan-280533840-16x9_0.jpg?VersionId=N_rGqP3W9zswRmzEb0zqzh8amdnvKiYm","source_id":"indiatoday","source_priority":2885,"source_url":"https://www.indiatoday.in","source_icon":"https://i.bytvi.com/domain_icons/indiatoday.png","language":"english","country":["india"],"category":["sports"],"ai_tag":"ONLY AVAILABLE IN PROFESSIONAL AND CORPORATE PLANS","sentiment":"ONLY AVAILABLE IN PROFESSIONAL AND CORPORATE PLANS","sentiment_stats":"ONLY AVAILABLE IN PROFESSIONAL AND CORPORATE PLANS","ai_region":"ONLY AVAILABLE IN CORPORATE PLANS"},{"article_id":"4909b6fe9f301fbe334812de5576330c","title":"T20 World Cup 2024 Squad: டி20 உலகக் கோப்பை..சஞ்சு சாம்சன் தான் என்னோட தேர்வு; கெவின் பீட்டர்சன் அதிரடி!","link":"https://tamil.abplive.com/sports/cricket/he-is-one-of-my-first-picks-pietersen-wants-sanju-samson-for-india-s-t20-world-cup-2024-squad-180657","keywords":["கிரிக்கெட்"],"creator":["மு.வா.ஜெகதீஸ் குமார்"],"video_url":null,"description":"இந்திய அணியின் தேர்வாளராக தான் இருந்தால் சஞ்சு சாம்சனை தேர்வு செய்து இருப்பேன் என்று கெவின் பீட்டர்சன் கூறியுள்ளார்.ஐ.பி.எல் 2024:ஐ.பி.எல் சீசன் 17 இந்தியாவில் விறுவிறுப்புடன் நடைபெற்று வருகிறது. இதனைத் தொடர்ந்து ரசிகர்கள் பெரும் எதிர்பார்ப்புடன் காத்திருக்கும் டி20 உலகக் கோப்பை 2024 தொடர் நடைபெற உள்ளது. அதாவது இந்த தொடர் வரும் ஜூன் 1 ஆம் தேதி வெஸ்ட் இண்டீஸ் மற்றும் அமெரிக்காவில் நடைபெறுகிறது. இந்த டி20 உலகக் கோப்பை 2024 தொடரில் இந்திய அணியின் யார் யார் இடம் பெறுவார்கள் என்ற எதிர்பார்ப்பும் நிலவுகிறது. இன்னும் ஒரு சில நாட்களில் டி20 உலகக் கோப்பைக்கான இந்திய வீரர்கள் அறிவிக்கப்படலாம் என்ற தகவல் வெளியாகியுள்ளது.என்னுடைய முதல் தேர்வு:முக்கியமாக இந்திய அணியின் விக்கெட் கீப்பராக தேர்வு செய்யப்படுவதற்கு சஞ்சு சாம்சன், கே.எல்.ராகுல் மற்றும் ரிஷப் பண்ட் ஆகியோரிடம் கடுமையான போட்டி காணப்படுகிறது. அதேபோல் தினேஷ் கார்த்திக் மற்றும் இஷான் கிசனும் இந்த போட்டியில் இருக்கின்றனர். இந்நிலையில் இந்திய அணியின் தேர்வாளராக தான் இருந்தால் சஞ்சு சாம்சனை தேர்வு செய்து இருப்பேன் என்று கெவின் பீட்டர்சன் கூறியுள்ளார்.இது தொடர்பாக இங்கிலாந்து அணியின் முன்னாள் வீரர் கெவின் பீட்டர்சன் பேசுகையில், “இன்னும் சில வாரங்களில் வெஸ்ட் இண்டீஸ் மற்றும் அமெரிக்காவுக்கு செல்லவிருக்கும் இந்திய அணியின் விமானத்தில் அவர் இருக்க வேண்டும் என்பதில் எனக்கு எந்த சந்தேகமும் இல்லை. அவர் ஒரு கேப்டனாக இருந்தும் கௌரவங்கள் வழங்கப்படவில்லை என்ற அழுத்தத்துடன் நிறைய போராடுகிறார். அவர் ரன் எடுக்கும் விதம் மற்றும் பேட்டிங் செய்யும் சூழ்நிலை சிறப்பாக இருக்கிறது. எனவே நான் தேர்வாளராக இருந்தால் டி20 உலக்க கோப்பைக்கான எனது முதல் தேர்வுகளில் அவர் ஒருவராக இருப்பார்” என்று கூறியுள்ளார் கெவின் பீட்டர்சன்.சஞ்சு சாம்சனின் அதிரடி ஆட்டம்:முன்னதாக இந்திய கிரிக்கெட் அணியில் தொடர்ந்து புறக்கணிக்கபடும் வீரராக சஞ்சு சாம்சன் இருக்கிறார். அவருக்கான வாய்ப்பை பிசிசிஐ முறையாக வழங்கவில்லை என்பது தான் கிரிக்கெட் ரசிகர்களின் ஆதங்கம். இச்சூலில் கெவின் பீட்டர்சன் இப்படி கூறியிருப்பது டி20 உலகக் கோப்பையில் சஞ்சு சாம்சனை சேர்க்க வேண்டும் என்று பிசிசிஐ-க்கு அழுத்தம் கொடுப்பதாக அமைந்துள்ளது.சஞ்சு சாம்சன் இந்த ஐபிஎல் சீசனில் தன்னுடைய சிறப்பான ஆட்டத்தை வெளிப்படுத்தி 385 ரன்களை குவித்து இருக்கிறார். அதேபோல், இவர் தலைமையிலான ராஜஸ்தான் ராயல்ஸ் அணி தான் ஐபிஎல் சீசன் 17ன் புள்ளிப்பட்டியலில் முதல் இடத்தில் இருக்கிறது மேலும் ப்ளேஆப் சுற்றுக்கு கிட்டத்தட்ட தேர்வாகி உள்ளது என்பது குறிப்பிடத்தக்கது.மேலும் படிக்க:ICC Men T20 World Cup: விரைவில் வெளியாகவுள்ள டி20 உலகக் கோப்பைக்கான இந்திய அணி.. விக்கெட் கீப்பருக்கு 5 பேர் போட்டியா..?மேலும் படிக்க:Gukesh Chess: உலக செஸ் சாம்பியன்ஷிப் போட்டிக்கு தகுதிபெற்ற குகேஷூக்கு ரூ. 75 லட்சம் ஊக்கத் தொகை - நேரில் வாழ்த்திய முதலமைச்சர்!","content":"ONLY AVAILABLE IN PAID PLANS","pubDate":"2024-04-28 12:09:44","image_url":"https://feeds.abplive.com/onecms/images/uploaded-images/2024/04/28/3b7244af4078154cd8a877df3141762f1714305290686572_original.jpeg","source_id":"abplive","source_priority":10959,"source_url":"http://abplive.com","source_icon":"https://i.bytvi.com/domain_icons/abplive.jpg","language":"tamil","country":["india"],"category":["sports"],"ai_tag":"ONLY AVAILABLE IN PROFESSIONAL AND CORPORATE PLANS","sentiment":"ONLY AVAILABLE IN PROFESSIONAL AND CORPORATE PLANS","sentiment_stats":"ONLY AVAILABLE IN PROFESSIONAL AND CORPORATE PLANS","ai_region":"ONLY AVAILABLE IN CORPORATE PLANS"},{"article_id":"c7c4bfae8fa8746b239a9809bf6e5575","title":"Gambhir seconds Kohli's take on their equation: Don't create hype","link":"https://www.indiatoday.in/sports/cricket/story/ipl-2024-gautam-gambhir-virat-kohli-2532747-2024-04-28?utm_source=rss","keywords":null,"creator":null,"video_url":null,"description":"Gambhir seconds Kohli's take on their equation: Don't create hype","content":"ONLY AVAILABLE IN PAID PLANS","pubDate":"2024-04-28 12:09:39","image_url":"https://akm-img-a-in.tosshub.com/indiatoday/images/story/202404/virat-kohli--gautam-gambhir-200906634-16x9_1.jpg?VersionId=Ry7tbensJglzgKJI92Y_8nbqfPPaNSmn","source_id":"indiatoday","source_priority":2885,"source_url":"https://www.indiatoday.in","source_icon":"https://i.bytvi.com/domain_icons/indiatoday.png","language":"english","country":["india"],"category":["sports"],"ai_tag":"ONLY AVAILABLE IN PROFESSIONAL AND CORPORATE PLANS","sentiment":"ONLY AVAILABLE IN PROFESSIONAL AND CORPORATE PLANS","sentiment_stats":"ONLY AVAILABLE IN PROFESSIONAL AND CORPORATE PLANS","ai_region":"ONLY AVAILABLE IN CORPORATE PLANS"},{"article_id":"7ab17a64b920d65f71db3fb07a13bb83","title":"PCB takes disciplinary action against players after breach in curfew leads to road accident","link":"https://www.indiatvnews.com/sports/cricket/pcb-takes-disciplinary-action-against-women-cricket-team-players-after-breach-in-curfew-leads-to-road-accident-2024-04-28-928431","keywords":null,"creator":null,"video_url":null,"description":"The Pakistan Cricket Board (PCB) confirmed an incident involving senior women's cricket team players getting injured in a car accident earlier this month on Sunday, April 28. PCB Chairman Mohsin Naqvi revealed that a few players breached the camp curfew a few days before the team's recent home series against West Indies and two players suffered intense injuries.","content":"ONLY AVAILABLE IN PAID PLANS","pubDate":"2024-04-28 12:05:52","image_url":"https://resize.indiatvnews.com/en/resize/newbucket/715_-/2024/04/main-2024-04-28t171141-1714304507.jpg","source_id":"indiatvnews","source_priority":10055,"source_url":"https://www.indiatvnews.com","source_icon":"https://i.bytvi.com/domain_icons/indiatvnews.png","language":"english","country":["india"],"category":["sports"],"ai_tag":"ONLY AVAILABLE IN PROFESSIONAL AND CORPORATE PLANS","sentiment":"ONLY AVAILABLE IN PROFESSIONAL AND CORPORATE PLANS","sentiment_stats":"ONLY AVAILABLE IN PROFESSIONAL AND CORPORATE PLANS","ai_region":"ONLY AVAILABLE IN CORPORATE PLANS"},{"article_id":"3c9936af7adaca1a72c4abd55554a996","title":"IND-W vs BAN-W 1st T20I 2024 Innings Update: Shafali Verma, Harmanpreet Kaur, Yastika Bhatia Help India Score 145/7","link":"https://www.latestly.com/socially/sports/cricket/ind-w-vs-ban-w-1st-t20i-2024-innings-update-shafali-verma-harmanpreet-kaur-yastika-bhatia-help-india-score-1457-5926192.html","keywords":null,"creator":null,"video_url":null,"description":"Choosing to bat first at Sylhet International Cricket Stadium in the first T20I match against Bangladesh Women’s side, the Indian Team scored 145 runs. Though no batter reached half century mark, Captain Yashtika Bhatia led the side with 36 runs.","content":"ONLY AVAILABLE IN PAID PLANS","pubDate":"2024-04-28 12:04:37","image_url":"https://st1.latestly.com/wp-content/uploads/2024/01/Harmanpreet-380x214.jpg","source_id":"latestly","source_priority":5523,"source_url":"https://www.latestly.com","source_icon":"https://i.bytvi.com/domain_icons/latestly.png","language":"english","country":["india"],"category":["sports"],"ai_tag":"ONLY AVAILABLE IN PROFESSIONAL AND CORPORATE PLANS","sentiment":"ONLY AVAILABLE IN PROFESSIONAL AND CORPORATE PLANS","sentiment_stats":"ONLY AVAILABLE IN PROFESSIONAL AND CORPORATE PLANS","ai_region":"ONLY AVAILABLE IN CORPORATE PLANS"},{"article_id":"665bab906170d90674f0da5b959ae9c0","title":"PCB Confirms 2 Members of Pakistan's Women's Team Suffer Serious Injuries in Road Accident as Players Breach Curfew","link":"https://www.news18.com/cricket/pcb-confirms-2-members-of-pakistans-womens-team-suffer-serious-injuries-in-road-accident-as-players-breach-curfew-8869521.html","keywords":["cricket"],"creator":null,"video_url":null,"description":"The PCB revealed that certain members of the women's team had broken curfew.","content":"ONLY AVAILABLE IN PAID PLANS","pubDate":"2024-04-28 12:02:28","image_url":"https://images.news18.com/ibnlive/uploads/2023/11/pcb-logo-2023-11-3cf6bd56084cf55474a3257e5286c561-3x2.jpg","source_id":"news18","source_priority":6644,"source_url":"https://www.news18.com","source_icon":"https://i.bytvi.com/domain_icons/news18.png","language":"english","country":["india"],"category":["sports"],"ai_tag":"ONLY AVAILABLE IN PROFESSIONAL AND CORPORATE PLANS","sentiment":"ONLY AVAILABLE IN PROFESSIONAL AND CORPORATE PLANS","sentiment_stats":"ONLY AVAILABLE IN PROFESSIONAL AND CORPORATE PLANS","ai_region":"ONLY AVAILABLE IN CORPORATE PLANS"},{"article_id":"7f2ae47b94b5af66743d11aaae3be76a","title":"DC vs KKR, IPL 2024: Predicted playing XI, live streaming details, weather and pitch report","link":"https://www.dnaindia.com/cricket/report-dc-vs-kkr-ipl-2024-predicted-playing-xi-live-streaming-details-weather-and-pitch-report-3087286","keywords":["sports","cricket"],"creator":["Aditya Bhatia"],"video_url":null,"description":"Check out the live streaming details for match 47 to be played at the Eden Gardens in Kolkata.","content":"ONLY AVAILABLE IN PAID PLANS","pubDate":"2024-04-28 12:02:00","image_url":"https://cdn.dnaindia.com/sites/default/files/styles/third/public/2024/04/28/2633102-untitled-design-7.jpg","source_id":"dnaindia","source_priority":18388,"source_url":"https://www.dnaindia.com","source_icon":null,"language":"english","country":["india"],"category":["sports"],"ai_tag":"ONLY AVAILABLE IN PROFESSIONAL AND CORPORATE PLANS","sentiment":"ONLY AVAILABLE IN PROFESSIONAL AND CORPORATE PLANS","sentiment_stats":"ONLY AVAILABLE IN PROFESSIONAL AND CORPORATE PLANS","ai_region":"ONLY AVAILABLE IN CORPORATE PLANS"},{"article_id":"85b0b97c1371566651901ad7747d557d","title":"Chahal Snubbed By Ex-India Star In T20 WC Squad, Says \"Don't Forget...\"","link":"https://sports.ndtv.com/cricket/yuzvendra-chahal-snubbed-by-ex-india-star-in-t20-world-cup-squad-says-dont-forget-5542339","keywords":null,"creator":null,"video_url":null,"description":"The deadline for the squad submission is May 1 and it has been reported that India captain Rohit Sharma will meet the selectors in the coming days to discuss the squad.","content":"ONLY AVAILABLE IN PAID PLANS","pubDate":"2024-04-28 12:01:36","image_url":"https://c.ndtvimg.com/2024-04/bm9ivlhg_kuldeep-yadav-yuzvendra-chahal-bcci_625x300_19_April_24.jpg","source_id":"ndtv","source_priority":1204,"source_url":"http://www.ndtv.com","source_icon":"https://i.bytvi.com/domain_icons/ndtv.png","language":"english","country":["india"],"category":["sports"],"ai_tag":"ONLY AVAILABLE IN PROFESSIONAL AND CORPORATE PLANS","sentiment":"ONLY AVAILABLE IN PROFESSIONAL AND CORPORATE PLANS","sentiment_stats":"ONLY AVAILABLE IN PROFESSIONAL AND CORPORATE PLANS","ai_region":"ONLY AVAILABLE IN CORPORATE PLANS"},{"article_id":"bc506cf1a2eb78032fe72adca33e8ea5","title":"Fabulous 40: Tarundeep Rai's journey from Asian Games snub to World Cup gold","link":"https://www.hindustantimes.com/sports/others/fabulous-40-tarundeep-rai-s-journey-from-asian-games-snub-to-world-cup-gold-101714305594594.html","keywords":["sports/others"],"creator":null,"video_url":null,"description":"Fabulous 40: Tarundeep Rai's journey from Asian Games snub to World Cup gold","content":"ONLY AVAILABLE IN PAID PLANS","pubDate":"2024-04-28 11:59:54","image_url":"https://images.hindustantimes.com/default/1600x900.jpg","source_id":"hindustantimes","source_priority":933,"source_url":"http://www.hindustantimes.com","source_icon":"https://i.bytvi.com/domain_icons/hindustantimes.png","language":"english","country":["india"],"category":["sports"],"ai_tag":"ONLY AVAILABLE IN PROFESSIONAL AND CORPORATE PLANS","sentiment":"ONLY AVAILABLE IN PROFESSIONAL AND CORPORATE PLANS","sentiment_stats":"ONLY AVAILABLE IN PROFESSIONAL AND CORPORATE PLANS","ai_region":"ONLY AVAILABLE IN CORPORATE PLANS"},{"article_id":"84e32b9788830b95cdb0846de8c60119","title":"Glenn Maxwell Returns from 'Mental Break', Roars After Dismissing Shubman Gill in Ahmedabad: WATCH","link":"https://www.news18.com/cricket/glenn-maxwell-returns-from-mental-break-roars-after-dismissing-shubman-gill-in-ahmedabad-watch-8869511.html","keywords":["cricket"],"creator":null,"video_url":null,"description":"Glenn Maxwell made an instinctive impact, picking up the prized wicket of GT skipper Shubman Gill to announce his comeback.","content":"ONLY AVAILABLE IN PAID PLANS","pubDate":"2024-04-28 12:11:19","image_url":"https://images.news18.com/ibnlive/uploads/2024/04/glenn-maxwell-announces-his-comeback-after-a-mental-break-2024-04-7ed4f7e210428f7de77643ed6baa365f-3x2.jpg","source_id":"news18","source_priority":6644,"source_url":"https://www.news18.com","source_icon":"https://i.bytvi.com/domain_icons/news18.png","language":"english","country":["india"],"category":["sports"],"ai_tag":"ONLY AVAILABLE IN PROFESSIONAL AND CORPORATE PLANS","sentiment":"ONLY AVAILABLE IN PROFESSIONAL AND CORPORATE PLANS","sentiment_stats":"ONLY AVAILABLE IN PROFESSIONAL AND CORPORATE PLANS","ai_region":"ONLY AVAILABLE IN CORPORATE PLANS"},{"article_id":"11eacd9a14d9592568f649154849cdfb","title":"GT vs RCB: Shahrukh reveals when he got to know about No.4 promoton after blitz","link":"https://www.indiatoday.in/sports/cricket/story/ipl-2024-gt-vs-rcb-shahrukh-khan-no4-ashish-nehra-ahmedabad-2532756-2024-04-28?utm_source=rss","keywords":null,"creator":null,"video_url":null,"description":"GT vs RCB: Shahrukh reveals when he got to know about No.4 promoton after blitz","content":"ONLY AVAILABLE IN PAID PLANS","pubDate":"2024-04-28 12:10:21","image_url":"https://akm-img-a-in.tosshub.com/indiatoday/images/story/202404/shahrukh-khan-280533840-16x9_0.jpg?VersionId=N_rGqP3W9zswRmzEb0zqzh8amdnvKiYm","source_id":"indiatoday","source_priority":2885,"source_url":"https://www.indiatoday.in","source_icon":"https://i.bytvi.com/domain_icons/indiatoday.png","language":"english","country":["india"],"category":["sports"],"ai_tag":"ONLY AVAILABLE IN PROFESSIONAL AND CORPORATE PLANS","sentiment":"ONLY AVAILABLE IN PROFESSIONAL AND CORPORATE PLANS","sentiment_stats":"ONLY AVAILABLE IN PROFESSIONAL AND CORPORATE PLANS","ai_region":"ONLY AVAILABLE IN CORPORATE PLANS"},{"article_id":"4909b6fe9f301fbe334812de5576330c","title":"T20 World Cup 2024 Squad: டி20 உலகக் கோப்பை..சஞ்சு சாம்சன் தான் என்னோட தேர்வு; கெவின் பீட்டர்சன் அதிரடி!","link":"https://tamil.abplive.com/sports/cricket/he-is-one-of-my-first-picks-pietersen-wants-sanju-samson-for-india-s-t20-world-cup-2024-squad-180657","keywords":["கிரிக்கெட்"],"creator":["மு.வா.ஜெகதீஸ் குமார்"],"video_url":null,"description":"இந்திய அணியின் தேர்வாளராக தான் இருந்தால் சஞ்சு சாம்சனை தேர்வு செய்து இருப்பேன் என்று கெவின் பீட்டர்சன் கூறியுள்ளார்.ஐ.பி.எல் 2024:ஐ.பி.எல் சீசன் 17 இந்தியாவில் விறுவிறுப்புடன் நடைபெற்று வருகிறது. இதனைத் தொடர்ந்து ரசிகர்கள் பெரும் எதிர்பார்ப்புடன் காத்திருக்கும் டி20 உலகக் கோப்பை 2024 தொடர் நடைபெற உள்ளது. அதாவது இந்த தொடர் வரும் ஜூன் 1 ஆம் தேதி வெஸ்ட் இண்டீஸ் மற்றும் அமெரிக்காவில் நடைபெறுகிறது. இந்த டி20 உலகக் கோப்பை 2024 தொடரில் இந்திய அணியின் யார் யார் இடம் பெறுவார்கள் என்ற எதிர்பார்ப்பும் நிலவுகிறது. இன்னும் ஒரு சில நாட்களில் டி20 உலகக் கோப்பைக்கான இந்திய வீரர்கள் அறிவிக்கப்படலாம் என்ற தகவல் வெளியாகியுள்ளது.என்னுடைய முதல் தேர்வு:முக்கியமாக இந்திய அணியின் விக்கெட் கீப்பராக தேர்வு செய்யப்படுவதற்கு சஞ்சு சாம்சன், கே.எல்.ராகுல் மற்றும் ரிஷப் பண்ட் ஆகியோரிடம் கடுமையான போட்டி காணப்படுகிறது. அதேபோல் தினேஷ் கார்த்திக் மற்றும் இஷான் கிசனும் இந்த போட்டியில் இருக்கின்றனர். இந்நிலையில் இந்திய அணியின் தேர்வாளராக தான் இருந்தால் சஞ்சு சாம்சனை தேர்வு செய்து இருப்பேன் என்று கெவின் பீட்டர்சன் கூறியுள்ளார்.இது தொடர்பாக இங்கிலாந்து அணியின் முன்னாள் வீரர் கெவின் பீட்டர்சன் பேசுகையில், “இன்னும் சில வாரங்களில் வெஸ்ட் இண்டீஸ் மற்றும் அமெரிக்காவுக்கு செல்லவிருக்கும் இந்திய அணியின் விமானத்தில் அவர் இருக்க வேண்டும் என்பதில் எனக்கு எந்த சந்தேகமும் இல்லை. அவர் ஒரு கேப்டனாக இருந்தும் கௌரவங்கள் வழங்கப்படவில்லை என்ற அழுத்தத்துடன் நிறைய போராடுகிறார். அவர் ரன் எடுக்கும் விதம் மற்றும் பேட்டிங் செய்யும் சூழ்நிலை சிறப்பாக இருக்கிறது. எனவே நான் தேர்வாளராக இருந்தால் டி20 உலக்க கோப்பைக்கான எனது முதல் தேர்வுகளில் அவர் ஒருவராக இருப்பார்” என்று கூறியுள்ளார் கெவின் பீட்டர்சன்.சஞ்சு சாம்சனின் அதிரடி ஆட்டம்:முன்னதாக இந்திய கிரிக்கெட் அணியில் தொடர்ந்து புறக்கணிக்கபடும் வீரராக சஞ்சு சாம்சன் இருக்கிறார். அவருக்கான வாய்ப்பை பிசிசிஐ முறையாக வழங்கவில்லை என்பது தான் கிரிக்கெட் ரசிகர்களின் ஆதங்கம். இச்சூலில் கெவின் பீட்டர்சன் இப்படி கூறியிருப்பது டி20 உலகக் கோப்பையில் சஞ்சு சாம்சனை சேர்க்க வேண்டும் என்று பிசிசிஐ-க்கு அழுத்தம் கொடுப்பதாக அமைந்துள்ளது.சஞ்சு சாம்சன் இந்த ஐபிஎல் சீசனில் தன்னுடைய சிறப்பான ஆட்டத்தை வெளிப்படுத்தி 385 ரன்களை குவித்து இருக்கிறார். அதேபோல், இவர் தலைமையிலான ராஜஸ்தான் ராயல்ஸ் அணி தான் ஐபிஎல் சீசன் 17ன் புள்ளிப்பட்டியலில் முதல் இடத்தில் இருக்கிறது மேலும் ப்ளேஆப் சுற்றுக்கு கிட்டத்தட்ட தேர்வாகி உள்ளது என்பது குறிப்பிடத்தக்கது.மேலும் படிக்க:ICC Men T20 World Cup: விரைவில் வெளியாகவுள்ள டி20 உலகக் கோப்பைக்கான இந்திய அணி.. விக்கெட் கீப்பருக்கு 5 பேர் போட்டியா..?மேலும் படிக்க:Gukesh Chess: உலக செஸ் சாம்பியன்ஷிப் போட்டிக்கு தகுதிபெற்ற குகேஷூக்கு ரூ. 75 லட்சம் ஊக்கத் தொகை - நேரில் வாழ்த்திய முதலமைச்சர்!","content":"ONLY AVAILABLE IN PAID PLANS","pubDate":"2024-04-28 12:09:44","image_url":"https://feeds.abplive.com/onecms/images/uploaded-images/2024/04/28/3b7244af4078154cd8a877df3141762f1714305290686572_original.jpeg","source_id":"abplive","source_priority":10959,"source_url":"http://abplive.com","source_icon":"https://i.bytvi.com/domain_icons/abplive.jpg","language":"tamil","country":["india"],"category":["sports"],"ai_tag":"ONLY AVAILABLE IN PROFESSIONAL AND CORPORATE PLANS","sentiment":"ONLY AVAILABLE IN PROFESSIONAL AND CORPORATE PLANS","sentiment_stats":"ONLY AVAILABLE IN PROFESSIONAL AND CORPORATE PLANS","ai_region":"ONLY AVAILABLE IN CORPORATE PLANS"},{"article_id":"c7c4bfae8fa8746b239a9809bf6e5575","title":"Gambhir seconds Kohli's take on their equation: Don't create hype","link":"https://www.indiatoday.in/sports/cricket/story/ipl-2024-gautam-gambhir-virat-kohli-2532747-2024-04-28?utm_source=rss","keywords":null,"creator":null,"video_url":null,"description":"Gambhir seconds Kohli's take on their equation: Don't create hype","content":"ONLY AVAILABLE IN PAID PLANS","pubDate":"2024-04-28 12:09:39","image_url":"https://akm-img-a-in.tosshub.com/indiatoday/images/story/202404/virat-kohli--gautam-gambhir-200906634-16x9_1.jpg?VersionId=Ry7tbensJglzgKJI92Y_8nbqfPPaNSmn","source_id":"indiatoday","source_priority":2885,"source_url":"https://www.indiatoday.in","source_icon":"https://i.bytvi.com/domain_icons/indiatoday.png","language":"english","country":["india"],"category":["sports"],"ai_tag":"ONLY AVAILABLE IN PROFESSIONAL AND CORPORATE PLANS","sentiment":"ONLY AVAILABLE IN PROFESSIONAL AND CORPORATE PLANS","sentiment_stats":"ONLY AVAILABLE IN PROFESSIONAL AND CORPORATE PLANS","ai_region":"ONLY AVAILABLE IN CORPORATE PLANS"},{"article_id":"7ab17a64b920d65f71db3fb07a13bb83","title":"PCB takes disciplinary action against players after breach in curfew leads to road accident","link":"https://www.indiatvnews.com/sports/cricket/pcb-takes-disciplinary-action-against-women-cricket-team-players-after-breach-in-curfew-leads-to-road-accident-2024-04-28-928431","keywords":null,"creator":null,"video_url":null,"description":"The Pakistan Cricket Board (PCB) confirmed an incident involving senior women's cricket team players getting injured in a car accident earlier this month on Sunday, April 28. PCB Chairman Mohsin Naqvi revealed that a few players breached the camp curfew a few days before the team's recent home series against West Indies and two players suffered intense injuries.","content":"ONLY AVAILABLE IN PAID PLANS","pubDate":"2024-04-28 12:05:52","image_url":"https://resize.indiatvnews.com/en/resize/newbucket/715_-/2024/04/main-2024-04-28t171141-1714304507.jpg","source_id":"indiatvnews","source_priority":10055,"source_url":"https://www.indiatvnews.com","source_icon":"https://i.bytvi.com/domain_icons/indiatvnews.png","language":"english","country":["india"],"category":["sports"],"ai_tag":"ONLY AVAILABLE IN PROFESSIONAL AND CORPORATE PLANS","sentiment":"ONLY AVAILABLE IN PROFESSIONAL AND CORPORATE PLANS","sentiment_stats":"ONLY AVAILABLE IN PROFESSIONAL AND CORPORATE PLANS","ai_region":"ONLY AVAILABLE IN CORPORATE PLANS"},{"article_id":"3c9936af7adaca1a72c4abd55554a996","title":"IND-W vs BAN-W 1st T20I 2024 Innings Update: Shafali Verma, Harmanpreet Kaur, Yastika Bhatia Help India Score 145/7","link":"https://www.latestly.com/socially/sports/cricket/ind-w-vs-ban-w-1st-t20i-2024-innings-update-shafali-verma-harmanpreet-kaur-yastika-bhatia-help-india-score-1457-5926192.html","keywords":null,"creator":null,"video_url":null,"description":"Choosing to bat first at Sylhet International Cricket Stadium in the first T20I match against Bangladesh Women’s side, the Indian Team scored 145 runs. Though no batter reached half century mark, Captain Yashtika Bhatia led the side with 36 runs.","content":"ONLY AVAILABLE IN PAID PLANS","pubDate":"2024-04-28 12:04:37","image_url":"https://st1.latestly.com/wp-content/uploads/2024/01/Harmanpreet-380x214.jpg","source_id":"latestly","source_priority":5523,"source_url":"https://www.latestly.com","source_icon":"https://i.bytvi.com/domain_icons/latestly.png","language":"english","country":["india"],"category":["sports"],"ai_tag":"ONLY AVAILABLE IN PROFESSIONAL AND CORPORATE PLANS","sentiment":"ONLY AVAILABLE IN PROFESSIONAL AND CORPORATE PLANS","sentiment_stats":"ONLY AVAILABLE IN PROFESSIONAL AND CORPORATE PLANS","ai_region":"ONLY AVAILABLE IN CORPORATE PLANS"},{"article_id":"665bab906170d90674f0da5b959ae9c0","title":"PCB Confirms 2 Members of Pakistan's Women's Team Suffer Serious Injuries in Road Accident as Players Breach Curfew","link":"https://www.news18.com/cricket/pcb-confirms-2-members-of-pakistans-womens-team-suffer-serious-injuries-in-road-accident-as-players-breach-curfew-8869521.html","keywords":["cricket"],"creator":null,"video_url":null,"description":"The PCB revealed that certain members of the women's team had broken curfew.","content":"ONLY AVAILABLE IN PAID PLANS","pubDate":"2024-04-28 12:02:28","image_url":"https://images.news18.com/ibnlive/uploads/2023/11/pcb-logo-2023-11-3cf6bd56084cf55474a3257e5286c561-3x2.jpg","source_id":"news18","source_priority":6644,"source_url":"https://www.news18.com","source_icon":"https://i.bytvi.com/domain_icons/news18.png","language":"english","country":["india"],"category":["sports"],"ai_tag":"ONLY AVAILABLE IN PROFESSIONAL AND CORPORATE PLANS","sentiment":"ONLY AVAILABLE IN PROFESSIONAL AND CORPORATE PLANS","sentiment_stats":"ONLY AVAILABLE IN PROFESSIONAL AND CORPORATE PLANS","ai_region":"ONLY AVAILABLE IN CORPORATE PLANS"},{"article_id":"7f2ae47b94b5af66743d11aaae3be76a","title":"DC vs KKR, IPL 2024: Predicted playing XI, live streaming details, weather and pitch report","link":"https://www.dnaindia.com/cricket/report-dc-vs-kkr-ipl-2024-predicted-playing-xi-live-streaming-details-weather-and-pitch-report-3087286","keywords":["sports","cricket"],"creator":["Aditya Bhatia"],"video_url":null,"description":"Check out the live streaming details for match 47 to be played at the Eden Gardens in Kolkata.","content":"ONLY AVAILABLE IN PAID PLANS","pubDate":"2024-04-28 12:02:00","image_url":"https://cdn.dnaindia.com/sites/default/files/styles/third/public/2024/04/28/2633102-untitled-design-7.jpg","source_id":"dnaindia","source_priority":18388,"source_url":"https://www.dnaindia.com","source_icon":null,"language":"english","country":["india"],"category":["sports"],"ai_tag":"ONLY AVAILABLE IN PROFESSIONAL AND CORPORATE PLANS","sentiment":"ONLY AVAILABLE IN PROFESSIONAL AND CORPORATE PLANS","sentiment_stats":"ONLY AVAILABLE IN PROFESSIONAL AND CORPORATE PLANS","ai_region":"ONLY AVAILABLE IN CORPORATE PLANS"},{"article_id":"85b0b97c1371566651901ad7747d557d","title":"Chahal Snubbed By Ex-India Star In T20 WC Squad, Says \"Don't Forget...\"","link":"https://sports.ndtv.com/cricket/yuzvendra-chahal-snubbed-by-ex-india-star-in-t20-world-cup-squad-says-dont-forget-5542339","keywords":null,"creator":null,"video_url":null,"description":"The deadline for the squad submission is May 1 and it has been reported that India captain Rohit Sharma will meet the selectors in the coming days to discuss the squad.","content":"ONLY AVAILABLE IN PAID PLANS","pubDate":"2024-04-28 12:01:36","image_url":"https://c.ndtvimg.com/2024-04/bm9ivlhg_kuldeep-yadav-yuzvendra-chahal-bcci_625x300_19_April_24.jpg","source_id":"ndtv","source_priority":1204,"source_url":"http://www.ndtv.com","source_icon":"https://i.bytvi.com/domain_icons/ndtv.png","language":"english","country":["india"],"category":["sports"],"ai_tag":"ONLY AVAILABLE IN PROFESSIONAL AND CORPORATE PLANS","sentiment":"ONLY AVAILABLE IN PROFESSIONAL AND CORPORATE PLANS","sentiment_stats":"ONLY AVAILABLE IN PROFESSIONAL AND CORPORATE PLANS","ai_region":"ONLY AVAILABLE IN CORPORATE PLANS"},{"article_id":"bc506cf1a2eb78032fe72adca33e8ea5","title":"Fabulous 40: Tarundeep Rai's journey from Asian Games snub to World Cup gold","link":"https://www.hindustantimes.com/sports/others/fabulous-40-tarundeep-rai-s-journey-from-asian-games-snub-to-world-cup-gold-101714305594594.html","keywords":["sports/others"],"creator":null,"video_url":null,"description":"Fabulous 40: Tarundeep Rai's journey from Asian Games snub to World Cup gold","content":"ONLY AVAILABLE IN PAID PLANS","pubDate":"2024-04-28 11:59:54","image_url":"https://images.hindustantimes.com/default/1600x900.jpg","source_id":"hindustantimes","source_priority":933,"source_url":"http://www.hindustantimes.com","source_icon":"https://i.bytvi.com/domain_icons/hindustantimes.png","language":"english","country":["india"],"category":["sports"],"ai_tag":"ONLY AVAILABLE IN PROFESSIONAL AND CORPORATE PLANS","sentiment":"ONLY AVAILABLE IN PROFESSIONAL AND CORPORATE PLANS","sentiment_stats":"ONLY AVAILABLE IN PROFESSIONAL AND CORPORATE PLANS","ai_region":"ONLY AVAILABLE IN CORPORATE PLANS"},{"article_id":"84e32b9788830b95cdb0846de8c60119","title":"Glenn Maxwell Returns from 'Mental Break', Roars After Dismissing Shubman Gill in Ahmedabad: WATCH","link":"https://www.news18.com/cricket/glenn-maxwell-returns-from-mental-break-roars-after-dismissing-shubman-gill-in-ahmedabad-watch-8869511.html","keywords":["cricket"],"creator":null,"video_url":null,"description":"Glenn Maxwell made an instinctive impact, picking up the prized wicket of GT skipper Shubman Gill to announce his comeback.","content":"ONLY AVAILABLE IN PAID PLANS","pubDate":"2024-04-28 12:11:19","image_url":"https://images.news18.com/ibnlive/uploads/2024/04/glenn-maxwell-announces-his-comeback-after-a-mental-break-2024-04-7ed4f7e210428f7de77643ed6baa365f-3x2.jpg","source_id":"news18","source_priority":6644,"source_url":"https://www.news18.com","source_icon":"https://i.bytvi.com/domain_icons/news18.png","language":"english","country":["india"],"category":["sports"],"ai_tag":"ONLY AVAILABLE IN PROFESSIONAL AND CORPORATE PLANS","sentiment":"ONLY AVAILABLE IN PROFESSIONAL AND CORPORATE PLANS","sentiment_stats":"ONLY AVAILABLE IN PROFESSIONAL AND CORPORATE PLANS","ai_region":"ONLY AVAILABLE IN CORPORATE PLANS"},{"article_id":"11eacd9a14d9592568f649154849cdfb","title":"GT vs RCB: Shahrukh reveals when he got to know about No.4 promoton after blitz","link":"https://www.indiatoday.in/sports/cricket/story/ipl-2024-gt-vs-rcb-shahrukh-khan-no4-ashish-nehra-ahmedabad-2532756-2024-04-28?utm_source=rss","keywords":null,"creator":null,"video_url":null,"description":"GT vs RCB: Shahrukh reveals when he got to know about No.4 promoton after blitz","content":"ONLY AVAILABLE IN PAID PLANS","pubDate":"2024-04-28 12:10:21","image_url":"https://akm-img-a-in.tosshub.com/indiatoday/images/story/202404/shahrukh-khan-280533840-16x9_0.jpg?VersionId=N_rGqP3W9zswRmzEb0zqzh8amdnvKiYm","source_id":"indiatoday","source_priority":2885,"source_url":"https://www.indiatoday.in","source_icon":"https://i.bytvi.com/domain_icons/indiatoday.png","language":"english","country":["india"],"category":["sports"],"ai_tag":"ONLY AVAILABLE IN PROFESSIONAL AND CORPORATE PLANS","sentiment":"ONLY AVAILABLE IN PROFESSIONAL AND CORPORATE PLANS","sentiment_stats":"ONLY AVAILABLE IN PROFESSIONAL AND CORPORATE PLANS","ai_region":"ONLY AVAILABLE IN CORPORATE PLANS"},{"article_id":"4909b6fe9f301fbe334812de5576330c","title":"T20 World Cup 2024 Squad: டி20 உலகக் கோப்பை..சஞ்சு சாம்சன் தான் என்னோட தேர்வு; கெவின் பீட்டர்சன் அதிரடி!","link":"https://tamil.abplive.com/sports/cricket/he-is-one-of-my-first-picks-pietersen-wants-sanju-samson-for-india-s-t20-world-cup-2024-squad-180657","keywords":["கிரிக்கெட்"],"creator":["மு.வா.ஜெகதீஸ் குமார்"],"video_url":null,"description":"இந்திய அணியின் தேர்வாளராக தான் இருந்தால் சஞ்சு சாம்சனை தேர்வு செய்து இருப்பேன் என்று கெவின் பீட்டர்சன் கூறியுள்ளார்.ஐ.பி.எல் 2024:ஐ.பி.எல் சீசன் 17 இந்தியாவில் விறுவிறுப்புடன் நடைபெற்று வருகிறது. இதனைத் தொடர்ந்து ரசிகர்கள் பெரும் எதிர்பார்ப்புடன் காத்திருக்கும் டி20 உலகக் கோப்பை 2024 தொடர் நடைபெற உள்ளது. அதாவது இந்த தொடர் வரும் ஜூன் 1 ஆம் தேதி வெஸ்ட் இண்டீஸ் மற்றும் அமெரிக்காவில் நடைபெறுகிறது. இந்த டி20 உலகக் கோப்பை 2024 தொடரில் இந்திய அணியின் யார் யார் இடம் பெறுவார்கள் என்ற எதிர்பார்ப்பும் நிலவுகிறது. இன்னும் ஒரு சில நாட்களில் டி20 உலகக் கோப்பைக்கான இந்திய வீரர்கள் அறிவிக்கப்படலாம் என்ற தகவல் வெளியாகியுள்ளது.என்னுடைய முதல் தேர்வு:முக்கியமாக இந்திய அணியின் விக்கெட் கீப்பராக தேர்வு செய்யப்படுவதற்கு சஞ்சு சாம்சன், கே.எல்.ராகுல் மற்றும் ரிஷப் பண்ட் ஆகியோரிடம் கடுமையான போட்டி காணப்படுகிறது. அதேபோல் தினேஷ் கார்த்திக் மற்றும் இஷான் கிசனும் இந்த போட்டியில் இருக்கின்றனர். இந்நிலையில் இந்திய அணியின் தேர்வாளராக தான் இருந்தால் சஞ்சு சாம்சனை தேர்வு செய்து இருப்பேன் என்று கெவின் பீட்டர்சன் கூறியுள்ளார்.இது தொடர்பாக இங்கிலாந்து அணியின் முன்னாள் வீரர் கெவின் பீட்டர்சன் பேசுகையில், “இன்னும் சில வாரங்களில் வெஸ்ட் இண்டீஸ் மற்றும் அமெரிக்காவுக்கு செல்லவிருக்கும் இந்திய அணியின் விமானத்தில் அவர் இருக்க வேண்டும் என்பதில் எனக்கு எந்த சந்தேகமும் இல்லை. அவர் ஒரு கேப்டனாக இருந்தும் கௌரவங்கள் வழங்கப்படவில்லை என்ற அழுத்தத்துடன் நிறைய போராடுகிறார். அவர் ரன் எடுக்கும் விதம் மற்றும் பேட்டிங் செய்யும் சூழ்நிலை சிறப்பாக இருக்கிறது. எனவே நான் தேர்வாளராக இருந்தால் டி20 உலக்க கோப்பைக்கான எனது முதல் தேர்வுகளில் அவர் ஒருவராக இருப்பார்” என்று கூறியுள்ளார் கெவின் பீட்டர்சன்.சஞ்சு சாம்சனின் அதிரடி ஆட்டம்:முன்னதாக இந்திய கிரிக்கெட் அணியில் தொடர்ந்து புறக்கணிக்கபடும் வீரராக சஞ்சு சாம்சன் இருக்கிறார். அவருக்கான வாய்ப்பை பிசிசிஐ முறையாக வழங்கவில்லை என்பது தான் கிரிக்கெட் ரசிகர்களின் ஆதங்கம். இச்சூலில் கெவின் பீட்டர்சன் இப்படி கூறியிருப்பது டி20 உலகக் கோப்பையில் சஞ்சு சாம்சனை சேர்க்க வேண்டும் என்று பிசிசிஐ-க்கு அழுத்தம் கொடுப்பதாக அமைந்துள்ளது.சஞ்சு சாம்சன் இந்த ஐபிஎல் சீசனில் தன்னுடைய சிறப்பான ஆட்டத்தை வெளிப்படுத்தி 385 ரன்களை குவித்து இருக்கிறார். அதேபோல், இவர் தலைமையிலான ராஜஸ்தான் ராயல்ஸ் அணி தான் ஐபிஎல் சீசன் 17ன் புள்ளிப்பட்டியலில் முதல் இடத்தில் இருக்கிறது மேலும் ப்ளேஆப் சுற்றுக்கு கிட்டத்தட்ட தேர்வாகி உள்ளது என்பது குறிப்பிடத்தக்கது.மேலும் படிக்க:ICC Men T20 World Cup: விரைவில் வெளியாகவுள்ள டி20 உலகக் கோப்பைக்கான இந்திய அணி.. விக்கெட் கீப்பருக்கு 5 பேர் போட்டியா..?மேலும் படிக்க:Gukesh Chess: உலக செஸ் சாம்பியன்ஷிப் போட்டிக்கு தகுதிபெற்ற குகேஷூக்கு ரூ. 75 லட்சம் ஊக்கத் தொகை - நேரில் வாழ்த்திய முதலமைச்சர்!","content":"ONLY AVAILABLE IN PAID PLANS","pubDate":"2024-04-28 12:09:44","image_url":"https://feeds.abplive.com/onecms/images/uploaded-images/2024/04/28/3b7244af4078154cd8a877df3141762f1714305290686572_original.jpeg","source_id":"abplive","source_priority":10959,"source_url":"http://abplive.com","source_icon":"https://i.bytvi.com/domain_icons/abplive.jpg","language":"tamil","country":["india"],"category":["sports"],"ai_tag":"ONLY AVAILABLE IN PROFESSIONAL AND CORPORATE PLANS","sentiment":"ONLY AVAILABLE IN PROFESSIONAL AND CORPORATE PLANS","sentiment_stats":"ONLY AVAILABLE IN PROFESSIONAL AND CORPORATE PLANS","ai_region":"ONLY AVAILABLE IN CORPORATE PLANS"},{"article_id":"c7c4bfae8fa8746b239a9809bf6e5575","title":"Gambhir seconds Kohli's take on their equation: Don't create hype","link":"https://www.indiatoday.in/sports/cricket/story/ipl-2024-gautam-gambhir-virat-kohli-2532747-2024-04-28?utm_source=rss","keywords":null,"creator":null,"video_url":null,"description":"Gambhir seconds Kohli's take on their equation: Don't create hype","content":"ONLY AVAILABLE IN PAID PLANS","pubDate":"2024-04-28 12:09:39","image_url":"https://akm-img-a-in.tosshub.com/indiatoday/images/story/202404/virat-kohli--gautam-gambhir-200906634-16x9_1.jpg?VersionId=Ry7tbensJglzgKJI92Y_8nbqfPPaNSmn","source_id":"indiatoday","source_priority":2885,"source_url":"https://www.indiatoday.in","source_icon":"https://i.bytvi.com/domain_icons/indiatoday.png","language":"english","country":["india"],"category":["sports"],"ai_tag":"ONLY AVAILABLE IN PROFESSIONAL AND CORPORATE PLANS","sentiment":"ONLY AVAILABLE IN PROFESSIONAL AND CORPORATE PLANS","sentiment_stats":"ONLY AVAILABLE IN PROFESSIONAL AND CORPORATE PLANS","ai_region":"ONLY AVAILABLE IN CORPORATE PLANS"},{"article_id":"7ab17a64b920d65f71db3fb07a13bb83","title":"PCB takes disciplinary action against players after breach in curfew leads to road accident","link":"https://www.indiatvnews.com/sports/cricket/pcb-takes-disciplinary-action-against-women-cricket-team-players-after-breach-in-curfew-leads-to-road-accident-2024-04-28-928431","keywords":null,"creator":null,"video_url":null,"description":"The Pakistan Cricket Board (PCB) confirmed an incident involving senior women's cricket team players getting injured in a car accident earlier this month on Sunday, April 28. PCB Chairman Mohsin Naqvi revealed that a few players breached the camp curfew a few days before the team's recent home series against West Indies and two players suffered intense injuries.","content":"ONLY AVAILABLE IN PAID PLANS","pubDate":"2024-04-28 12:05:52","image_url":"https://resize.indiatvnews.com/en/resize/newbucket/715_-/2024/04/main-2024-04-28t171141-1714304507.jpg","source_id":"indiatvnews","source_priority":10055,"source_url":"https://www.indiatvnews.com","source_icon":"https://i.bytvi.com/domain_icons/indiatvnews.png","language":"english","country":["india"],"category":["sports"],"ai_tag":"ONLY AVAILABLE IN PROFESSIONAL AND CORPORATE PLANS","sentiment":"ONLY AVAILABLE IN PROFESSIONAL AND CORPORATE PLANS","sentiment_stats":"ONLY AVAILABLE IN PROFESSIONAL AND CORPORATE PLANS","ai_region":"ONLY AVAILABLE IN CORPORATE PLANS"},{"article_id":"3c9936af7adaca1a72c4abd55554a996","title":"IND-W vs BAN-W 1st T20I 2024 Innings Update: Shafali Verma, Harmanpreet Kaur, Yastika Bhatia Help India Score 145/7","link":"https://www.latestly.com/socially/sports/cricket/ind-w-vs-ban-w-1st-t20i-2024-innings-update-shafali-verma-harmanpreet-kaur-yastika-bhatia-help-india-score-1457-5926192.html","keywords":null,"creator":null,"video_url":null,"description":"Choosing to bat first at Sylhet International Cricket Stadium in the first T20I match against Bangladesh Women’s side, the Indian Team scored 145 runs. Though no batter reached half century mark, Captain Yashtika Bhatia led the side with 36 runs.","content":"ONLY AVAILABLE IN PAID PLANS","pubDate":"2024-04-28 12:04:37","image_url":"https://st1.latestly.com/wp-content/uploads/2024/01/Harmanpreet-380x214.jpg","source_id":"latestly","source_priority":5523,"source_url":"https://www.latestly.com","source_icon":"https://i.bytvi.com/domain_icons/latestly.png","language":"english","country":["india"],"category":["sports"],"ai_tag":"ONLY AVAILABLE IN PROFESSIONAL AND CORPORATE PLANS","sentiment":"ONLY AVAILABLE IN PROFESSIONAL AND CORPORATE PLANS","sentiment_stats":"ONLY AVAILABLE IN PROFESSIONAL AND CORPORATE PLANS","ai_region":"ONLY AVAILABLE IN CORPORATE PLANS"},{"article_id":"665bab906170d90674f0da5b959ae9c0","title":"PCB Confirms 2 Members of Pakistan's Women's Team Suffer Serious Injuries in Road Accident as Players Breach Curfew","link":"https://www.news18.com/cricket/pcb-confirms-2-members-of-pakistans-womens-team-suffer-serious-injuries-in-road-accident-as-players-breach-curfew-8869521.html","keywords":["cricket"],"creator":null,"video_url":null,"description":"The PCB revealed that certain members of the women's team had broken curfew.","content":"ONLY AVAILABLE IN PAID PLANS","pubDate":"2024-04-28 12:02:28","image_url":"https://images.news18.com/ibnlive/uploads/2023/11/pcb-logo-2023-11-3cf6bd56084cf55474a3257e5286c561-3x2.jpg","source_id":"news18","source_priority":6644,"source_url":"https://www.news18.com","source_icon":"https://i.bytvi.com/domain_icons/news18.png","language":"english","country":["india"],"category":["sports"],"ai_tag":"ONLY AVAILABLE IN PROFESSIONAL AND CORPORATE PLANS","sentiment":"ONLY AVAILABLE IN PROFESSIONAL AND CORPORATE PLANS","sentiment_stats":"ONLY AVAILABLE IN PROFESSIONAL AND CORPORATE PLANS","ai_region":"ONLY AVAILABLE IN CORPORATE PLANS"},{"article_id":"7f2ae47b94b5af66743d11aaae3be76a","title":"DC vs KKR, IPL 2024: Predicted playing XI, live streaming details, weather and pitch report","link":"https://www.dnaindia.com/cricket/report-dc-vs-kkr-ipl-2024-predicted-playing-xi-live-streaming-details-weather-and-pitch-report-3087286","keywords":["sports","cricket"],"creator":["Aditya Bhatia"],"video_url":null,"description":"Check out the live streaming details for match 47 to be played at the Eden Gardens in Kolkata.","content":"ONLY AVAILABLE IN PAID PLANS","pubDate":"2024-04-28 12:02:00","image_url":"https://cdn.dnaindia.com/sites/default/files/styles/third/public/2024/04/28/2633102-untitled-design-7.jpg","source_id":"dnaindia","source_priority":18388,"source_url":"https://www.dnaindia.com","source_icon":null,"language":"english","country":["india"],"category":["sports"],"ai_tag":"ONLY AVAILABLE IN PROFESSIONAL AND CORPORATE PLANS","sentiment":"ONLY AVAILABLE IN PROFESSIONAL AND CORPORATE PLANS","sentiment_stats":"ONLY AVAILABLE IN PROFESSIONAL AND CORPORATE PLANS","ai_region":"ONLY AVAILABLE IN CORPORATE PLANS"},{"article_id":"85b0b97c1371566651901ad7747d557d","title":"Chahal Snubbed By Ex-India Star In T20 WC Squad, Says \"Don't Forget...\"","link":"https://sports.ndtv.com/cricket/yuzvendra-chahal-snubbed-by-ex-india-star-in-t20-world-cup-squad-says-dont-forget-5542339","keywords":null,"creator":null,"video_url":null,"description":"The deadline for the squad submission is May 1 and it has been reported that India captain Rohit Sharma will meet the selectors in the coming days to discuss the squad.","content":"ONLY AVAILABLE IN PAID PLANS","pubDate":"2024-04-28 12:01:36","image_url":"https://c.ndtvimg.com/2024-04/bm9ivlhg_kuldeep-yadav-yuzvendra-chahal-bcci_625x300_19_April_24.jpg","source_id":"ndtv","source_priority":1204,"source_url":"http://www.ndtv.com","source_icon":"https://i.bytvi.com/domain_icons/ndtv.png","language":"english","country":["india"],"category":["sports"],"ai_tag":"ONLY AVAILABLE IN PROFESSIONAL AND CORPORATE PLANS","sentiment":"ONLY AVAILABLE IN PROFESSIONAL AND CORPORATE PLANS","sentiment_stats":"ONLY AVAILABLE IN PROFESSIONAL AND CORPORATE PLANS","ai_region":"ONLY AVAILABLE IN CORPORATE PLANS"},{"article_id":"bc506cf1a2eb78032fe72adca33e8ea5","title":"Fabulous 40: Tarundeep Rai's journey from Asian Games snub to World Cup gold","link":"https://www.hindustantimes.com/sports/others/fabulous-40-tarundeep-rai-s-journey-from-asian-games-snub-to-world-cup-gold-101714305594594.html","keywords":["sports/others"],"creator":null,"video_url":null,"description":"Fabulous 40: Tarundeep Rai's journey from Asian Games snub to World Cup gold","content":"ONLY AVAILABLE IN PAID PLANS","pubDate":"2024-04-28 11:59:54","image_url":"https://images.hindustantimes.com/default/1600x900.jpg","source_id":"hindustantimes","source_priority":933,"source_url":"http://www.hindustantimes.com","source_icon":"https://i.bytvi.com/domain_icons/hindustantimes.png","language":"english","country":["india"],"category":["sports"],"ai_tag":"ONLY AVAILABLE IN PROFESSIONAL AND CORPORATE PLANS","sentiment":"ONLY AVAILABLE IN PROFESSIONAL AND CORPORATE PLANS","sentiment_stats":"ONLY AVAILABLE IN PROFESSIONAL AND CORPORATE PLANS","ai_region":"ONLY AVAILABLE IN CORPORATE PLANS"}]}